Workbook

Sheet All_User
A1: NO | B1: NAME | C1: 이름 | D1: email | E1: Business Title | F1: BU | G1: ROLE | H1: Lease_List | I1: Old_List | J1: ADD_data | K1: Ipad_List | L1: TeamsNum | M1: Printer | N1: Monitor | O1: BU | P1: 영업자 구분 | R1: 퇴사정보
A2: 1 | B2: Dong Jun Ahn | C2: 안동준 | D2: dj.ahn@stryker.com | E2: Sales Manager, Neurovascular | F2: Sales and Marketing Job Family Group | G2: Direct Sales | H2: {=IFERROR(INDEX(Lease_List!D:D,MATCH(All_User!D2,Lease_List!H:H,0)),"없음")} -> 없음 | I2: 5CG2181LW7 | K2: {=IFERROR(INDEX(Ipad_List!C:C,MATCH(All_User!D2,Ipad_List!J:J,0)),"없음")} -> QWG7C19T9N | L2: {=IFERROR(INDEX(TeamsNumber!B:B,MATCH(All_User!D2,TeamsNumber!D:D,0)),"없음")} -> tel:+82234517682 | M2: {=IFERROR(INDEX(Printer!D:D,MATCH(All_User!D2,Printer!G:G,0)),"없음")} -> 없음 | N2: {=IFERROR(INDEX(Monitor!A:A,MATCH(D2,Monitor!D:D,0)),"없음")} -> 없음 | O2: {=IFERROR(INDEX(sales!D:D,MATCH(D2,sales!C:C,0)),"없음")} -> NV | P2: {=IFERROR(INDEX(sales!E:E,MATCH(D2,sales!C:C,0)),"없음")} -> NV | Q2: {=IFERROR(INDEX(sales!C:C,MATCH(D2,sales!C:C,0)),"list없음")} -> dj.ahn@stryker.com
A3: 2 | B3: Jiyong Ahn | C3: 안지용 | D3: gd.ahn@stryker.com | E3: Senior Mako Product Specialist | F3: Sales and Marketing Job Family Group | G3: Medical Education | H3: {=IFERROR(INDEX(Lease_List!D:D,MATCH(All_User!D3,Lease_List!H:H,0)),"없음")} -> 5CD4232BFL | I3: 없음 | K3: {=IFERROR(INDEX(Ipad_List!C:C,MATCH(All_User!D3,Ipad_List!J:J,0)),"없음")} -> L69V0Q1VT3 | L3: {=IFERROR(INDEX(TeamsNumber!B:B,MATCH(All_User!D3,TeamsNumber!D:D,0)),"없음")} -> tel:+82234517566 | M3: {=IFERROR(INDEX(Printer!D:D,MATCH(All_User!D3,Printer!H:H,0)),"없음")} -> 확인중 | N3: {=IFERROR(INDEX(Monitor!A:A,MATCH(D3,Monitor!D:D,0)),"없음")} -> 없음 | O3: {=IFERROR(INDEX(sales!D:D,MATCH(D3,sales!C:C,0)),"없음")} -> 0 | P3: {=IFERROR(INDEX(sales!E:E,MATCH(D3,sales!C:C,0)),"없음")} -> 0
A4: 3 | B4: Andrew Ahn | C4: 안별 | D4: andrew.ahn@stryker.com | E4: Senior Field Service Engineer Medical | F4: Customer Services Job Family Group | G4: Technical Customer Support | H4: {=IFERROR(INDEX(Lease_List!D:D,MATCH(All_User!D4,Lease_List!H:H,0)),"없음")} -> 5CD5179KJ6 | I4: 04/13/22 | K4: {=IFERROR(INDEX(Ipad_List!C:C,MATCH(All_User!D4,Ipad_List!J:J,0)),"없음")} -> C4RQH3W74V | L4: {=IFERROR(INDEX(TeamsNumber!B:B,MATCH(All_User!D4,TeamsNumber!D:D,0)),"없음")} -> tel:+82234517512 | M4: {=IFERROR(INDEX(Printer!D:D,MATCH(All_User!D4,Printer!H:H,0)),"없음")} -> 없음 | N4: {=IFERROR(INDEX(Monitor!A:A,MATCH(D4,Monitor!D:D,0)),"없음")} -> 없음 | O4: {=IFERROR(INDEX(sales!D:D,MATCH(D4,sales!C:C,0)),"없음")} -> 0 | P4: {=IFERROR(INDEX(sales!E:E,MATCH(D4,sales!C:C,0)),"없음")} -> TS | Q4: {=IFERROR(INDEX(sales!C:C,MATCH(D4,sales!C:C,0)),"list없음")} -> andrew.ahn@stryker.com
A5: 4 | B5: Ryan Ahn | C5: 안성현 | D5: ryan.ahn@stryker.com | E5: Senior Kit Representative | F5: Supply Chain Job Family Group | G5: Materials | H5: {=IFERROR(INDEX(Lease_List!D:D,MATCH(All_User!D5,Lease_List!H:H,0)),"없음")} -> 5CD442C071 | I5: 없음 | K5: {=IFERROR(INDEX(Ipad_List!C:C,MATCH(All_User!D5,Ipad_List!J:J,0)),"없음")} -> 없음 | L5: {=IFERROR(INDEX(TeamsNumber!B:B,MATCH(All_User!D5,TeamsNumber!D:D,0)),"없음")} -> tel:+82234517594 | M5: {=IFERROR(INDEX(Printer!D:D,MATCH(All_User!D5,Printer!H:H,0)),"없음")} -> 없음 | N5: {=IFERROR(INDEX(Monitor!A:A,MATCH(D5,Monitor!D:D,0)),"없음")} -> 없음 | O5: {=IFERROR(INDEX(sales!D:D,MATCH(D5,sales!C:C,0)),"없음")} -> 없음 | P5: {=IFERROR(INDEX(sales!E:E,MATCH(D5,sales!C:C,0)),"없음")} -> 없음
A6: 5 | B6: Hyeran An | C6: 안혜란 | D6: hyeran.an@stryker.com | E6: Customer Service Specialist | F6: Customer Services Job Family Group | G6: Customer Services | H6: {=IFERROR(INDEX(Lease_List!D:D,MATCH(All_User!D6,Lease_List!H:H,0)),"없음")} -> 5CD4145N3N | I6: 없음 | K6: {=IFERROR(INDEX(Ipad_List!C:C,MATCH(All_User!D6,Ipad_List!J:J,0)),"없음")} -> 없음 | L6: {=IFERROR(INDEX(TeamsNumber!B:B,MATCH(All_User!D6,TeamsNumber!D:D,0)),"없음")} -> tel:+82234517662 | M6: {=IFERROR(INDEX(Printer!D:D,MATCH(All_User!D6,Printer!H:H,0)),"없음")} -> 없음 | N6: {=IFERROR(INDEX(Monitor!A:A,MATCH(D6,Monitor!D:D,0)),"없음")} -> 없음 | O6: {=IFERROR(INDEX(sales!D:D,MATCH(D6,sales!C:C,0)),"없음")} -> 없음 | P6: {=IFERROR(INDEX(sales!E:E,MATCH(D6,sales!C:C,0)),"없음")} -> 없음
A7: 6 | B7: Sophie Bae | C7: 배지현 | D7: sophie.bae@stryker.com | E7: Business Operation Specialist, Neurovascular | F7: Sales and Marketing Job Family Group | G7: Sales Operations | H7: {=IFERROR(INDEX(Lease_List!D:D,MATCH(All_User!D7,Lease_List!H:H,0)),"없음")} -> 5CD3469HD0 | I7: 없음 | K7: {=IFERROR(INDEX(Ipad_List!C:C,MATCH(All_User!D7,Ipad_List!J:J,0)),"없음")} -> 없음 | L7: {=IFERROR(INDEX(TeamsNumber!B:B,MATCH(All_User!D7,TeamsNumber!D:D,0)),"없음")} -> tel:+82234517661 | M7: {=IFERROR(INDEX(Printer!D:D,MATCH(All_User!D7,Printer!H:H,0)),"없음")} -> 없음 | N7: {=IFERROR(INDEX(Monitor!A:A,MATCH(D7,Monitor!D:D,0)),"없음")} -> 없음 | O7: {=IFERROR(INDEX(sales!D:D,MATCH(D7,sales!C:C,0)),"없음")} -> 없음 | P7: {=IFERROR(INDEX(sales!E:E,MATCH(D7,sales!C:C,0)),"없음")} -> 없음
A8: 7 | B8: Vincent Bae | C8: 배성빈 | D8: vincent.bae@stryker.com | E8: Associate Mako Product Specialist | F8: Sales and Marketing Job Family Group | G8: Medical Education | H8: {=IFERROR(INDEX(Lease_List!D:D,MATCH(All_User!D8,Lease_List!H:H,0)),"없음")} -> 5CD5062YDY | I8: 없음 | K8: {=IFERROR(INDEX(Ipad_List!C:C,MATCH(All_User!D8,Ipad_List!J:J,0)),"없음")} -> HL7Q0T6MHW | L8: {=IFERROR(INDEX(TeamsNumber!B:B,MATCH(All_User!D8,TeamsNumber!D:D,0)),"없음")} -> 없음 | M8: {=IFERROR(INDEX(Printer!D:D,MATCH(All_User!D8,Printer!H:H,0)),"없음")} -> 없음 | N8: {=IFERROR(INDEX(Monitor!A:A,MATCH(D8,Monitor!D:D,0)),"없음")} -> 없음 | O8: {=IFERROR(INDEX(sales!D:D,MATCH(D8,sales!C:C,0)),"없음")} -> Mako | P8: {=IFERROR(INDEX(sales!E:E,MATCH(D8,sales!C:C,0)),"없음")} -> MPS | Q8: {=IFERROR(INDEX(sales!C:C,MATCH(D8,sales!C:C,0)),"list없음")} -> vincent.bae@stryker.com
A9: 8 | B9: Chloe Baek | C9: 백경남 | D9: chloe.baek@stryker.com | E9: Lead Specialist, Demand Planning, MedSurg | F9: Supply Chain Job Family Group | G9: Supply Planning | H9: {=IFERROR(INDEX(Lease_List!D:D,MATCH(All_User!D9,Lease_List!H:H,0)),"없음")} -> 5CD3469HDN | I9: 없음 | K9: {=IFERROR(INDEX(Ipad_List!C:C,MATCH(All_User!D9,Ipad_List!J:J,0)),"없음")} -> 없음 | L9: {=IFERROR(INDEX(TeamsNumber!B:B,MATCH(All_User!D9,TeamsNumber!D:D,0)),"없음")} -> tel:+82234517519 | M9: {=IFERROR(INDEX(Printer!D:D,MATCH(All_User!D9,Printer!H:H,0)),"없음")} -> 없음 | N9: {=IFERROR(INDEX(Monitor!A:A,MATCH(D9,Monitor!D:D,0)),"없음")} -> 없음 | O9: {=IFERROR(INDEX(sales!D:D,MATCH(D9,sales!C:C,0)),"없음")} -> 없음 | P9: {=IFERROR(INDEX(sales!E:E,MATCH(D9,sales!C:C,0)),"없음")} -> 없음
A10: 10 | B10: Alicia Bang | C10: 방은영 | D10: alicia.bang@stryker.com | E10: Senior RA Specialist | F10: RAQA Job Family Group | G10: Regulatory Affairs | H10: {=IFERROR(INDEX(Lease_List!D:D,MATCH(All_User!D10,Lease_List!H:H,0)),"없음")} -> 5CG53403D0 | I10: 없음 | K10: {=IFERROR(INDEX(Ipad_List!C:C,MATCH(All_User!D10,Ipad_List!J:J,0)),"없음")} -> 없음 | L10: {=IFERROR(INDEX(TeamsNumber!B:B,MATCH(All_User!D10,TeamsNumber!D:D,0)),"없음")} -> tel:+82234517637 | M10: {=IFERROR(INDEX(Printer!D:D,MATCH(All_User!D10,Printer!H:H,0)),"없음")} -> 없음 | N10: {=IFERROR(INDEX(Monitor!A:A,MATCH(D10,Monitor!D:D,0)),"없음")} -> LCD 모니터 | O10: {=IFERROR(INDEX(sales!D:D,MATCH(D10,sales!C:C,0)),"없음")} -> 없음 | P10: {=IFERROR(INDEX(sales!E:E,MATCH(D10,sales!C:C,0)),"없음")} -> 없음
A11: 11 | B11: Bella Bang | C11: 방선희 | D11: bella.bang@stryker.com | E11: Mako Product Specialist | F11: Sales and Marketing Job Family Group | G11: Medical Education | H11: {=IFERROR(INDEX(Lease_List!D:D,MATCH(All_User!D11,Lease_List!H:H,0)),"없음")} -> 5CD5062YF5 | I11: 없음 | K11: {=IFERROR(INDEX(Ipad_List!C:C,MATCH(All_User!D11,Ipad_List!J:J,0)),"없음")} -> QXKLQ74WYW | L11: {=IFERROR(INDEX(TeamsNumber!B:B,MATCH(All_User!D11,TeamsNumber!D:D,0)),"없음")} -> tel:+82234517568 | M11: {=IFERROR(INDEX(Printer!D:D,MATCH(All_User!D11,Printer!H:H,0)),"없음")} -> 없음 | N11: {=IFERROR(INDEX(Monitor!A:A,MATCH(D11,Monitor!D:D,0)),"없음")} -> 없음 | O11: {=IFERROR(INDEX(sales!D:D,MATCH(D11,sales!C:C,0)),"없음")} -> Mako | P11: {=IFERROR(INDEX(sales!E:E,MATCH(D11,sales!C:C,0)),"없음")} -> MPS | Q11: {=IFERROR(INDEX(sales!C:C,MATCH(D11,sales!C:C,0)),"list없음")} -> bella.bang@stryker.com
A12: 12 | B12: Sung Hoon Bang | C12: 방성훈 | D12: sunghoon.bang@stryker.com | E12: Lead Sales Representative | F12: Sales and Marketing Job Family Group | G12: Indirect Sales | H12: {=IFERROR(INDEX(Lease_List!D:D,MATCH(All_User!D12,Lease_List!H:H,0)),"없음")} -> 5CD4305D85 | I12: 없음 | K12: {=IFERROR(INDEX(Ipad_List!C:C,MATCH(All_User!D12,Ipad_List!J:J,0)),"없음")} -> OQ2GGXF3FK | L12: {=IFERROR(INDEX(TeamsNumber!B:B,MATCH(All_User!D12,TeamsNumber!D:D,0)),"없음")} -> tel:+82234517591 | M12: {=IFERROR(INDEX(Printer!D:D,MATCH(All_User!D12,Printer!H:H,0)),"없음")} -> 없음 | N12: {=IFERROR(INDEX(Monitor!A:A,MATCH(D12,Monitor!D:D,0)),"없음")} -> 없음 | O12: {=IFERROR(INDEX(sales!D:D,MATCH(D12,sales!C:C,0)),"없음")} -> Knee | P12: {=IFERROR(INDEX(sales!E:E,MATCH(D12,sales!C:C,0)),"없음")} -> Sales | Q12: {=IFERROR(INDEX(sales!C:C,MATCH(D12,sales!C:C,0)),"list없음")} -> sunghoon.bang@stryker.com
A13: 13 | B13: Jisoo Byeon | C13: 변지수 | D13: jisoo.byeon@stryker.com | E13: Business Operation Coordinator | F13: Sales and Marketing Job Family Group | G13: Sales Support | H13: {=IFERROR(INDEX(Lease_List!D:D,MATCH(All_User!D13,Lease_List!H:H,0)),"없음")} -> 5CD4232BFF | I13: 없음 | K13: {=IFERROR(INDEX(Ipad_List!C:C,MATCH(All_User!D13,Ipad_List!J:J,0)),"없음")} -> 없음 | L13: {=IFERROR(INDEX(TeamsNumber!B:B,MATCH(All_User!D13,TeamsNumber!D:D,0)),"없음")} -> tel:+82234517513 | M13: {=IFERROR(INDEX(Printer!D:D,MATCH(All_User!D13,Printer!H:H,0)),"없음")} -> 없음 | N13: {=IFERROR(INDEX(Monitor!A:A,MATCH(D13,Monitor!D:D,0)),"없음")} -> 없음 | O13: {=IFERROR(INDEX(sales!D:D,MATCH(D13,sales!C:C,0)),"없음")} -> 없음 | P13: {=IFERROR(INDEX(sales!E:E,MATCH(D13,sales!C:C,0)),"없음")} -> 없음
A14: 14 | B14: Jun Seong Byun | C14: 변준성 | D14: junseong.byun@stryker.com | E14: Mako Product Specialist | F14: Sales and Marketing Job Family Group | G14: Medical Education | H14: {=IFERROR(INDEX(Lease_List!D:D,MATCH(All_User!D14,Lease_List!H:H,0)),"없음")} -> 5CD442C074 | I14: 없음 | K14: {=IFERROR(INDEX(Ipad_List!C:C,MATCH(All_User!D14,Ipad_List!J:J,0)),"없음")} -> R34F5XVT2M | L14: {=IFERROR(INDEX(TeamsNumber!B:B,MATCH(All_User!D14,TeamsNumber!D:D,0)),"없음")} -> tel:+82234517659 | M14: {=IFERROR(INDEX(Printer!D:D,MATCH(All_User!D14,Printer!H:H,0)),"없음")} -> 없음 | N14: {=IFERROR(INDEX(Monitor!A:A,MATCH(D14,Monitor!D:D,0)),"없음")} -> 없음 | O14: {=IFERROR(INDEX(sales!D:D,MATCH(D14,sales!C:C,0)),"없음")} -> Mako | P14: {=IFERROR(INDEX(sales!E:E,MATCH(D14,sales!C:C,0)),"없음")} -> MPS | Q14: {=IFERROR(INDEX(sales!C:C,MATCH(D14,sales!C:C,0)),"list없음")} -> junseong.byun@stryker.com
A15: 15 | B15: Bruce Cha | C15: 차철민 | D15: Bruce.Cha@stryker.com | E15: Mako Account Manager | F15: Sales and Marketing Job Family Group | G15: Medical Education | H15: {=IFERROR(INDEX(Lease_List!D:D,MATCH(All_User!D15,Lease_List!H:H,0)),"없음")} -> 5CD3469HD6 | I15: 없음 | K15: {=IFERROR(INDEX(Ipad_List!C:C,MATCH(All_User!D15,Ipad_List!J:J,0)),"없음")} -> LXDC4F97QM | L15: {=IFERROR(INDEX(TeamsNumber!B:B,MATCH(All_User!D15,TeamsNumber!D:D,0)),"없음")} -> tel:+82234517549 | M15: {=IFERROR(INDEX(Printer!D:D,MATCH(All_User!D15,Printer!H:H,0)),"없음")} -> SL-C563W | N15: {=IFERROR(INDEX(Monitor!A:A,MATCH(D15,Monitor!D:D,0)),"없음")} -> 없음 | O15: {=IFERROR(INDEX(sales!D:D,MATCH(D15,sales!C:C,0)),"없음")} -> Mako | P15: {=IFERROR(INDEX(sales!E:E,MATCH(D15,sales!C:C,0)),"없음")} -> Sales | Q15: {=IFERROR(INDEX(sales!C:C,MATCH(D15,sales!C:C,0)),"list없음")} -> Bruce.Cha@stryker.com
A16: 16 | B16: Carl Cha | C16: 차영훈 | D16: carl.cha@stryker.com | E16: Technical Service Engineer | F16: Customer Services Job Family Group | G16: Technical Customer Support | H16: {=IFERROR(INDEX(Lease_List!D:D,MATCH(All_User!D16,Lease_List!H:H,0)),"없음")} -> 없음 | I16: 없음 | J16: 5CD32871LG | K16: {=IFERROR(INDEX(Ipad_List!C:C,MATCH(All_User!D16,Ipad_List!J:J,0)),"없음")} -> Q4VGFW40QV | L16: {=IFERROR(INDEX(TeamsNumber!B:B,MATCH(All_User!D16,TeamsNumber!D:D,0)),"없음")} -> tel:+82234517668 | M16: {=IFERROR(INDEX(Printer!D:D,MATCH(All_User!D16,Printer!G:G,0)),"없음")} -> 없음 | N16: {=IFERROR(INDEX(Monitor!A:A,MATCH(D16,Monitor!D:D,0)),"없음")} -> 없음 | O16: {=IFERROR(INDEX(sales!D:D,MATCH(D16,sales!C:C,0)),"없음")} -> 0 | P16: {=IFERROR(INDEX(sales!E:E,MATCH(D16,sales!C:C,0)),"없음")} -> TS | Q16: {=IFERROR(INDEX(sales!C:C,MATCH(D16,sales!C:C,0)),"list없음")} -> carl.cha@stryker.com
A18: 18 | B18: Willy Chang | C18: 장훈 | D18: Willy.Chang@stryker.com | E18: Mako Account Manager | F18: Sales and Marketing Job Family Group | G18: Medical Education | H18: {=IFERROR(INDEX(Lease_List!D:D,MATCH(All_User!D18,Lease_List!H:H,0)),"없음")} -> 5CD5179KHY | I18: 5CG2181LVJ | K18: {=IFERROR(INDEX(Ipad_List!C:C,MATCH(All_User!D18,Ipad_List!J:J,0)),"없음")} -> Q4VMC2579N | L18: {=IFERROR(INDEX(TeamsNumber!B:B,MATCH(All_User!D18,TeamsNumber!D:D,0)),"없음")} -> tel:+82234517557 | M18: {=IFERROR(INDEX(Printer!D:D,MATCH(All_User!D18,Printer!H:H,0)),"없음")} -> SL-C565FW | N18: {=IFERROR(INDEX(Monitor!A:A,MATCH(D18,Monitor!D:D,0)),"없음")} -> 없음 | O18: {=IFERROR(INDEX(sales!D:D,MATCH(D18,sales!C:C,0)),"없음")} -> Mako | P18: {=IFERROR(INDEX(sales!E:E,MATCH(D18,sales!C:C,0)),"없음")} -> Sales | Q18: {=IFERROR(INDEX(sales!C:C,MATCH(D18,sales!C:C,0)),"list없음")} -> Willy.Chang@stryker.com
A19: 19 | B19: Heesun Cho | C19: 조희선 | D19: heesun.cho@stryker.com | E19: Finance Director, Korea | F19: Finance Job Family Group | G19: Finance | H19: {=IFERROR(INDEX(Lease_List!D:D,MATCH(All_User!D19,Lease_List!H:H,0)),"없음")} -> 5CD442C07H | I19: 없음 | K19: {=IFERROR(INDEX(Ipad_List!C:C,MATCH(All_User!D19,Ipad_List!J:J,0)),"없음")} -> DLXCC0M0KC43 | L19: {=IFERROR(INDEX(TeamsNumber!B:B,MATCH(All_User!D19,TeamsNumber!D:D,0)),"없음")} -> tel:+82234517644 | M19: {=IFERROR(INDEX(Printer!D:D,MATCH(All_User!D19,Printer!H:H,0)),"없음")} -> 없음 | N19: {=IFERROR(INDEX(Monitor!A:A,MATCH(D19,Monitor!D:D,0)),"없음")} -> LCD 모니터 | O19: {=IFERROR(INDEX(sales!D:D,MATCH(D19,sales!C:C,0)),"없음")} -> 없음 | P19: {=IFERROR(INDEX(sales!E:E,MATCH(D19,sales!C:C,0)),"없음")} -> 없음
A20: 20 | B20: Martin Cho | C20: 조명수 | D20: martin.cho@stryker.com | E20: Sales Representative, MedSurg, Korea | F20: Sales and Marketing Job Family Group | G20: Indirect Sales | H20: {=IFERROR(INDEX(Lease_List!D:D,MATCH(All_User!D20,Lease_List!H:H,0)),"없음")} -> 5CD5179KHG | I20: 5CG2181LW1 | K20: {=IFERROR(INDEX(Ipad_List!C:C,MATCH(All_User!D20,Ipad_List!J:J,0)),"없음")} -> L2Q9F70301 | L20: {=IFERROR(INDEX(TeamsNumber!B:B,MATCH(All_User!D20,TeamsNumber!D:D,0)),"없음")} -> tel:+82234517699 | M20: {=IFERROR(INDEX(Printer!D:D,MATCH(All_User!D20,Printer!H:H,0)),"없음")} -> SL-C563W | N20: {=IFERROR(INDEX(Monitor!A:A,MATCH(D20,Monitor!D:D,0)),"없음")} -> 없음 | O20: {=IFERROR(INDEX(sales!D:D,MATCH(D20,sales!C:C,0)),"없음")} -> MedSurg | P20: {=IFERROR(INDEX(sales!E:E,MATCH(D20,sales!C:C,0)),"없음")} -> Sales | Q20: {=IFERROR(INDEX(sales!C:C,MATCH(D20,sales!C:C,0)),"list없음")} -> martin.cho@stryker.com
A21: 21 | B21: Jungshin Cho | C21: 조정신 | D21: jungshin.cho@stryker.com | E21: CS Manager | F21: Customer Services Job Family Group | G21: Customer Services | H21: {=IFERROR(INDEX(Lease_List!D:D,MATCH(All_User!D21,Lease_List!H:H,0)),"없음")} -> 5CD442C07C | I21: 없음 | K21: {=IFERROR(INDEX(Ipad_List!C:C,MATCH(All_User!D21,Ipad_List!J:J,0)),"없음")} -> 없음 | L21: {=IFERROR(INDEX(TeamsNumber!B:B,MATCH(All_User!D21,TeamsNumber!D:D,0)),"없음")} -> tel:+82234517658 | M21: {=IFERROR(INDEX(Printer!D:D,MATCH(All_User!D21,Printer!H:H,0)),"없음")} -> 없음 | N21: {=IFERROR(INDEX(Monitor!A:A,MATCH(D21,Monitor!D:D,0)),"없음")} -> 없음 | O21: {=IFERROR(INDEX(sales!D:D,MATCH(D21,sales!C:C,0)),"없음")} -> 없음 | P21: {=IFERROR(INDEX(sales!E:E,MATCH(D21,sales!C:C,0)),"없음")} -> 없음
A23: 23 | B23: Roy Choi | C23: 최호정 | D23: roy.choi@stryker.com | E23: Senior Mako Product Specialist | F23: Sales and Marketing Job Family Group | G23: Medical Education | H23: {=IFERROR(INDEX(Lease_List!D:D,MATCH(All_User!D23,Lease_List!H:H,0)),"없음")} -> 없음 | I23: 07/25/23 | K23: {=IFERROR(INDEX(Ipad_List!C:C,MATCH(All_User!D23,Ipad_List!J:J,0)),"없음")} -> LD0W924NX3 | L23: {=IFERROR(INDEX(TeamsNumber!B:B,MATCH(All_User!D23,TeamsNumber!D:D,0)),"없음")} -> tel:+82234517567 | M23: {=IFERROR(INDEX(Printer!D:D,MATCH(All_User!D23,Printer!G:G,0)),"없음")} -> 없음 | N23: {=IFERROR(INDEX(Monitor!A:A,MATCH(D23,Monitor!D:D,0)),"없음")} -> 없음 | O23: {=IFERROR(INDEX(sales!D:D,MATCH(D23,sales!C:C,0)),"없음")} -> 0 | P23: {=IFERROR(INDEX(sales!E:E,MATCH(D23,sales!C:C,0)),"없음")} -> 0
A24: 24 | B24: Claire Choi | D24: claire.choi@stryker.com | E24: Mako Product Specialist | F24: Sales and Marketing Job Family Group | G24: Medical Education | H24: {=IFERROR(INDEX(Lease_List!D:D,MATCH(All_User!D24,Lease_List!H:H,0)),"없음")} -> 없음 | I24: 없음 | J24: C6CS1Z2(델?) | K24: {=IFERROR(INDEX(Ipad_List!C:C,MATCH(All_User!D24,Ipad_List!J:J,0)),"없음")} -> CQ0MQK66GM | L24: {=IFERROR(INDEX(TeamsNumber!B:B,MATCH(All_User!D24,TeamsNumber!D:D,0)),"없음")} -> tel:+82234517525 | M24: {=IFERROR(INDEX(Printer!D:D,MATCH(All_User!D24,Printer!G:G,0)),"없음")} -> 없음 | N24: {=IFERROR(INDEX(Monitor!A:A,MATCH(D24,Monitor!D:D,0)),"없음")} -> 없음 | O24: {=IFERROR(INDEX(sales!D:D,MATCH(D24,sales!C:C,0)),"없음")} -> Mako | P24: {=IFERROR(INDEX(sales!E:E,MATCH(D24,sales!C:C,0)),"없음")} -> MPS | Q24: {=IFERROR(INDEX(sales!C:C,MATCH(D24,sales!C:C,0)),"list없음")} -> claire.choi@stryker.com
A25: 25 | B25: Brad Choi | C25: 최동혁 | D25: brad.choi@stryker.com | E25: Senior Sales Representative | F25: Sales and Marketing Job Family Group | G25: Indirect Sales | H25: {=IFERROR(INDEX(Lease_List!D:D,MATCH(All_User!D25,Lease_List!H:H,0)),"없음")} -> 5CD4145N3V | I25: 없음 | K25: {=IFERROR(INDEX(Ipad_List!C:C,MATCH(All_User!D25,Ipad_List!J:J,0)),"없음")} -> MKTFHJRWT2 | L25: {=IFERROR(INDEX(TeamsNumber!B:B,MATCH(All_User!D25,TeamsNumber!D:D,0)),"없음")} -> tel:+82234517559 | M25: {=IFERROR(INDEX(Printer!D:D,MATCH(All_User!D25,Printer!H:H,0)),"없음")} -> SL-C563W | N25: {=IFERROR(INDEX(Monitor!A:A,MATCH(D25,Monitor!D:D,0)),"없음")} -> 없음 | O25: {=IFERROR(INDEX(sales!D:D,MATCH(D25,sales!C:C,0)),"없음")} -> Implants | P25: {=IFERROR(INDEX(sales!E:E,MATCH(D25,sales!C:C,0)),"없음")} -> Sales | Q25: {=IFERROR(INDEX(sales!C:C,MATCH(D25,sales!C:C,0)),"list없음")} -> brad.choi@stryker.com
A26: 26 | B26: Kyu Choi | C26: 최규범 | D26: kyu.choi@stryker.com | E26: Sales Representative, NV | F26: Sales and Marketing Job Family Group | G26: Direct Sales | H26: {=IFERROR(INDEX(Lease_List!D:D,MATCH(All_User!D26,Lease_List!H:H,0)),"없음")} -> 5CD5179KHS | I26: 07/25/23 | K26: {=IFERROR(INDEX(Ipad_List!C:C,MATCH(All_User!D26,Ipad_List!J:J,0)),"없음")} -> HP6F2M6GJ7 | L26: {=IFERROR(INDEX(TeamsNumber!B:B,MATCH(All_User!D26,TeamsNumber!D:D,0)),"없음")} -> tel:+82234517623 | M26: {=IFERROR(INDEX(Printer!D:D,MATCH(All_User!D26,Printer!H:H,0)),"없음")} -> SL-C565FW | N26: {=IFERROR(INDEX(Monitor!A:A,MATCH(D26,Monitor!D:D,0)),"없음")} -> 없음 | O26: {=IFERROR(INDEX(sales!D:D,MATCH(D26,sales!C:C,0)),"없음")} -> NV | P26: {=IFERROR(INDEX(sales!E:E,MATCH(D26,sales!C:C,0)),"없음")} -> NV | Q26: {=IFERROR(INDEX(sales!C:C,MATCH(D26,sales!C:C,0)),"list없음")} -> kyu.choi@stryker.com
A28: 28 | B28: Mason Choi | C28: 최민우 | D28: mason.choi@stryker.com | E28: Associate Mako Product Specialist | F28: Sales and Marketing Job Family Group | G28: Medical Education | H28: {=IFERROR(INDEX(Lease_List!D:D,MATCH(All_User!D28,Lease_List!H:H,0)),"없음")} -> 5CD5062YF4 | I28: 없음 | K28: {=IFERROR(INDEX(Ipad_List!C:C,MATCH(All_User!D28,Ipad_List!J:J,0)),"없음")} -> QC36D93T16 | L28: {=IFERROR(INDEX(TeamsNumber!B:B,MATCH(All_User!D28,TeamsNumber!D:D,0)),"없음")} -> tel:+82234517517 | M28: {=IFERROR(INDEX(Printer!D:D,MATCH(All_User!D28,Printer!H:H,0)),"없음")} -> 없음 | N28: {=IFERROR(INDEX(Monitor!A:A,MATCH(D28,Monitor!D:D,0)),"없음")} -> 없음 | O28: {=IFERROR(INDEX(sales!D:D,MATCH(D28,sales!C:C,0)),"없음")} -> Mako | P28: {=IFERROR(INDEX(sales!E:E,MATCH(D28,sales!C:C,0)),"없음")} -> MPS | Q28: {=IFERROR(INDEX(sales!C:C,MATCH(D28,sales!C:C,0)),"list없음")} -> mason.choi@stryker.com
A29: 29 | B29: Jaewook Chung | C29: 정재욱 | D29: jae.chung@stryker.com | E29: Senior Product Manager | F29: Sales and Marketing Job Family Group | G29: Product Management | H29: {=IFERROR(INDEX(Lease_List!D:D,MATCH(All_User!D29,Lease_List!H:H,0)),"없음")} -> 5CD442C072 | I29: 없음 | K29: {=IFERROR(INDEX(Ipad_List!C:C,MATCH(All_User!D29,Ipad_List!J:J,0)),"없음")} -> GMF3VLXNKG | L29: {=IFERROR(INDEX(TeamsNumber!B:B,MATCH(All_User!D29,TeamsNumber!D:D,0)),"없음")} -> tel:+82234517618 | M29: {=IFERROR(INDEX(Printer!D:D,MATCH(All_User!D29,Printer!H:H,0)),"없음")} -> SL-C483W | N29: {=IFERROR(INDEX(Monitor!A:A,MATCH(D29,Monitor!D:D,0)),"없음")} -> LCD 모니터 | O29: {=IFERROR(INDEX(sales!D:D,MATCH(D29,sales!C:C,0)),"없음")} -> 0 | P29: {=IFERROR(INDEX(sales!E:E,MATCH(D29,sales!C:C,0)),"없음")} -> MKT | Q29: {=IFERROR(INDEX(sales!C:C,MATCH(D29,sales!C:C,0)),"list없음")} -> jae.chung@stryker.com
A30: 30 | B30: David Chung | C30: 정석우 | D30: david.chung@stryker.com | E30: Sales Representative | F30: Sales and Marketing Job Family Group | G30: Indirect Sales | H30: {=IFERROR(INDEX(Lease_List!D:D,MATCH(All_User!D30,Lease_List!H:H,0)),"없음")} -> 5CD4232BF1 | I30: 없음 | K30: {=IFERROR(INDEX(Ipad_List!C:C,MATCH(All_User!D30,Ipad_List!J:J,0)),"없음")} -> DWJX4VVTX2 | L30: {=IFERROR(INDEX(TeamsNumber!B:B,MATCH(All_User!D30,TeamsNumber!D:D,0)),"없음")} -> tel:+82234517648 | M30: {=IFERROR(INDEX(Printer!D:D,MATCH(All_User!D30,Printer!H:H,0)),"없음")} -> 없음 | N30: {=IFERROR(INDEX(Monitor!A:A,MATCH(D30,Monitor!D:D,0)),"없음")} -> 없음 | O30: {=IFERROR(INDEX(sales!D:D,MATCH(D30,sales!C:C,0)),"없음")} -> Knee | P30: {=IFERROR(INDEX(sales!E:E,MATCH(D30,sales!C:C,0)),"없음")} -> Sales | Q30: {=IFERROR(INDEX(sales!C:C,MATCH(D30,sales!C:C,0)),"list없음")} -> david.chung@stryker.com
A31: 31 | B31: Chaeyeon Chung | C31: 정채연 | D31: chaeyeon.chung@stryker.com | E31: RA Specialist | F31: RAQA Job Family Group | G31: Regulatory Affairs | H31: {=IFERROR(INDEX(Lease_List!D:D,MATCH(All_User!D31,Lease_List!H:H,0)),"없음")} -> 5CD5062YDT | I31: 없음 | K31: {=IFERROR(INDEX(Ipad_List!C:C,MATCH(All_User!D31,Ipad_List!J:J,0)),"없음")} -> 없음 | L31: {=IFERROR(INDEX(TeamsNumber!B:B,MATCH(All_User!D31,TeamsNumber!D:D,0)),"없음")} -> 없음 | M31: {=IFERROR(INDEX(Printer!D:D,MATCH(All_User!D31,Printer!H:H,0)),"없음")} -> 없음 | N31: {=IFERROR(INDEX(Monitor!A:A,MATCH(D31,Monitor!D:D,0)),"없음")} -> 없음 | O31: {=IFERROR(INDEX(sales!D:D,MATCH(D31,sales!C:C,0)),"없음")} -> 없음 | P31: {=IFERROR(INDEX(sales!E:E,MATCH(D31,sales!C:C,0)),"없음")} -> 없음
A32: 32 | B32: Nathan Eom | C32: 엄태영 | D32: Nathan.Eom@stryker.com | E32: Sales Manager | F32: Sales and Marketing Job Family Group | G32: Indirect Sales | H32: {=IFERROR(INDEX(Lease_List!D:D,MATCH(All_User!D32,Lease_List!H:H,0)),"없음")} -> 5CD4305D8C | I32: 없음 | K32: {=IFERROR(INDEX(Ipad_List!C:C,MATCH(All_User!D32,Ipad_List!J:J,0)),"없음")} -> GW245H3KYL | L32: {=IFERROR(INDEX(TeamsNumber!B:B,MATCH(All_User!D32,TeamsNumber!D:D,0)),"없음")} -> tel:+82234517611 | M32: {=IFERROR(INDEX(Printer!D:D,MATCH(All_User!D32,Printer!H:H,0)),"없음")} -> SL-C486FW | N32: {=IFERROR(INDEX(Monitor!A:A,MATCH(D32,Monitor!D:D,0)),"없음")} -> 없음 | O32: {=IFERROR(INDEX(sales!D:D,MATCH(D32,sales!C:C,0)),"없음")} -> MedSurg | P32: {=IFERROR(INDEX(sales!E:E,MATCH(D32,sales!C:C,0)),"없음")} -> Sales | Q32: {=IFERROR(INDEX(sales!C:C,MATCH(D32,sales!C:C,0)),"list없음")} -> Nathan.Eom@stryker.com
A33: 33 | B33: Jack Eum | C33: 엄재원 | D33: jack.eum@stryker.com | E33: Senior Sales Representative | F33: Sales and Marketing Job Family Group | G33: Indirect Sales | H33: {=IFERROR(INDEX(Lease_List!D:D,MATCH(All_User!D33,Lease_List!H:H,0)),"없음")} -> 없음 | I33: 5CG2261LCR | K33: {=IFERROR(INDEX(Ipad_List!C:C,MATCH(All_User!D33,Ipad_List!J:J,0)),"없음")} -> D64QK42W36 | L33: {=IFERROR(INDEX(TeamsNumber!B:B,MATCH(All_User!D33,TeamsNumber!D:D,0)),"없음")} -> tel:+82234517610 | M33: {=IFERROR(INDEX(Printer!D:D,MATCH(All_User!D33,Printer!G:G,0)),"없음")} -> 없음 | N33: {=IFERROR(INDEX(Monitor!A:A,MATCH(D33,Monitor!D:D,0)),"없음")} -> 없음 | O33: {=IFERROR(INDEX(sales!D:D,MATCH(D33,sales!C:C,0)),"없음")} -> Knee | P33: {=IFERROR(INDEX(sales!E:E,MATCH(D33,sales!C:C,0)),"없음")} -> Sales | Q33: {=IFERROR(INDEX(sales!C:C,MATCH(D33,sales!C:C,0)),"list없음")} -> jack.eum@stryker.com
A34: 34 | B34: Emma Eun | C34: 은예석 | D34: emma.eun@stryker.com | E34: Business Operation Coordinator | F34: Sales and Marketing Job Family Group | G34: Sales Support | H34: {=IFERROR(INDEX(Lease_List!D:D,MATCH(All_User!D34,Lease_List!H:H,0)),"없음")} -> 없음 | I34: 07/25/23 | K34: {=IFERROR(INDEX(Ipad_List!C:C,MATCH(All_User!D34,Ipad_List!J:J,0)),"없음")} -> 없음 | L34: {=IFERROR(INDEX(TeamsNumber!B:B,MATCH(All_User!D34,TeamsNumber!D:D,0)),"없음")} -> 없음 | M34: {=IFERROR(INDEX(Printer!D:D,MATCH(All_User!D34,Printer!G:G,0)),"없음")} -> 없음 | N34: {=IFERROR(INDEX(Monitor!A:A,MATCH(D34,Monitor!D:D,0)),"없음")} -> 없음 | O34: {=IFERROR(INDEX(sales!D:D,MATCH(D34,sales!C:C,0)),"없음")} -> 없음 | P34: {=IFERROR(INDEX(sales!E:E,MATCH(D34,sales!C:C,0)),"없음")} -> 없음
A35: 35 | B35: Gyolim Gu | C35: 구교림 | D35: gyolim.gu@stryker.com | E35: Senior Planner | F35: Supply Chain Job Family Group | G35: Supply Planning | H35: {=IFERROR(INDEX(Lease_List!D:D,MATCH(All_User!D35,Lease_List!H:H,0)),"없음")} -> 5CD442C076 | I35: 5CG2181LVR | K35: {=IFERROR(INDEX(Ipad_List!C:C,MATCH(All_User!D35,Ipad_List!J:J,0)),"없음")} -> 없음 | L35: {=IFERROR(INDEX(TeamsNumber!B:B,MATCH(All_User!D35,TeamsNumber!D:D,0)),"없음")} -> tel:+82234517600 | M35: {=IFERROR(INDEX(Printer!D:D,MATCH(All_User!D35,Printer!H:H,0)),"없음")} -> 없음 | N35: {=IFERROR(INDEX(Monitor!A:A,MATCH(D35,Monitor!D:D,0)),"없음")} -> 없음 | O35: {=IFERROR(INDEX(sales!D:D,MATCH(D35,sales!C:C,0)),"없음")} -> 없음 | P35: {=IFERROR(INDEX(sales!E:E,MATCH(D35,sales!C:C,0)),"없음")} -> 없음
A36: 36 | B36: Alice Han | C36: 한민주 | D36: alice.han@stryker.com | E36: Senior RA Specialist | F36: RAQA Job Family Group | G36: Regulatory Affairs | H36: {=IFERROR(INDEX(Lease_List!D:D,MATCH(All_User!D36,Lease_List!H:H,0)),"없음")} -> 5CD5179KHR | I36: 5CG2181LXB | K36: {=IFERROR(INDEX(Ipad_List!C:C,MATCH(All_User!D36,Ipad_List!J:J,0)),"없음")} -> 없음 | L36: {=IFERROR(INDEX(TeamsNumber!B:B,MATCH(All_User!D36,TeamsNumber!D:D,0)),"없음")} -> tel:+82234517639 | M36: {=IFERROR(INDEX(Printer!D:D,MATCH(All_User!D36,Printer!H:H,0)),"없음")} -> 없음 | N36: {=IFERROR(INDEX(Monitor!A:A,MATCH(D36,Monitor!D:D,0)),"없음")} -> LCD 모니터 | O36: {=IFERROR(INDEX(sales!D:D,MATCH(D36,sales!C:C,0)),"없음")} -> 없음 | P36: {=IFERROR(INDEX(sales!E:E,MATCH(D36,sales!C:C,0)),"없음")} -> 없음
A37: 37 | B37: Leo Han | C37: 한현준 | D37: leo.han@stryker.com | E37: Mako Product Specialist | F37: Sales and Marketing Job Family Group | G37: Medical Education | H37: {=IFERROR(INDEX(Lease_List!D:D,MATCH(All_User!D37,Lease_List!H:H,0)),"없음")} -> 5CD4305D8Y | I37: 없음 | K37: {=IFERROR(INDEX(Ipad_List!C:C,MATCH(All_User!D37,Ipad_List!J:J,0)),"없음")} -> CXVPVQXG09 | L37: {=IFERROR(INDEX(TeamsNumber!B:B,MATCH(All_User!D37,TeamsNumber!D:D,0)),"없음")} -> tel:+82234517588 | M37: {=IFERROR(INDEX(Printer!D:D,MATCH(All_User!D37,Printer!H:H,0)),"없음")} -> SL-C563W | N37: {=IFERROR(INDEX(Monitor!A:A,MATCH(D37,Monitor!D:D,0)),"없음")} -> 없음 | O37: {=IFERROR(INDEX(sales!D:D,MATCH(D37,sales!C:C,0)),"없음")} -> Mako | P37: {=IFERROR(INDEX(sales!E:E,MATCH(D37,sales!C:C,0)),"없음")} -> MPS | Q37: {=IFERROR(INDEX(sales!C:C,MATCH(D37,sales!C:C,0)),"list없음")} -> leo.han@stryker.com
A38: 38 | B38: Mihee Han | C38: 한미희 | D38: mihee.han@stryker.com | E38: Associate Manager, FICM | F38: Finance Job Family Group | G38: Finance | H38: {=IFERROR(INDEX(Lease_List!D:D,MATCH(All_User!D38,Lease_List!H:H,0)),"없음")} -> 5CD3469HDB | I38: 없음 | J38: 5CG10801FQ(retired) | K38: {=IFERROR(INDEX(Ipad_List!C:C,MATCH(All_User!D38,Ipad_List!J:J,0)),"없음")} -> 없음 | L38: {=IFERROR(INDEX(TeamsNumber!B:B,MATCH(All_User!D38,TeamsNumber!D:D,0)),"없음")} -> tel:+82234517546 | M38: {=IFERROR(INDEX(Printer!D:D,MATCH(All_User!D38,Printer!G:G,0)),"없음")} -> 없음 | N38: {=IFERROR(INDEX(Monitor!A:A,MATCH(D38,Monitor!D:D,0)),"없음")} -> 없음 | O38: {=IFERROR(INDEX(sales!D:D,MATCH(D38,sales!C:C,0)),"없음")} -> 없음 | P38: {=IFERROR(INDEX(sales!E:E,MATCH(D38,sales!C:C,0)),"없음")} -> 없음
A39: 39 | B39: Jason Han | C39: 한준석 | D39: jason.han@stryker.com | E39: BU Director, Knee, Korea | F39: Sales and Marketing Job Family Group | G39: Sales and Marketing | H39: {=IFERROR(INDEX(Lease_List!D:D,MATCH(All_User!D39,Lease_List!H:H,0)),"없음")} -> 5CD5179KGZ | I39: 5CG2181LWF | K39: {=IFERROR(INDEX(Ipad_List!C:C,MATCH(All_User!D39,Ipad_List!J:J,0)),"없음")} -> KG27H3Q1J1 | L39: {=IFERROR(INDEX(TeamsNumber!B:B,MATCH(All_User!D39,TeamsNumber!D:D,0)),"없음")} -> tel:+82234517516 | M39: {=IFERROR(INDEX(Printer!D:D,MATCH(All_User!D39,Printer!H:H,0)),"없음")} -> 없음 | N39: {=IFERROR(INDEX(Monitor!A:A,MATCH(D39,Monitor!D:D,0)),"없음")} -> 없음 | O39: {=IFERROR(INDEX(sales!D:D,MATCH(D39,sales!C:C,0)),"없음")} -> 없음 | P39: {=IFERROR(INDEX(sales!E:E,MATCH(D39,sales!C:C,0)),"없음")} -> 없음
A41: 41 | B41: Arum Han | C41: 한아름 | D41: arum.han@stryker.com | E41: QA Manager | F41: RAQA Job Family Group | G41: Quality | H41: {=IFERROR(INDEX(Lease_List!D:D,MATCH(All_User!D41,Lease_List!H:H,0)),"없음")} -> 5CD4305D95 | I41: 없음 | K41: {=IFERROR(INDEX(Ipad_List!C:C,MATCH(All_User!D41,Ipad_List!J:J,0)),"없음")} -> 없음 | L41: {=IFERROR(INDEX(TeamsNumber!B:B,MATCH(All_User!D41,TeamsNumber!D:D,0)),"없음")} -> tel:+82234517634 | M41: {=IFERROR(INDEX(Printer!D:D,MATCH(All_User!D41,Printer!H:H,0)),"없음")} -> 없음 | N41: {=IFERROR(INDEX(Monitor!A:A,MATCH(D41,Monitor!D:D,0)),"없음")} -> 없음 | O41: {=IFERROR(INDEX(sales!D:D,MATCH(D41,sales!C:C,0)),"없음")} -> 없음 | P41: {=IFERROR(INDEX(sales!E:E,MATCH(D41,sales!C:C,0)),"없음")} -> 없음
A42: 42 | B42: Yejin Heo | C42: 허예진 | D42: yejin.heo@stryker.com | E42: Sales Representative, NV | F42: Sales and Marketing Job Family Group | G42: Direct Sales | H42: {=IFERROR(INDEX(Lease_List!D:D,MATCH(All_User!D42,Lease_List!H:H,0)),"없음")} -> 없음 | I42: 5CD32081ZB | K42: {=IFERROR(INDEX(Ipad_List!C:C,MATCH(All_User!D42,Ipad_List!J:J,0)),"없음")} -> DYQP729JPM | L42: {=IFERROR(INDEX(TeamsNumber!B:B,MATCH(All_User!D42,TeamsNumber!D:D,0)),"없음")} -> tel:+82234517643 | M42: {=IFERROR(INDEX(Printer!D:D,MATCH(All_User!D42,Printer!G:G,0)),"없음")} -> 없음 | N42: {=IFERROR(INDEX(Monitor!A:A,MATCH(D42,Monitor!D:D,0)),"없음")} -> 없음 | O42: {=IFERROR(INDEX(sales!D:D,MATCH(D42,sales!C:C,0)),"없음")} -> NV | P42: {=IFERROR(INDEX(sales!E:E,MATCH(D42,sales!C:C,0)),"없음")} -> NV | Q42: {=IFERROR(INDEX(sales!C:C,MATCH(D42,sales!C:C,0)),"list없음")} -> yejin.heo@stryker.com
A43: 43 | B43: Ashley Hong | C43: 홍윤경 | D43: ashley.hong@stryker.com | E43: Mako Product Specialist | F43: Sales and Marketing Job Family Group | G43: Medical Education | H43: {=IFERROR(INDEX(Lease_List!D:D,MATCH(All_User!D43,Lease_List!H:H,0)),"없음")} -> 5CD4232BFV | I43: 없음 | K43: {=IFERROR(INDEX(Ipad_List!C:C,MATCH(All_User!D43,Ipad_List!J:J,0)),"없음")} -> J99N6MMPMT | L43: {=IFERROR(INDEX(TeamsNumber!B:B,MATCH(All_User!D43,TeamsNumber!D:D,0)),"없음")} -> tel:+82234517581 | M43: {=IFERROR(INDEX(Printer!D:D,MATCH(All_User!D43,Printer!H:H,0)),"없음")} -> 없음 | N43: {=IFERROR(INDEX(Monitor!A:A,MATCH(D43,Monitor!D:D,0)),"없음")} -> 없음 | O43: {=IFERROR(INDEX(sales!D:D,MATCH(D43,sales!C:C,0)),"없음")} -> Mako | P43: {=IFERROR(INDEX(sales!E:E,MATCH(D43,sales!C:C,0)),"없음")} -> MPS | Q43: {=IFERROR(INDEX(sales!C:C,MATCH(D43,sales!C:C,0)),"list없음")} -> ashley.hong@stryker.com
A44: 44 | B44: Seo Yeong Hong | C44: 홍서영 | D44: seoyeong.hong@stryker.com | E44: Operations Specialist, Medical | F44: Supply Chain Job Family Group | G44: Logistics | H44: {=IFERROR(INDEX(Lease_List!D:D,MATCH(All_User!D44,Lease_List!H:H,0)),"없음")} -> 5CD4305D8H | I44: 없음 | K44: {=IFERROR(INDEX(Ipad_List!C:C,MATCH(All_User!D44,Ipad_List!J:J,0)),"없음")} -> 없음 | L44: {=IFERROR(INDEX(TeamsNumber!B:B,MATCH(All_User!D44,TeamsNumber!D:D,0)),"없음")} -> tel:+82234517630 | M44: {=IFERROR(INDEX(Printer!D:D,MATCH(All_User!D44,Printer!H:H,0)),"없음")} -> 없음 | N44: {=IFERROR(INDEX(Monitor!A:A,MATCH(D44,Monitor!D:D,0)),"없음")} -> 없음 | O44: {=IFERROR(INDEX(sales!D:D,MATCH(D44,sales!C:C,0)),"없음")} -> 없음 | P44: {=IFERROR(INDEX(sales!E:E,MATCH(D44,sales!C:C,0)),"없음")} -> 없음
A45: 45 | B45: Cozy Huh | C45: 허 소현 | D45: cozy.huh@stryker.com | E45: Business Operation Specialist | F45: Sales and Marketing Job Family Group | G45: Sales Support | H45: {=IFERROR(INDEX(Lease_List!D:D,MATCH(All_User!D45,Lease_List!H:H,0)),"없음")} -> 없음 | I45: 없음 | J45: 5CD32871LL | K45: {=IFERROR(INDEX(Ipad_List!C:C,MATCH(All_User!D45,Ipad_List!J:J,0)),"없음")} -> 없음 | L45: {=IFERROR(INDEX(TeamsNumber!B:B,MATCH(All_User!D45,TeamsNumber!D:D,0)),"없음")} -> tel:+82234517553 | M45: {=IFERROR(INDEX(Printer!D:D,MATCH(All_User!D45,Printer!G:G,0)),"없음")} -> 없음 | N45: {=IFERROR(INDEX(Monitor!A:A,MATCH(D45,Monitor!D:D,0)),"없음")} -> LCD 모니터 | O45: {=IFERROR(INDEX(sales!D:D,MATCH(D45,sales!C:C,0)),"없음")} -> 없음 | P45: {=IFERROR(INDEX(sales!E:E,MATCH(D45,sales!C:C,0)),"없음")} -> 없음
A46: 46 | B46: Sung Youn Hur | C46: 허성연 | D46: sungyoun.hur@stryker.com | E46: ICM Manager | F46: Sales and Marketing Job Family Group | G46: Sales Strategy | H46: {=IFERROR(INDEX(Lease_List!D:D,MATCH(All_User!D46,Lease_List!H:H,0)),"없음")} -> 5CD442C078 | I46: 없음 | K46: {=IFERROR(INDEX(Ipad_List!C:C,MATCH(All_User!D46,Ipad_List!J:J,0)),"없음")} -> 없음 | L46: {=IFERROR(INDEX(TeamsNumber!B:B,MATCH(All_User!D46,TeamsNumber!D:D,0)),"없음")} -> tel:+82234517552 | M46: {=IFERROR(INDEX(Printer!D:D,MATCH(All_User!D46,Printer!H:H,0)),"없음")} -> 없음 | N46: {=IFERROR(INDEX(Monitor!A:A,MATCH(D46,Monitor!D:D,0)),"없음")} -> 없음 | O46: {=IFERROR(INDEX(sales!D:D,MATCH(D46,sales!C:C,0)),"없음")} -> 없음 | P46: {=IFERROR(INDEX(sales!E:E,MATCH(D46,sales!C:C,0)),"없음")} -> 없음
A47: 47 | B47: Oscar Hwang | C47: 황해수 | D47: oscar.hwang@stryker.com | E47: Senior Technical Service Engineer | F47: Customer Services Job Family Group | G47: Technical Customer Support | H47: {=IFERROR(INDEX(Lease_List!D:D,MATCH(All_User!D47,Lease_List!H:H,0)),"없음")} -> 5CD442C07G | I47: 없음 | K47: {=IFERROR(INDEX(Ipad_List!C:C,MATCH(All_User!D47,Ipad_List!J:J,0)),"없음")} -> XYGFK42KQP | L47: {=IFERROR(INDEX(TeamsNumber!B:B,MATCH(All_User!D47,TeamsNumber!D:D,0)),"없음")} -> tel:+82234517671 | M47: {=IFERROR(INDEX(Printer!D:D,MATCH(All_User!D47,Printer!H:H,0)),"없음")} -> 확인중 | N47: {=IFERROR(INDEX(Monitor!A:A,MATCH(D47,Monitor!D:D,0)),"없음")} -> 없음 | O47: {=IFERROR(INDEX(sales!D:D,MATCH(D47,sales!C:C,0)),"없음")} -> 0 | P47: {=IFERROR(INDEX(sales!E:E,MATCH(D47,sales!C:C,0)),"없음")} -> TS | Q47: {=IFERROR(INDEX(sales!C:C,MATCH(D47,sales!C:C,0)),"list없음")} -> oscar.hwang@stryker.com
A48: 48 | B48: Young Hwang | C48: 황우영 | D48: young.hwang@stryker.com | E48: Senior Sales Representative, Neurovascular, Korea | F48: Sales and Marketing Job Family Group | G48: Direct Sales | H48: {=IFERROR(INDEX(Lease_List!D:D,MATCH(All_User!D48,Lease_List!H:H,0)),"없음")} -> 5CD5179KHZ | I48: 5CG2181LWL | K48: {=IFERROR(INDEX(Ipad_List!C:C,MATCH(All_User!D48,Ipad_List!J:J,0)),"없음")} -> FNP3C7WRP2 | L48: {=IFERROR(INDEX(TeamsNumber!B:B,MATCH(All_User!D48,TeamsNumber!D:D,0)),"없음")} -> tel:+82234517688 | M48: {=IFERROR(INDEX(Printer!D:D,MATCH(All_User!D48,Printer!H:H,0)),"없음")} -> 2차 조사 정보 없음 | N48: {=IFERROR(INDEX(Monitor!A:A,MATCH(D48,Monitor!D:D,0)),"없음")} -> 없음 | O48: {=IFERROR(INDEX(sales!D:D,MATCH(D48,sales!C:C,0)),"없음")} -> NV | P48: {=IFERROR(INDEX(sales!E:E,MATCH(D48,sales!C:C,0)),"없음")} -> NV | Q48: {=IFERROR(INDEX(sales!C:C,MATCH(D48,sales!C:C,0)),"list없음")} -> young.hwang@stryker.com
A49: 49 | B49: Theo Hwang | C49: 황현택 | D49: theo.hwang@stryker.com | E49: Senior Sales Representative, MedSurg | F49: Sales and Marketing Job Family Group | G49: Indirect Sales | H49: {=IFERROR(INDEX(Lease_List!D:D,MATCH(All_User!D49,Lease_List!H:H,0)),"없음")} -> 5CD3469HCX | I49: 없음 | K49: {=IFERROR(INDEX(Ipad_List!C:C,MATCH(All_User!D49,Ipad_List!J:J,0)),"없음")} -> GD2WG3K71P | L49: {=IFERROR(INDEX(TeamsNumber!B:B,MATCH(All_User!D49,TeamsNumber!D:D,0)),"없음")} -> tel:+82234517686 | M49: {=IFERROR(INDEX(Printer!D:D,MATCH(All_User!D49,Printer!H:H,0)),"없음")} -> SL-C563W | N49: {=IFERROR(INDEX(Monitor!A:A,MATCH(D49,Monitor!D:D,0)),"없음")} -> 없음 | O49: {=IFERROR(INDEX(sales!D:D,MATCH(D49,sales!C:C,0)),"없음")} -> MedSurg | P49: {=IFERROR(INDEX(sales!E:E,MATCH(D49,sales!C:C,0)),"없음")} -> Sales | Q49: {=IFERROR(INDEX(sales!C:C,MATCH(D49,sales!C:C,0)),"list없음")} -> theo.hwang@stryker.com
A51: 51 | B51: Daniel Jang | C51: 장동혁 | D51: daniel.jang@stryker.com | E51: Senior Sales Representative | F51: Sales and Marketing Job Family Group | G51: Indirect Sales | H51: {=IFERROR(INDEX(Lease_List!D:D,MATCH(All_User!D51,Lease_List!H:H,0)),"없음")} -> 5CD442C07D | I51: 없음 | K51: {=IFERROR(INDEX(Ipad_List!C:C,MATCH(All_User!D51,Ipad_List!J:J,0)),"없음")} -> Q9JKF6RRK4 | L51: {=IFERROR(INDEX(TeamsNumber!B:B,MATCH(All_User!D51,TeamsNumber!D:D,0)),"없음")} -> tel:+82234517666 | M51: {=IFERROR(INDEX(Printer!D:D,MATCH(All_User!D51,Printer!H:H,0)),"없음")} -> 없음 | N51: {=IFERROR(INDEX(Monitor!A:A,MATCH(D51,Monitor!D:D,0)),"없음")} -> 없음 | O51: {=IFERROR(INDEX(sales!D:D,MATCH(D51,sales!C:C,0)),"없음")} -> Shoulder | P51: {=IFERROR(INDEX(sales!E:E,MATCH(D51,sales!C:C,0)),"없음")} -> Sales | Q51: {=IFERROR(INDEX(sales!C:C,MATCH(D51,sales!C:C,0)),"list없음")} -> daniel.jang@stryker.com
A52: 52 | B52: Ethan Jang | C52: 장찬희 | D52: ethan.jang@stryker.com | E52: Field Service Engineer | F52: Customer Services Job Family Group | G52: Technical Customer Support | H52: {=IFERROR(INDEX(Lease_List!D:D,MATCH(All_User!D52,Lease_List!H:H,0)),"없음")} -> 5CD5062YDW | I52: 없음 | K52: {=IFERROR(INDEX(Ipad_List!C:C,MATCH(All_User!D52,Ipad_List!J:J,0)),"없음")} -> G7CV2M99YM | L52: {=IFERROR(INDEX(TeamsNumber!B:B,MATCH(All_User!D52,TeamsNumber!D:D,0)),"없음")} -> tel:+82234517535 | M52: {=IFERROR(INDEX(Printer!D:D,MATCH(All_User!D52,Printer!H:H,0)),"없음")} -> 없음 | N52: {=IFERROR(INDEX(Monitor!A:A,MATCH(D52,Monitor!D:D,0)),"없음")} -> 없음 | O52: {=IFERROR(INDEX(sales!D:D,MATCH(D52,sales!C:C,0)),"없음")} -> 0 | P52: {=IFERROR(INDEX(sales!E:E,MATCH(D52,sales!C:C,0)),"없음")} -> TS | Q52: {=IFERROR(INDEX(sales!C:C,MATCH(D52,sales!C:C,0)),"list없음")} -> ethan.jang@stryker.com
A53: 53 | B53: Eunhyang Jeon | C53: 전은향 | D53: cindy.jeon@stryker.com | E53: Lead Specialist, Demand Planning, Orthopedics | F53: Supply Chain Job Family Group | G53: Supply Planning | H53: {=IFERROR(INDEX(Lease_List!D:D,MATCH(All_User!D53,Lease_List!H:H,0)),"없음")} -> 5CD3469HDQ | I53: 없음 | K53: {=IFERROR(INDEX(Ipad_List!C:C,MATCH(All_User!D53,Ipad_List!J:J,0)),"없음")} -> 없음 | L53: {=IFERROR(INDEX(TeamsNumber!B:B,MATCH(All_User!D53,TeamsNumber!D:D,0)),"없음")} -> tel:+82234517665 | M53: {=IFERROR(INDEX(Printer!D:D,MATCH(All_User!D53,Printer!H:H,0)),"없음")} -> 없음 | N53: {=IFERROR(INDEX(Monitor!A:A,MATCH(D53,Monitor!D:D,0)),"없음")} -> 없음 | O53: {=IFERROR(INDEX(sales!D:D,MATCH(D53,sales!C:C,0)),"없음")} -> 없음 | P53: {=IFERROR(INDEX(sales!E:E,MATCH(D53,sales!C:C,0)),"없음")} -> 없음
A54: 54 | B54: Lucas Jeon | C54: 전혁구 | D54: lucas.jeon@stryker.com | E54: Sales Representative, NV | F54: Sales and Marketing Job Family Group | G54: Direct Sales | H54: {=IFERROR(INDEX(Lease_List!D:D,MATCH(All_User!D54,Lease_List!H:H,0)),"없음")} -> 없음 | I54: 07/25/23 | K54: {=IFERROR(INDEX(Ipad_List!C:C,MATCH(All_User!D54,Ipad_List!J:J,0)),"없음")} -> J7J79LY961 | L54: {=IFERROR(INDEX(TeamsNumber!B:B,MATCH(All_User!D54,TeamsNumber!D:D,0)),"없음")} -> tel:+82234517604 | M54: {=IFERROR(INDEX(Printer!D:D,MATCH(All_User!D54,Printer!G:G,0)),"없음")} -> 없음 | N54: {=IFERROR(INDEX(Monitor!A:A,MATCH(D54,Monitor!D:D,0)),"없음")} -> 없음 | O54: {=IFERROR(INDEX(sales!D:D,MATCH(D54,sales!C:C,0)),"없음")} -> NV | P54: {=IFERROR(INDEX(sales!E:E,MATCH(D54,sales!C:C,0)),"없음")} -> NV | Q54: {=IFERROR(INDEX(sales!C:C,MATCH(D54,sales!C:C,0)),"list없음")} -> lucas.jeon@stryker.com
A55: 55 | B55: Chan Jeon | C55: 전일찬 | D55: chan.jeon@stryker.com | E55: Senior Sales Representative, MedSurg | F55: Sales and Marketing Job Family Group | G55: Direct Sales | H55: {=IFERROR(INDEX(Lease_List!D:D,MATCH(All_User!D55,Lease_List!H:H,0)),"없음")} -> 없음 | I55: 07/25/23 | K55: {=IFERROR(INDEX(Ipad_List!C:C,MATCH(All_User!D55,Ipad_List!J:J,0)),"없음")} -> WHYPLVY40L | L55: {=IFERROR(INDEX(TeamsNumber!B:B,MATCH(All_User!D55,TeamsNumber!D:D,0)),"없음")} -> tel:+82234517527 | M55: {=IFERROR(INDEX(Printer!D:D,MATCH(All_User!D55,Printer!G:G,0)),"없음")} -> 없음 | N55: {=IFERROR(INDEX(Monitor!A:A,MATCH(D55,Monitor!D:D,0)),"없음")} -> 없음 | O55: {=IFERROR(INDEX(sales!D:D,MATCH(D55,sales!C:C,0)),"없음")} -> MedSurg | P55: {=IFERROR(INDEX(sales!E:E,MATCH(D55,sales!C:C,0)),"없음")} -> Sales | Q55: {=IFERROR(INDEX(sales!C:C,MATCH(D55,sales!C:C,0)),"list없음")} -> chan.jeon@stryker.com
A56: 56 | B56: Yoonbee Jeong | C56: 정윤비 | D56: yoonbee.jeong@stryker.com | E56: Senior Marketing Specialist, Mako | F56: Sales and Marketing Job Family Group | G56: Product Management | H56: {=IFERROR(INDEX(Lease_List!D:D,MATCH(All_User!D56,Lease_List!H:H,0)),"없음")} -> 5CD4305D80 | I56: 없음 | K56: {=IFERROR(INDEX(Ipad_List!C:C,MATCH(All_User!D56,Ipad_List!J:J,0)),"없음")} -> M2FKP9T7QX | L56: {=IFERROR(INDEX(TeamsNumber!B:B,MATCH(All_User!D56,TeamsNumber!D:D,0)),"없음")} -> tel:+82234517589 | M56: {=IFERROR(INDEX(Printer!D:D,MATCH(All_User!D56,Printer!H:H,0)),"없음")} -> SL-C563W | N56: {=IFERROR(INDEX(Monitor!A:A,MATCH(D56,Monitor!D:D,0)),"없음")} -> 없음 | O56: {=IFERROR(INDEX(sales!D:D,MATCH(D56,sales!C:C,0)),"없음")} -> 0 | P56: {=IFERROR(INDEX(sales!E:E,MATCH(D56,sales!C:C,0)),"없음")} -> Sales | Q56: {=IFERROR(INDEX(sales!C:C,MATCH(D56,sales!C:C,0)),"list없음")} -> yoonbee.jeong@stryker.com
A57: 57 | B57: Somi Jeong | C57: 정소미 | D57: somi.jeong@stryker.com | E57: Associate Mako Product Specialist | F57: Sales and Marketing Job Family Group | G57: Medical Education | H57: {=IFERROR(INDEX(Lease_List!D:D,MATCH(All_User!D57,Lease_List!H:H,0)),"없음")} -> 5CD4305D8Z | I57: 없음 | K57: {=IFERROR(INDEX(Ipad_List!C:C,MATCH(All_User!D57,Ipad_List!J:J,0)),"없음")} -> DFC7V7Q9X3 | L57: {=IFERROR(INDEX(TeamsNumber!B:B,MATCH(All_User!D57,TeamsNumber!D:D,0)),"없음")} -> tel:+82234517642 | M57: {=IFERROR(INDEX(Printer!D:D,MATCH(All_User!D57,Printer!H:H,0)),"없음")} -> 없음 | N57: {=IFERROR(INDEX(Monitor!A:A,MATCH(D57,Monitor!D:D,0)),"없음")} -> 없음 | O57: {=IFERROR(INDEX(sales!D:D,MATCH(D57,sales!C:C,0)),"없음")} -> Mako | P57: {=IFERROR(INDEX(sales!E:E,MATCH(D57,sales!C:C,0)),"없음")} -> MPS | Q57: {=IFERROR(INDEX(sales!C:C,MATCH(D57,sales!C:C,0)),"list없음")} -> somi.jeong@stryker.com
A58: 58 | B58: Dahye Jeong | C58: 정다혜 | D58: dahye.jeong@stryker.com | E58: Associate Mako Product Specialist | F58: Sales and Marketing Job Family Group | G58: Medical Education | H58: {=IFERROR(INDEX(Lease_List!D:D,MATCH(All_User!D58,Lease_List!H:H,0)),"없음")} -> 5CD5179KHD | I58: 없음 | K58: {=IFERROR(INDEX(Ipad_List!C:C,MATCH(All_User!D58,Ipad_List!J:J,0)),"없음")} -> GVYCM2VJKW | L58: {=IFERROR(INDEX(TeamsNumber!B:B,MATCH(All_User!D58,TeamsNumber!D:D,0)),"없음")} -> tel:+82234517500 | M58: {=IFERROR(INDEX(Printer!D:D,MATCH(All_User!D58,Printer!H:H,0)),"없음")} -> 없음 | N58: {=IFERROR(INDEX(Monitor!A:A,MATCH(D58,Monitor!D:D,0)),"없음")} -> 없음 | O58: {=IFERROR(INDEX(sales!D:D,MATCH(D58,sales!C:C,0)),"없음")} -> Mako | P58: {=IFERROR(INDEX(sales!E:E,MATCH(D58,sales!C:C,0)),"없음")} -> MPS | Q58: {=IFERROR(INDEX(sales!C:C,MATCH(D58,sales!C:C,0)),"list없음")} -> dahye.jeong@stryker.com
A59: 59 | B59: HanGil Jeong | C59: 정한길 | D59: hangil.jeong@stryker.com | E59: Logistics Manager | F59: Supply Chain Job Family Group | G59: Logistics | H59: {=IFERROR(INDEX(Lease_List!D:D,MATCH(All_User!D59,Lease_List!H:H,0)),"없음")} -> 5CD4145N3R | I59: 없음 | K59: {=IFERROR(INDEX(Ipad_List!C:C,MATCH(All_User!D59,Ipad_List!J:J,0)),"없음")} -> 없음 | L59: {=IFERROR(INDEX(TeamsNumber!B:B,MATCH(All_User!D59,TeamsNumber!D:D,0)),"없음")} -> tel:+82234517627 | M59: {=IFERROR(INDEX(Printer!D:D,MATCH(All_User!D59,Printer!H:H,0)),"없음")} -> 없음 | N59: {=IFERROR(INDEX(Monitor!A:A,MATCH(D59,Monitor!D:D,0)),"없음")} -> 없음 | O59: {=IFERROR(INDEX(sales!D:D,MATCH(D59,sales!C:C,0)),"없음")} -> 없음 | P59: {=IFERROR(INDEX(sales!E:E,MATCH(D59,sales!C:C,0)),"없음")} -> 없음
A60: 60 | B60: Sunglee Jeun | C60: 전성이 | D60: sungyi.jeon@stryker.com | E60: FP&A Manager | F60: Finance Job Family Group | G60: Financial Planning and Analysis | H60: {=IFERROR(INDEX(Lease_List!D:D,MATCH(All_User!D60,Lease_List!H:H,0)),"없음")} -> 5CD3469HD3 | I60: 없음 | K60: {=IFERROR(INDEX(Ipad_List!C:C,MATCH(All_User!D60,Ipad_List!J:J,0)),"없음")} -> 없음 | L60: {=IFERROR(INDEX(TeamsNumber!B:B,MATCH(All_User!D60,TeamsNumber!D:D,0)),"없음")} -> tel:+82234517501 | M60: {=IFERROR(INDEX(Printer!D:D,MATCH(All_User!D60,Printer!H:H,0)),"없음")} -> 없음 | N60: {=IFERROR(INDEX(Monitor!A:A,MATCH(D60,Monitor!D:D,0)),"없음")} -> 없음 | O60: {=IFERROR(INDEX(sales!D:D,MATCH(D60,sales!C:C,0)),"없음")} -> 없음 | P60: {=IFERROR(INDEX(sales!E:E,MATCH(D60,sales!C:C,0)),"없음")} -> 없음
A61: 61 | B61: JH Ji | C61: 지정훈 | D61: jh.ji@stryker.com | E61: Commercial Excellence Director | F61: Compliance Job Family Group | G61: Healthcare Economics | H61: {=IFERROR(INDEX(Lease_List!D:D,MATCH(All_User!D61,Lease_List!H:H,0)),"없음")} -> 5CD4305D8M | I61: 없음 | K61: {=IFERROR(INDEX(Ipad_List!C:C,MATCH(All_User!D61,Ipad_List!J:J,0)),"없음")} -> HW21HF1YCH | L61: {=IFERROR(INDEX(TeamsNumber!B:B,MATCH(All_User!D61,TeamsNumber!D:D,0)),"없음")} -> tel:+82234517632 | M61: {=IFERROR(INDEX(Printer!D:D,MATCH(All_User!D61,Printer!H:H,0)),"없음")} -> 없음 | N61: {=IFERROR(INDEX(Monitor!A:A,MATCH(D61,Monitor!D:D,0)),"없음")} -> 없음 | O61: {=IFERROR(INDEX(sales!D:D,MATCH(D61,sales!C:C,0)),"없음")} -> 없음 | P61: {=IFERROR(INDEX(sales!E:E,MATCH(D61,sales!C:C,0)),"없음")} -> 없음
A62: 62 | B62: Jay Ji | C62: 지정은 | D62: jay.ji@stryker.com | E62: Product Manager, Shoulder | F62: Sales and Marketing Job Family Group | G62: Product Management | H62: {=IFERROR(INDEX(Lease_List!D:D,MATCH(All_User!D62,Lease_List!H:H,0)),"없음")} -> 5CD5062YF6 | I62: 없음 | K62: {=IFERROR(INDEX(Ipad_List!C:C,MATCH(All_User!D62,Ipad_List!J:J,0)),"없음")} -> GGWR7NXY2D | L62: {=IFERROR(INDEX(TeamsNumber!B:B,MATCH(All_User!D62,TeamsNumber!D:D,0)),"없음")} -> tel:+82234517603 | M62: {=IFERROR(INDEX(Printer!D:D,MATCH(All_User!D62,Printer!H:H,0)),"없음")} -> 없음 | N62: {=IFERROR(INDEX(Monitor!A:A,MATCH(D62,Monitor!D:D,0)),"없음")} -> LCD 모니터 | O62: {=IFERROR(INDEX(sales!D:D,MATCH(D62,sales!C:C,0)),"없음")} -> 0 | P62: {=IFERROR(INDEX(sales!E:E,MATCH(D62,sales!C:C,0)),"없음")} -> Sales | Q62: {=IFERROR(INDEX(sales!C:C,MATCH(D62,sales!C:C,0)),"list없음")} -> jay.ji@stryker.com
A63: 63 | B63: Scott Jo | C63: 조상혁 | D63: scott.jo@stryker.com | E63: Sales Manager | F63: Sales and Marketing Job Family Group | G63: Indirect Sales | H63: {=IFERROR(INDEX(Lease_List!D:D,MATCH(All_User!D63,Lease_List!H:H,0)),"없음")} -> 5CD4232BFJ | I63: 없음 | K63: {=IFERROR(INDEX(Ipad_List!C:C,MATCH(All_User!D63,Ipad_List!J:J,0)),"없음")} -> JFK7CC9090 | L63: {=IFERROR(INDEX(TeamsNumber!B:B,MATCH(All_User!D63,TeamsNumber!D:D,0)),"없음")} -> tel:+82234517655 | M63: {=IFERROR(INDEX(Printer!D:D,MATCH(All_User!D63,Printer!H:H,0)),"없음")} -> 없음 | N63: {=IFERROR(INDEX(Monitor!A:A,MATCH(D63,Monitor!D:D,0)),"없음")} -> 없음 | O63: {=IFERROR(INDEX(sales!D:D,MATCH(D63,sales!C:C,0)),"없음")} -> Knee | P63: {=IFERROR(INDEX(sales!E:E,MATCH(D63,sales!C:C,0)),"없음")} -> Sales | Q63: {=IFERROR(INDEX(sales!C:C,MATCH(D63,sales!C:C,0)),"list없음")} -> scott.jo@stryker.com
A64: 64 | B64: Irene Jun | C64: 전신영 | D64: irene.jun@stryker.com | E64: Lead Specialist, Regulatory Affairs | F64: RAQA Job Family Group | G64: Regulatory Affairs | H64: {=IFERROR(INDEX(Lease_List!D:D,MATCH(All_User!D64,Lease_List!H:H,0)),"없음")} -> 5CD3469HDR | I64: 없음 | K64: {=IFERROR(INDEX(Ipad_List!C:C,MATCH(All_User!D64,Ipad_List!J:J,0)),"없음")} -> 없음 | L64: {=IFERROR(INDEX(TeamsNumber!B:B,MATCH(All_User!D64,TeamsNumber!D:D,0)),"없음")} -> tel:+82234517635 | M64: {=IFERROR(INDEX(Printer!D:D,MATCH(All_User!D64,Printer!H:H,0)),"없음")} -> 없음 | N64: {=IFERROR(INDEX(Monitor!A:A,MATCH(D64,Monitor!D:D,0)),"없음")} -> 없음 | O64: {=IFERROR(INDEX(sales!D:D,MATCH(D64,sales!C:C,0)),"없음")} -> 없음 | P64: {=IFERROR(INDEX(sales!E:E,MATCH(D64,sales!C:C,0)),"없음")} -> 없음
A65: 65 | B65: Jade Jung | C65: 정지운 | D65: jade.jung@stryker.com | E65: Mako Product Specialist | F65: Sales and Marketing Job Family Group | G65: Medical Education | H65: {=IFERROR(INDEX(Lease_List!D:D,MATCH(All_User!D65,Lease_List!H:H,0)),"없음")} -> 5CD442C079 | I65: 없음 | K65: {=IFERROR(INDEX(Ipad_List!C:C,MATCH(All_User!D65,Ipad_List!J:J,0)),"없음")} -> J6YXV33LDP | L65: {=IFERROR(INDEX(TeamsNumber!B:B,MATCH(All_User!D65,TeamsNumber!D:D,0)),"없음")} -> tel:+82234517569 | M65: {=IFERROR(INDEX(Printer!D:D,MATCH(All_User!D65,Printer!H:H,0)),"없음")} -> 없음 | N65: {=IFERROR(INDEX(Monitor!A:A,MATCH(D65,Monitor!D:D,0)),"없음")} -> 없음 | O65: {=IFERROR(INDEX(sales!D:D,MATCH(D65,sales!C:C,0)),"없음")} -> Mako | P65: {=IFERROR(INDEX(sales!E:E,MATCH(D65,sales!C:C,0)),"없음")} -> MPS | Q65: {=IFERROR(INDEX(sales!C:C,MATCH(D65,sales!C:C,0)),"list없음")} -> jade.jung@stryker.com
A66: 66 | B66: Jenny Jung | C66: 정진희 | D66: jenny.jung@stryker.com | E66: Associate Marketing Manager | F66: Sales and Marketing Job Family Group | G66: Product Management | H66: {=IFERROR(INDEX(Lease_List!D:D,MATCH(All_User!D66,Lease_List!H:H,0)),"없음")} -> 5CD3469HDT | I66: 없음 | K66: {=IFERROR(INDEX(Ipad_List!C:C,MATCH(All_User!D66,Ipad_List!J:J,0)),"없음")} -> DG3XL2W5VX | L66: {=IFERROR(INDEX(TeamsNumber!B:B,MATCH(All_User!D66,TeamsNumber!D:D,0)),"없음")} -> tel:+82234517605 | M66: {=IFERROR(INDEX(Printer!D:D,MATCH(All_User!D66,Printer!H:H,0)),"없음")} -> 없음 | N66: {=IFERROR(INDEX(Monitor!A:A,MATCH(D66,Monitor!D:D,0)),"없음")} -> LCD 모니터 | O66: {=IFERROR(INDEX(sales!D:D,MATCH(D66,sales!C:C,0)),"없음")} -> 0 | P66: {=IFERROR(INDEX(sales!E:E,MATCH(D66,sales!C:C,0)),"없음")} -> MKT | Q66: {=IFERROR(INDEX(sales!C:C,MATCH(D66,sales!C:C,0)),"list없음")} -> jenny.jung@stryker.com
A67: 67 | B67: Suhwan Jung | C67: 정수환 | D67: suhwan.jung@stryker.com | E67: Mako Product Specialist | F67: Sales and Marketing Job Family Group | G67: Medical Education | H67: {=IFERROR(INDEX(Lease_List!D:D,MATCH(All_User!D67,Lease_List!H:H,0)),"없음")} -> 5CD4305D8X | I67: 없음 | K67: {=IFERROR(INDEX(Ipad_List!C:C,MATCH(All_User!D67,Ipad_List!J:J,0)),"없음")} -> XCYDTQ4H1F | L67: {=IFERROR(INDEX(TeamsNumber!B:B,MATCH(All_User!D67,TeamsNumber!D:D,0)),"없음")} -> tel:+82234517584 | M67: {=IFERROR(INDEX(Printer!D:D,MATCH(All_User!D67,Printer!H:H,0)),"없음")} -> 없음 | N67: {=IFERROR(INDEX(Monitor!A:A,MATCH(D67,Monitor!D:D,0)),"없음")} -> 없음 | O67: {=IFERROR(INDEX(sales!D:D,MATCH(D67,sales!C:C,0)),"없음")} -> Mako | P67: {=IFERROR(INDEX(sales!E:E,MATCH(D67,sales!C:C,0)),"없음")} -> MPS | Q67: {=IFERROR(INDEX(sales!C:C,MATCH(D67,sales!C:C,0)),"list없음")} -> suhwan.jung@stryker.com
A68: 68 | B68: Seo Hyun Jung | C68: 정서현 | D68: seohyun.jung@stryker.com | E68: Mako Product Specialist | F68: Sales and Marketing Job Family Group | G68: Medical Education | H68: {=IFERROR(INDEX(Lease_List!D:D,MATCH(All_User!D68,Lease_List!H:H,0)),"없음")} -> 5CD4305D94 | I68: 없음 | K68: {=IFERROR(INDEX(Ipad_List!C:C,MATCH(All_User!D68,Ipad_List!J:J,0)),"없음")} -> C19HH7PP2V | L68: {=IFERROR(INDEX(TeamsNumber!B:B,MATCH(All_User!D68,TeamsNumber!D:D,0)),"없음")} -> tel:+82234517574 | M68: {=IFERROR(INDEX(Printer!D:D,MATCH(All_User!D68,Printer!H:H,0)),"없음")} -> 없음 | N68: {=IFERROR(INDEX(Monitor!A:A,MATCH(D68,Monitor!D:D,0)),"없음")} -> 없음 | O68: {=IFERROR(INDEX(sales!D:D,MATCH(D68,sales!C:C,0)),"없음")} -> Mako | P68: {=IFERROR(INDEX(sales!E:E,MATCH(D68,sales!C:C,0)),"없음")} -> MPS | Q68: {=IFERROR(INDEX(sales!C:C,MATCH(D68,sales!C:C,0)),"list없음")} -> seohyun.jung@stryker.com
A69: 69 | B69: Celine Jung | C69: 정혜빈 | D69: celine.jung@stryker.com | E69: Regulatory Affairs Specialist | F69: RAQA Job Family Group | G69: Regulatory Affairs | H69: {=IFERROR(INDEX(Lease_List!D:D,MATCH(All_User!D69,Lease_List!H:H,0)),"없음")} -> 5CD4232BFG | I69: 없음 | K69: {=IFERROR(INDEX(Ipad_List!C:C,MATCH(All_User!D69,Ipad_List!J:J,0)),"없음")} -> 없음 | L69: {=IFERROR(INDEX(TeamsNumber!B:B,MATCH(All_User!D69,TeamsNumber!D:D,0)),"없음")} -> tel:+82234517636 | M69: {=IFERROR(INDEX(Printer!D:D,MATCH(All_User!D69,Printer!H:H,0)),"없음")} -> 없음 | N69: {=IFERROR(INDEX(Monitor!A:A,MATCH(D69,Monitor!D:D,0)),"없음")} -> 없음 | O69: {=IFERROR(INDEX(sales!D:D,MATCH(D69,sales!C:C,0)),"없음")} -> 없음 | P69: {=IFERROR(INDEX(sales!E:E,MATCH(D69,sales!C:C,0)),"없음")} -> 없음
A70: 70 | B70: Sol Jung | C70: 정솔 | D70: sol.jung@stryker.com | E70: Associate Mako Product Specialist | F70: Sales and Marketing Job Family Group | G70: Medical Education | H70: {=IFERROR(INDEX(Lease_List!D:D,MATCH(All_User!D70,Lease_List!H:H,0)),"없음")} -> 5CD5062YF8 | I70: 5CD32081Z7 | K70: {=IFERROR(INDEX(Ipad_List!C:C,MATCH(All_User!D70,Ipad_List!J:J,0)),"없음")} -> G09WDG49T4 | L70: {=IFERROR(INDEX(TeamsNumber!B:B,MATCH(All_User!D70,TeamsNumber!D:D,0)),"없음")} -> tel:+82234517694 | M70: {=IFERROR(INDEX(Printer!D:D,MATCH(All_User!D70,Printer!H:H,0)),"없음")} -> 없음 | N70: {=IFERROR(INDEX(Monitor!A:A,MATCH(D70,Monitor!D:D,0)),"없음")} -> 없음 | O70: {=IFERROR(INDEX(sales!D:D,MATCH(D70,sales!C:C,0)),"없음")} -> Mako | P70: {=IFERROR(INDEX(sales!E:E,MATCH(D70,sales!C:C,0)),"없음")} -> MPS | Q70: {=IFERROR(INDEX(sales!C:C,MATCH(D70,sales!C:C,0)),"list없음")} -> sol.jung@stryker.com
A72: 72 | B72: James Kang | D72: James.Kang@stryker.com | E72: Director, ICM, East Asia | F72: Sales and Marketing Job Family Group | G72: Sales Strategy | H72: {=IFERROR(INDEX(Lease_List!D:D,MATCH(All_User!D72,Lease_List!H:H,0)),"없음")} -> 5CD5179KJ2 | I72: 5CG2181LCX | K72: {=IFERROR(INDEX(Ipad_List!C:C,MATCH(All_User!D72,Ipad_List!J:J,0)),"없음")} -> VKGPQR7276 | L72: {=IFERROR(INDEX(TeamsNumber!B:B,MATCH(All_User!D72,TeamsNumber!D:D,0)),"없음")} -> tel:+82234517570 | M72: {=IFERROR(INDEX(Printer!D:D,MATCH(All_User!D72,Printer!H:H,0)),"없음")} -> 없음 | N72: {=IFERROR(INDEX(Monitor!A:A,MATCH(D72,Monitor!D:D,0)),"없음")} -> LCD 모니터 | O72: {=IFERROR(INDEX(sales!D:D,MATCH(D72,sales!C:C,0)),"없음")} -> 없음 | P72: {=IFERROR(INDEX(sales!E:E,MATCH(D72,sales!C:C,0)),"없음")} -> 없음
A73: 73 | B73: Louis Kang | C73: 강원영 | D73: louis.kang@stryker.com | E73: Lead Sales Representative | F73: Sales and Marketing Job Family Group | G73: Indirect Sales | H73: {=IFERROR(INDEX(Lease_List!D:D,MATCH(All_User!D73,Lease_List!H:H,0)),"없음")} -> 5CD5179KHH | I73: 5CG2181LVF | K73: {=IFERROR(INDEX(Ipad_List!C:C,MATCH(All_User!D73,Ipad_List!J:J,0)),"없음")} -> H7Q22YXYWF | L73: {=IFERROR(INDEX(TeamsNumber!B:B,MATCH(All_User!D73,TeamsNumber!D:D,0)),"없음")} -> tel:+82234517550 | M73: {=IFERROR(INDEX(Printer!D:D,MATCH(All_User!D73,Printer!H:H,0)),"없음")} -> SL-C563W | N73: {=IFERROR(INDEX(Monitor!A:A,MATCH(D73,Monitor!D:D,0)),"없음")} -> 없음 | O73: {=IFERROR(INDEX(sales!D:D,MATCH(D73,sales!C:C,0)),"없음")} -> Knee | P73: {=IFERROR(INDEX(sales!E:E,MATCH(D73,sales!C:C,0)),"없음")} -> Sales | Q73: {=IFERROR(INDEX(sales!C:C,MATCH(D73,sales!C:C,0)),"list없음")} -> louis.kang@stryker.com
A74: 74 | B74: Chloe Kang | C74: 강혜영 | D74: chloe.kang@stryker.com | E74: Executive Assistant & Office Manager | F74: Administration Job Family Group | G74: Administration | H74: {=IFERROR(INDEX(Lease_List!D:D,MATCH(All_User!D74,Lease_List!H:H,0)),"없음")} -> 5CD5179KHM | I74: 없음 | K74: {=IFERROR(INDEX(Ipad_List!C:C,MATCH(All_User!D74,Ipad_List!J:J,0)),"없음")} -> 없음 | L74: {=IFERROR(INDEX(TeamsNumber!B:B,MATCH(All_User!D74,TeamsNumber!D:D,0)),"없음")} -> tel:+82234517543 | M74: {=IFERROR(INDEX(Printer!D:D,MATCH(All_User!D74,Printer!H:H,0)),"없음")} -> 없음 | N74: {=IFERROR(INDEX(Monitor!A:A,MATCH(D74,Monitor!D:D,0)),"없음")} -> LCD 모니터 | O74: {=IFERROR(INDEX(sales!D:D,MATCH(D74,sales!C:C,0)),"없음")} -> 없음 | P74: {=IFERROR(INDEX(sales!E:E,MATCH(D74,sales!C:C,0)),"없음")} -> 없음
A76: 76 | B76: Leslie Kim | C76: 김지연 | D76: Leslie.kim@stryker.com | E76: Director, RA/QA and Reimbursement | F76: RAQA Job Family Group | G76: RAQA | H76: {=IFERROR(INDEX(Lease_List!D:D,MATCH(All_User!D76,Lease_List!H:H,0)),"없음")} -> 5CD4232BF3 | I76: 없음 | K76: {=IFERROR(INDEX(Ipad_List!C:C,MATCH(All_User!D76,Ipad_List!J:J,0)),"없음")} -> TRW5JJG7JP | L76: {=IFERROR(INDEX(TeamsNumber!B:B,MATCH(All_User!D76,TeamsNumber!D:D,0)),"없음")} -> tel:+82234517524 | M76: {=IFERROR(INDEX(Printer!D:D,MATCH(All_User!D76,Printer!H:H,0)),"없음")} -> 없음 | N76: {=IFERROR(INDEX(Monitor!A:A,MATCH(D76,Monitor!D:D,0)),"없음")} -> LCD 모니터 | O76: {=IFERROR(INDEX(sales!D:D,MATCH(D76,sales!C:C,0)),"없음")} -> 없음 | P76: {=IFERROR(INDEX(sales!E:E,MATCH(D76,sales!C:C,0)),"없음")} -> 없음
A77: 77 | B77: Justin Kim | C77: 김정오 | D77: Justin.Kim@stryker.com | E77: Mako Capital Sales Manager | F77: Sales and Marketing Job Family Group | G77: Direct Sales | H77: {=IFERROR(INDEX(Lease_List!D:D,MATCH(All_User!D77,Lease_List!H:H,0)),"없음")} -> 5CD5062YF1 | I77: 없음 | K77: {=IFERROR(INDEX(Ipad_List!C:C,MATCH(All_User!D77,Ipad_List!J:J,0)),"없음")} -> THD6Q4W3LT | L77: {=IFERROR(INDEX(TeamsNumber!B:B,MATCH(All_User!D77,TeamsNumber!D:D,0)),"없음")} -> tel:+82234517558 | M77: {=IFERROR(INDEX(Printer!D:D,MATCH(All_User!D77,Printer!H:H,0)),"없음")} -> SL-C565W | N77: {=IFERROR(INDEX(Monitor!A:A,MATCH(D77,Monitor!D:D,0)),"없음")} -> 없음 | O77: {=IFERROR(INDEX(sales!D:D,MATCH(D77,sales!C:C,0)),"없음")} -> Mako | P77: {=IFERROR(INDEX(sales!E:E,MATCH(D77,sales!C:C,0)),"없음")} -> Sales | Q77: {=IFERROR(INDEX(sales!C:C,MATCH(D77,sales!C:C,0)),"list없음")} -> Justin.Kim@stryker.com
A78: 78 | B78: Sue Kim | C78: 김정숙 | D78: Sue.Kim@stryker.com | E78: Business Unit Director | F78: Sales and Marketing Job Family Group | G78: Sales and Marketing | H78: {=IFERROR(INDEX(Lease_List!D:D,MATCH(All_User!D78,Lease_List!H:H,0)),"없음")} -> 5CD409908M | I78: 없음 | K78: {=IFERROR(INDEX(Ipad_List!C:C,MATCH(All_User!D78,Ipad_List!J:J,0)),"없음")} -> DDPWWYNVPX | L78: {=IFERROR(INDEX(TeamsNumber!B:B,MATCH(All_User!D78,TeamsNumber!D:D,0)),"없음")} -> tel:+82234517676 | M78: {=IFERROR(INDEX(Printer!D:D,MATCH(All_User!D78,Printer!H:H,0)),"없음")} -> 확인중 | N78: {=IFERROR(INDEX(Monitor!A:A,MATCH(D78,Monitor!D:D,0)),"없음")} -> 없음 | O78: {=IFERROR(INDEX(sales!D:D,MATCH(D78,sales!C:C,0)),"없음")} -> 0 | P78: {=IFERROR(INDEX(sales!E:E,MATCH(D78,sales!C:C,0)),"없음")} -> 0
A79: 79 | B79: Danny Kim | C79: 김문호 | D79: danny.kim@stryker.com | E79: Sales Manager | F79: Sales and Marketing Job Family Group | G79: Indirect Sales | H79: {=IFERROR(INDEX(Lease_List!D:D,MATCH(All_User!D79,Lease_List!H:H,0)),"없음")} -> 5CD4232BFN | I79: 없음 | K79: {=IFERROR(INDEX(Ipad_List!C:C,MATCH(All_User!D79,Ipad_List!J:J,0)),"없음")} -> DWFLMWX243 | L79: {=IFERROR(INDEX(TeamsNumber!B:B,MATCH(All_User!D79,TeamsNumber!D:D,0)),"없음")} -> tel:+82234517530 | M79: {=IFERROR(INDEX(Printer!D:D,MATCH(All_User!D79,Printer!H:H,0)),"없음")} -> SL-C563W | N79: {=IFERROR(INDEX(Monitor!A:A,MATCH(D79,Monitor!D:D,0)),"없음")} -> 없음 | O79: {=IFERROR(INDEX(sales!D:D,MATCH(D79,sales!C:C,0)),"없음")} -> MedSurg | P79: {=IFERROR(INDEX(sales!E:E,MATCH(D79,sales!C:C,0)),"없음")} -> Sales | Q79: {=IFERROR(INDEX(sales!C:C,MATCH(D79,sales!C:C,0)),"list없음")} -> danny.kim@stryker.com
A80: 80 | B80: Rayna Kim | C80: 김지연 | D80: Rayna.Kim@stryker.com | E80: Senior Marketing Specialist, Neurovascular, Korea | F80: Sales and Marketing Job Family Group | G80: Advertising/Marketing Communications | H80: {=IFERROR(INDEX(Lease_List!D:D,MATCH(All_User!D80,Lease_List!H:H,0)),"없음")} -> 5CD5179KJB | I80: 5CG2181LCT | K80: {=IFERROR(INDEX(Ipad_List!C:C,MATCH(All_User!D80,Ipad_List!J:J,0)),"없음")} -> FQPW2GVP7C | L80: {=IFERROR(INDEX(TeamsNumber!B:B,MATCH(All_User!D80,TeamsNumber!D:D,0)),"없음")} -> tel:+82234517680 | M80: {=IFERROR(INDEX(Printer!D:D,MATCH(All_User!D80,Printer!H:H,0)),"없음")} -> 없음 | N80: {=IFERROR(INDEX(Monitor!A:A,MATCH(D80,Monitor!D:D,0)),"없음")} -> 없음 | O80: {=IFERROR(INDEX(sales!D:D,MATCH(D80,sales!C:C,0)),"없음")} -> 0 | P80: {=IFERROR(INDEX(sales!E:E,MATCH(D80,sales!C:C,0)),"없음")} -> MKT | Q80: {=IFERROR(INDEX(sales!C:C,MATCH(D80,sales!C:C,0)),"list없음")} -> Rayna.Kim@stryker.com
A81: 81 | B81: Suhyun Kim | C81: 김수현 | D81: Suhyun.Kim@stryker.com | E81: Associate Sales Manager | F81: Sales and Marketing Job Family Group | G81: Sales and Marketing | H81: {=IFERROR(INDEX(Lease_List!D:D,MATCH(All_User!D81,Lease_List!H:H,0)),"없음")} -> 5CD409908J | I81: 없음 | K81: {=IFERROR(INDEX(Ipad_List!C:C,MATCH(All_User!D81,Ipad_List!J:J,0)),"없음")} -> MQ6X021QX2 | L81: {=IFERROR(INDEX(TeamsNumber!B:B,MATCH(All_User!D81,TeamsNumber!D:D,0)),"없음")} -> tel:+82234517598 | M81: {=IFERROR(INDEX(Printer!D:D,MATCH(All_User!D81,Printer!H:H,0)),"없음")} -> SL-C486FW | N81: {=IFERROR(INDEX(Monitor!A:A,MATCH(D81,Monitor!D:D,0)),"없음")} -> 없음 | O81: {=IFERROR(INDEX(sales!D:D,MATCH(D81,sales!C:C,0)),"없음")} -> Implants | P81: {=IFERROR(INDEX(sales!E:E,MATCH(D81,sales!C:C,0)),"없음")} -> Sales | Q81: {=IFERROR(INDEX(sales!C:C,MATCH(D81,sales!C:C,0)),"list없음")} -> Suhyun.Kim@stryker.com
A82: 82 | B82: Yoori Kim | C82: 김유리 | D82: yoori.kim@stryker.com | E82: HR Director, Korea and East Asia Functions | F82: Human Resources Job Family Group | G82: Human Resources Generalist | H82: {=IFERROR(INDEX(Lease_List!D:D,MATCH(All_User!D82,Lease_List!H:H,0)),"없음")} -> 5CD409908K | I82: 없음 | K82: {=IFERROR(INDEX(Ipad_List!C:C,MATCH(All_User!D82,Ipad_List!J:J,0)),"없음")} -> C14X1226DV | L82: {=IFERROR(INDEX(TeamsNumber!B:B,MATCH(All_User!D82,TeamsNumber!D:D,0)),"없음")} -> tel:+82234517540 | M82: {=IFERROR(INDEX(Printer!D:D,MATCH(All_User!D82,Printer!H:H,0)),"없음")} -> 없음 | N82: {=IFERROR(INDEX(Monitor!A:A,MATCH(D82,Monitor!D:D,0)),"없음")} -> 없음 | O82: {=IFERROR(INDEX(sales!D:D,MATCH(D82,sales!C:C,0)),"없음")} -> 없음 | P82: {=IFERROR(INDEX(sales!E:E,MATCH(D82,sales!C:C,0)),"없음")} -> 없음
A83: 83 | B83: Songmin Kim | C83: 김송민 | D83: songmin.kim@stryker.com | E83: Manager, Market Access | F83: Compliance Job Family Group | G83: Healthcare Economics | H83: {=IFERROR(INDEX(Lease_List!D:D,MATCH(All_User!D83,Lease_List!H:H,0)),"없음")} -> 5CD3469HDJ | I83: 없음 | K83: {=IFERROR(INDEX(Ipad_List!C:C,MATCH(All_User!D83,Ipad_List!J:J,0)),"없음")} -> 없음 | L83: {=IFERROR(INDEX(TeamsNumber!B:B,MATCH(All_User!D83,TeamsNumber!D:D,0)),"없음")} -> tel:+82234517633 | M83: {=IFERROR(INDEX(Printer!D:D,MATCH(All_User!D83,Printer!H:H,0)),"없음")} -> 없음 | N83: {=IFERROR(INDEX(Monitor!A:A,MATCH(D83,Monitor!D:D,0)),"없음")} -> 없음 | O83: {=IFERROR(INDEX(sales!D:D,MATCH(D83,sales!C:C,0)),"없음")} -> 없음 | P83: {=IFERROR(INDEX(sales!E:E,MATCH(D83,sales!C:C,0)),"없음")} -> 없음
A84: 84 | B84: Jackson Kim | C84: 김정연 | D84: jackson.kim@stryker.com | E84: Product Manager, Neurovascular | F84: Sales and Marketing Job Family Group | G84: Product Management | H84: {=IFERROR(INDEX(Lease_List!D:D,MATCH(All_User!D84,Lease_List!H:H,0)),"없음")} -> 5CD5179KJ1 | I84: 5CG2181LXH | K84: {=IFERROR(INDEX(Ipad_List!C:C,MATCH(All_User!D84,Ipad_List!J:J,0)),"없음")} -> MK21Q5L65C | L84: {=IFERROR(INDEX(TeamsNumber!B:B,MATCH(All_User!D84,TeamsNumber!D:D,0)),"없음")} -> tel:+82234517685 | M84: {=IFERROR(INDEX(Printer!D:D,MATCH(All_User!D84,Printer!H:H,0)),"없음")} -> 확인중 | N84: {=IFERROR(INDEX(Monitor!A:A,MATCH(D84,Monitor!D:D,0)),"없음")} -> 없음 | O84: {=IFERROR(INDEX(sales!D:D,MATCH(D84,sales!C:C,0)),"없음")} -> 0 | P84: {=IFERROR(INDEX(sales!E:E,MATCH(D84,sales!C:C,0)),"없음")} -> Sales | Q84: {=IFERROR(INDEX(sales!C:C,MATCH(D84,sales!C:C,0)),"list없음")} -> jackson.kim@stryker.com
A85: 85 | B85: Genie Kim | C85: 김현진 | D85: genie.kim@stryker.com | E85: Senior Sales Representative | F85: Sales and Marketing Job Family Group | G85: Indirect Sales | H85: {=IFERROR(INDEX(Lease_List!D:D,MATCH(All_User!D85,Lease_List!H:H,0)),"없음")} -> 5CD5179KHX | I85: 5CG2181LW3 | K85: {=IFERROR(INDEX(Ipad_List!C:C,MATCH(All_User!D85,Ipad_List!J:J,0)),"없음")} -> J9157FQXYM | L85: {=IFERROR(INDEX(TeamsNumber!B:B,MATCH(All_User!D85,TeamsNumber!D:D,0)),"없음")} -> tel:+82234517596 | M85: {=IFERROR(INDEX(Printer!D:D,MATCH(All_User!D85,Printer!H:H,0)),"없음")} -> 반납 | N85: {=IFERROR(INDEX(Monitor!A:A,MATCH(D85,Monitor!D:D,0)),"없음")} -> 없음 | O85: {=IFERROR(INDEX(sales!D:D,MATCH(D85,sales!C:C,0)),"없음")} -> Implants | P85: {=IFERROR(INDEX(sales!E:E,MATCH(D85,sales!C:C,0)),"없음")} -> Sales | Q85: {=IFERROR(INDEX(sales!C:C,MATCH(D85,sales!C:C,0)),"list없음")} -> genie.kim@stryker.com
A86: 86 | B86: Jason Kim | C86: 김재헌 | D86: jason.kim1@stryker.com | E86: Lead Sales Representative | F86: Sales and Marketing Job Family Group | G86: Indirect Sales | H86: {=IFERROR(INDEX(Lease_List!D:D,MATCH(All_User!D86,Lease_List!H:H,0)),"없음")} -> 5CD5062YDG | I86: 5CG2181LVN | K86: {=IFERROR(INDEX(Ipad_List!C:C,MATCH(All_User!D86,Ipad_List!J:J,0)),"없음")} -> M6T0VJHK6P | L86: {=IFERROR(INDEX(TeamsNumber!B:B,MATCH(All_User!D86,TeamsNumber!D:D,0)),"없음")} -> tel:+82234517597 | M86: {=IFERROR(INDEX(Printer!D:D,MATCH(All_User!D86,Printer!H:H,0)),"없음")} -> 2차 조사 정보 없음 | N86: {=IFERROR(INDEX(Monitor!A:A,MATCH(D86,Monitor!D:D,0)),"없음")} -> 없음 | O86: {=IFERROR(INDEX(sales!D:D,MATCH(D86,sales!C:C,0)),"없음")} -> Implants | P86: {=IFERROR(INDEX(sales!E:E,MATCH(D86,sales!C:C,0)),"없음")} -> Sales | Q86: {=IFERROR(INDEX(sales!C:C,MATCH(D86,sales!C:C,0)),"list없음")} -> jason.kim1@stryker.com
A87: 87 | B87: Henry Kim | C87: 김한성 | D87: henry.kim1@stryker.com | E87: Senior Sales Representative, Neurovascular, Korea | F87: Sales and Marketing Job Family Group | G87: Direct Sales | H87: {=IFERROR(INDEX(Lease_List!D:D,MATCH(All_User!D87,Lease_List!H:H,0)),"없음")} -> 5CD409908L | I87: 없음 | K87: {=IFERROR(INDEX(Ipad_List!C:C,MATCH(All_User!D87,Ipad_List!J:J,0)),"없음")} -> R75T7C9N17 | L87: {=IFERROR(INDEX(TeamsNumber!B:B,MATCH(All_User!D87,TeamsNumber!D:D,0)),"없음")} -> tel:+82234517687 | M87: {=IFERROR(INDEX(Printer!D:D,MATCH(All_User!D87,Printer!H:H,0)),"없음")} -> SL-C486FW | N87: {=IFERROR(INDEX(Monitor!A:A,MATCH(D87,Monitor!D:D,0)),"없음")} -> 없음 | O87: {=IFERROR(INDEX(sales!D:D,MATCH(D87,sales!C:C,0)),"없음")} -> NV | P87: {=IFERROR(INDEX(sales!E:E,MATCH(D87,sales!C:C,0)),"없음")} -> NV | Q87: {=IFERROR(INDEX(sales!C:C,MATCH(D87,sales!C:C,0)),"list없음")} -> henry.kim1@stryker.com
A89: 89 | B89: Yeonjoo Kim | C89: 김연주 | D89: yeonjoo.kim@stryker.com | E89: Product Manager | F89: Sales and Marketing Job Family Group | G89: Product Management | H89: {=IFERROR(INDEX(Lease_List!D:D,MATCH(All_User!D89,Lease_List!H:H,0)),"없음")} -> 5CD4232BF7 | I89: 없음 | K89: {=IFERROR(INDEX(Ipad_List!C:C,MATCH(All_User!D89,Ipad_List!J:J,0)),"없음")} -> HYFKQFR4RD | L89: {=IFERROR(INDEX(TeamsNumber!B:B,MATCH(All_User!D89,TeamsNumber!D:D,0)),"없음")} -> tel:+82234517560 | M89: {=IFERROR(INDEX(Printer!D:D,MATCH(All_User!D89,Printer!H:H,0)),"없음")} -> SL-C563W | N89: {=IFERROR(INDEX(Monitor!A:A,MATCH(D89,Monitor!D:D,0)),"없음")} -> 없음 | O89: {=IFERROR(INDEX(sales!D:D,MATCH(D89,sales!C:C,0)),"없음")} -> 0 | P89: {=IFERROR(INDEX(sales!E:E,MATCH(D89,sales!C:C,0)),"없음")} -> MKT | Q89: {=IFERROR(INDEX(sales!C:C,MATCH(D89,sales!C:C,0)),"list없음")} -> yeonjoo.kim@stryker.com
A90: 90 | B90: William Kim | C90: 김성진 | D90: william.kim1@stryker.com | E90: Finance Manager | F90: Finance Job Family Group | G90: Accounting | H90: {=IFERROR(INDEX(Lease_List!D:D,MATCH(All_User!D90,Lease_List!H:H,0)),"없음")} -> 5CD4305D8Q | I90: 없음 | K90: {=IFERROR(INDEX(Ipad_List!C:C,MATCH(All_User!D90,Ipad_List!J:J,0)),"없음")} -> 없음 | L90: {=IFERROR(INDEX(TeamsNumber!B:B,MATCH(All_User!D90,TeamsNumber!D:D,0)),"없음")} -> tel:+82234517646 | M90: {=IFERROR(INDEX(Printer!D:D,MATCH(All_User!D90,Printer!H:H,0)),"없음")} -> 없음 | N90: {=IFERROR(INDEX(Monitor!A:A,MATCH(D90,Monitor!D:D,0)),"없음")} -> 없음 | O90: {=IFERROR(INDEX(sales!D:D,MATCH(D90,sales!C:C,0)),"없음")} -> 없음 | P90: {=IFERROR(INDEX(sales!E:E,MATCH(D90,sales!C:C,0)),"없음")} -> 없음
A91: 91 | B91: Terry Kim | C91: 김용석 | D91: terry.kim@stryker.com | E91: Lead FP&A Analyst, Finance | F91: Finance Job Family Group | G91: Financial Planning and Analysis | H91: {=IFERROR(INDEX(Lease_List!D:D,MATCH(All_User!D91,Lease_List!H:H,0)),"없음")} -> 5CD5179KHJ | I91: 없음 | K91: {=IFERROR(INDEX(Ipad_List!C:C,MATCH(All_User!D91,Ipad_List!J:J,0)),"없음")} -> 없음 | L91: {=IFERROR(INDEX(TeamsNumber!B:B,MATCH(All_User!D91,TeamsNumber!D:D,0)),"없음")} -> tel:+82234517647 | M91: {=IFERROR(INDEX(Printer!D:D,MATCH(All_User!D91,Printer!H:H,0)),"없음")} -> 없음 | N91: {=IFERROR(INDEX(Monitor!A:A,MATCH(D91,Monitor!D:D,0)),"없음")} -> LCD 모니터 | O91: {=IFERROR(INDEX(sales!D:D,MATCH(D91,sales!C:C,0)),"없음")} -> 없음 | P91: {=IFERROR(INDEX(sales!E:E,MATCH(D91,sales!C:C,0)),"없음")} -> 없음
A92: 92 | B92: Ahyoung Kim | C92: 김아영 | D92: ahyoung.kim@stryker.com | E92: Lead Specialist Regulatory Affairs Quality Assurance | F92: RAQA Job Family Group | G92: RAQA Compliance | H92: {=IFERROR(INDEX(Lease_List!D:D,MATCH(All_User!D92,Lease_List!H:H,0)),"없음")} -> 5CD3469HDV | I92: 없음 | K92: {=IFERROR(INDEX(Ipad_List!C:C,MATCH(All_User!D92,Ipad_List!J:J,0)),"없음")} -> 없음 | L92: {=IFERROR(INDEX(TeamsNumber!B:B,MATCH(All_User!D92,TeamsNumber!D:D,0)),"없음")} -> tel:+82234517638 | M92: {=IFERROR(INDEX(Printer!D:D,MATCH(All_User!D92,Printer!H:H,0)),"없음")} -> 없음 | N92: {=IFERROR(INDEX(Monitor!A:A,MATCH(D92,Monitor!D:D,0)),"없음")} -> 없음 | O92: {=IFERROR(INDEX(sales!D:D,MATCH(D92,sales!C:C,0)),"없음")} -> 없음 | P92: {=IFERROR(INDEX(sales!E:E,MATCH(D92,sales!C:C,0)),"없음")} -> 없음
A93: 93 | B93: Jayden Kim | C93: 김민재 | D93: jayden.kim@stryker.com | E93: Senior Sales Representative | F93: Sales and Marketing Job Family Group | G93: Direct Sales | H93: {=IFERROR(INDEX(Lease_List!D:D,MATCH(All_User!D93,Lease_List!H:H,0)),"없음")} -> 5CD4305D8W | I93: 없음 | K93: {=IFERROR(INDEX(Ipad_List!C:C,MATCH(All_User!D93,Ipad_List!J:J,0)),"없음")} -> P7Q3X0HYFW | L93: {=IFERROR(INDEX(TeamsNumber!B:B,MATCH(All_User!D93,TeamsNumber!D:D,0)),"없음")} -> tel:+82234517582 | M93: {=IFERROR(INDEX(Printer!D:D,MATCH(All_User!D93,Printer!H:H,0)),"없음")} -> SL-C563W | N93: {=IFERROR(INDEX(Monitor!A:A,MATCH(D93,Monitor!D:D,0)),"없음")} -> 없음 | O93: {=IFERROR(INDEX(sales!D:D,MATCH(D93,sales!C:C,0)),"없음")} -> Mako | P93: {=IFERROR(INDEX(sales!E:E,MATCH(D93,sales!C:C,0)),"없음")} -> Sales | Q93: {=IFERROR(INDEX(sales!C:C,MATCH(D93,sales!C:C,0)),"list없음")} -> jayden.kim@stryker.com
A95: 95 | B95: Dongkyu Kim | C95: 김동규 | D95: dongkyu.kim@stryker.com | E95: Associate Mako Product Specialist | F95: Sales and Marketing Job Family Group | G95: Medical Education | H95: {=IFERROR(INDEX(Lease_List!D:D,MATCH(All_User!D95,Lease_List!H:H,0)),"없음")} -> 5CD4305D81 | I95: 없음 | K95: {=IFERROR(INDEX(Ipad_List!C:C,MATCH(All_User!D95,Ipad_List!J:J,0)),"없음")} -> F9XWF4345F | L95: {=IFERROR(INDEX(TeamsNumber!B:B,MATCH(All_User!D95,TeamsNumber!D:D,0)),"없음")} -> tel:+82234517536 | M95: {=IFERROR(INDEX(Printer!D:D,MATCH(All_User!D95,Printer!H:H,0)),"없음")} -> 없음 | N95: {=IFERROR(INDEX(Monitor!A:A,MATCH(D95,Monitor!D:D,0)),"없음")} -> 없음 | O95: {=IFERROR(INDEX(sales!D:D,MATCH(D95,sales!C:C,0)),"없음")} -> Mako | P95: {=IFERROR(INDEX(sales!E:E,MATCH(D95,sales!C:C,0)),"없음")} -> MPS | Q95: {=IFERROR(INDEX(sales!C:C,MATCH(D95,sales!C:C,0)),"list없음")} -> dongkyu.kim@stryker.com
A96: 96 | B96: Minki Kim | C96: 김민기 | D96: minki.kim@stryker.com | E96: Marketing Manager, Implants, Korea | F96: Sales and Marketing Job Family Group | G96: Product Management | H96: {=IFERROR(INDEX(Lease_List!D:D,MATCH(All_User!D96,Lease_List!H:H,0)),"없음")} -> 5CD442C07F | I96: 없음 | K96: {=IFERROR(INDEX(Ipad_List!C:C,MATCH(All_User!D96,Ipad_List!J:J,0)),"없음")} -> XGH27YLWQM | L96: {=IFERROR(INDEX(TeamsNumber!B:B,MATCH(All_User!D96,TeamsNumber!D:D,0)),"없음")} -> tel:+82234517555 | M96: {=IFERROR(INDEX(Printer!D:D,MATCH(All_User!D96,Printer!H:H,0)),"없음")} -> 없음 | N96: {=IFERROR(INDEX(Monitor!A:A,MATCH(D96,Monitor!D:D,0)),"없음")} -> 없음 | O96: {=IFERROR(INDEX(sales!D:D,MATCH(D96,sales!C:C,0)),"없음")} -> 0 | P96: {=IFERROR(INDEX(sales!E:E,MATCH(D96,sales!C:C,0)),"없음")} -> MKT | Q96: {=IFERROR(INDEX(sales!C:C,MATCH(D96,sales!C:C,0)),"list없음")} -> minki.kim@stryker.com
A97: 97 | B97: Soyoun Kim | C97: 김소연 | D97: soyoun.kim@stryker.com | E97: Compliance Officer, East Asia | F97: Compliance Job Family Group | G97: Compliance | H97: {=IFERROR(INDEX(Lease_List!D:D,MATCH(All_User!D97,Lease_List!H:H,0)),"없음")} -> 5CD5179KH1 | I97: 5CG2181LW5 | K97: {=IFERROR(INDEX(Ipad_List!C:C,MATCH(All_User!D97,Ipad_List!J:J,0)),"없음")} -> QT422FMH26 | L97: {=IFERROR(INDEX(TeamsNumber!B:B,MATCH(All_User!D97,TeamsNumber!D:D,0)),"없음")} -> tel:+82234517529 | M97: {=IFERROR(INDEX(Printer!D:D,MATCH(All_User!D97,Printer!H:H,0)),"없음")} -> 없음 | N97: {=IFERROR(INDEX(Monitor!A:A,MATCH(D97,Monitor!D:D,0)),"없음")} -> 없음 | O97: {=IFERROR(INDEX(sales!D:D,MATCH(D97,sales!C:C,0)),"없음")} -> 없음 | P97: {=IFERROR(INDEX(sales!E:E,MATCH(D97,sales!C:C,0)),"없음")} -> 없음
A98: 98 | B98: Hailey Kim | C98: 김정화 | D98: hailey.kim@stryker.com | E98: Senior Accountant | F98: Finance Job Family Group | G98: Accounts Payable/Receivable | H98: {=IFERROR(INDEX(Lease_List!D:D,MATCH(All_User!D98,Lease_List!H:H,0)),"없음")} -> 5CD442C07B | I98: 5CG2181LXO | K98: {=IFERROR(INDEX(Ipad_List!C:C,MATCH(All_User!D98,Ipad_List!J:J,0)),"없음")} -> 없음 | L98: {=IFERROR(INDEX(TeamsNumber!B:B,MATCH(All_User!D98,TeamsNumber!D:D,0)),"없음")} -> tel:+82234517601 | M98: {=IFERROR(INDEX(Printer!D:D,MATCH(All_User!D98,Printer!H:H,0)),"없음")} -> 없음 | N98: {=IFERROR(INDEX(Monitor!A:A,MATCH(D98,Monitor!D:D,0)),"없음")} -> 없음 | O98: {=IFERROR(INDEX(sales!D:D,MATCH(D98,sales!C:C,0)),"없음")} -> 없음 | P98: {=IFERROR(INDEX(sales!E:E,MATCH(D98,sales!C:C,0)),"없음")} -> 없음
A99: 99 | B99: Mason Kim | C99: 김오현 | D99: mason.kim1@stryker.com | E99: Associate MAKO Product Specialist | F99: Sales and Marketing Job Family Group | G99: Medical Education | H99: {=IFERROR(INDEX(Lease_List!D:D,MATCH(All_User!D99,Lease_List!H:H,0)),"없음")} -> 5CD4145N3K | I99: 없음 | K99: {=IFERROR(INDEX(Ipad_List!C:C,MATCH(All_User!D99,Ipad_List!J:J,0)),"없음")} -> P40KK7NLQG | L99: {=IFERROR(INDEX(TeamsNumber!B:B,MATCH(All_User!D99,TeamsNumber!D:D,0)),"없음")} -> tel:+82234517692 | M99: {=IFERROR(INDEX(Printer!D:D,MATCH(All_User!D99,Printer!H:H,0)),"없음")} -> 없음 | N99: {=IFERROR(INDEX(Monitor!A:A,MATCH(D99,Monitor!D:D,0)),"없음")} -> 없음 | O99: {=IFERROR(INDEX(sales!D:D,MATCH(D99,sales!C:C,0)),"없음")} -> Mako | P99: {=IFERROR(INDEX(sales!E:E,MATCH(D99,sales!C:C,0)),"없음")} -> MPS | Q99: {=IFERROR(INDEX(sales!C:C,MATCH(D99,sales!C:C,0)),"list없음")} -> mason.kim1@stryker.com
A100: 100 | B100: Mindo Kim | C100: 김민도 | D100: mindo.kim@stryker.com | E100: Associate Mako Product Specialist | F100: Sales and Marketing Job Family Group | G100: Medical Education | H100: {=IFERROR(INDEX(Lease_List!D:D,MATCH(All_User!D100,Lease_List!H:H,0)),"없음")} -> 없음 | I100: 없음 | J100: 5CG2261LCV | K100: {=IFERROR(INDEX(Ipad_List!C:C,MATCH(All_User!D100,Ipad_List!J:J,0)),"없음")} -> LY9JGJQMTP | L100: {=IFERROR(INDEX(TeamsNumber!B:B,MATCH(All_User!D100,TeamsNumber!D:D,0)),"없음")} -> tel:+82234517615 | M100: {=IFERROR(INDEX(Printer!D:D,MATCH(All_User!D100,Printer!G:G,0)),"없음")} -> 없음 | N100: {=IFERROR(INDEX(Monitor!A:A,MATCH(D100,Monitor!D:D,0)),"없음")} -> 없음 | O100: {=IFERROR(INDEX(sales!D:D,MATCH(D100,sales!C:C,0)),"없음")} -> Mako | P100: {=IFERROR(INDEX(sales!E:E,MATCH(D100,sales!C:C,0)),"없음")} -> MPS | Q100: {=IFERROR(INDEX(sales!C:C,MATCH(D100,sales!C:C,0)),"list없음")} -> mindo.kim@stryker.com
A101: 101 | B101: Aspyn Kim | C101: 김주희 | D101: aspyn.kim@stryker.com | E101: Associate Mako Product Specialist | F101: Sales and Marketing Job Family Group | G101: Medical Education | H101: {=IFERROR(INDEX(Lease_List!D:D,MATCH(All_User!D101,Lease_List!H:H,0)),"없음")} -> 없음 | I101: 5CG2181LWV | J101: 5CG2181LWV | K101: {=IFERROR(INDEX(Ipad_List!C:C,MATCH(All_User!D101,Ipad_List!J:J,0)),"없음")} -> JJWL6VTHKK | L101: {=IFERROR(INDEX(TeamsNumber!B:B,MATCH(All_User!D101,TeamsNumber!D:D,0)),"없음")} -> tel:+82234517620 | M101: {=IFERROR(INDEX(Printer!D:D,MATCH(All_User!D101,Printer!G:G,0)),"없음")} -> 없음 | N101: {=IFERROR(INDEX(Monitor!A:A,MATCH(D101,Monitor!D:D,0)),"없음")} -> 없음 | O101: {=IFERROR(INDEX(sales!D:D,MATCH(D101,sales!C:C,0)),"없음")} -> Mako | P101: {=IFERROR(INDEX(sales!E:E,MATCH(D101,sales!C:C,0)),"없음")} -> MPS | Q101: {=IFERROR(INDEX(sales!C:C,MATCH(D101,sales!C:C,0)),"list없음")} -> aspyn.kim@stryker.com
A102: 102 | B102: Minjeong Kim | C102: 김민정 | D102: minjeong.kim@stryker.com | E102: Associate Mako Product Specialist | F102: Sales and Marketing Job Family Group | G102: Medical Education | H102: {=IFERROR(INDEX(Lease_List!D:D,MATCH(All_User!D102,Lease_List!H:H,0)),"없음")} -> 5CD442C075 | I102: 없음 | K102: {=IFERROR(INDEX(Ipad_List!C:C,MATCH(All_User!D102,Ipad_List!J:J,0)),"없음")} -> K9NWHMWT44 | L102: {=IFERROR(INDEX(TeamsNumber!B:B,MATCH(All_User!D102,TeamsNumber!D:D,0)),"없음")} -> tel:+82234517628 | M102: {=IFERROR(INDEX(Printer!D:D,MATCH(All_User!D102,Printer!H:H,0)),"없음")} -> 없음 | N102: {=IFERROR(INDEX(Monitor!A:A,MATCH(D102,Monitor!D:D,0)),"없음")} -> 없음 | O102: {=IFERROR(INDEX(sales!D:D,MATCH(D102,sales!C:C,0)),"없음")} -> Mako | P102: {=IFERROR(INDEX(sales!E:E,MATCH(D102,sales!C:C,0)),"없음")} -> MPS | Q102: {=IFERROR(INDEX(sales!C:C,MATCH(D102,sales!C:C,0)),"list없음")} -> minjeong.kim@stryker.com
A103: 103 | B103: Lina Kim | C103: 김인아 | D103: lina.kim@stryker.com | E103: Business Operation Specialist | F103: Sales and Marketing Job Family Group | G103: Sales Support | H103: {=IFERROR(INDEX(Lease_List!D:D,MATCH(All_User!D103,Lease_List!H:H,0)),"없음")} -> 5CD4305D8K | I103: 없음 | K103: {=IFERROR(INDEX(Ipad_List!C:C,MATCH(All_User!D103,Ipad_List!J:J,0)),"없음")} -> 없음 | L103: {=IFERROR(INDEX(TeamsNumber!B:B,MATCH(All_User!D103,TeamsNumber!D:D,0)),"없음")} -> tel:+82234517697 | M103: {=IFERROR(INDEX(Printer!D:D,MATCH(All_User!D103,Printer!H:H,0)),"없음")} -> 없음 | N103: {=IFERROR(INDEX(Monitor!A:A,MATCH(D103,Monitor!D:D,0)),"없음")} -> LCD 모니터 | O103: {=IFERROR(INDEX(sales!D:D,MATCH(D103,sales!C:C,0)),"없음")} -> 없음 | P103: {=IFERROR(INDEX(sales!E:E,MATCH(D103,sales!C:C,0)),"없음")} -> 없음
A104: 104 | B104: David Kim | C104: 김성준 | D104: david.kim3@stryker.com | E104: Lead Sales Representative | F104: Sales and Marketing Job Family Group | G104: Indirect Sales | H104: {=IFERROR(INDEX(Lease_List!D:D,MATCH(All_User!D104,Lease_List!H:H,0)),"없음")} -> 없음 | I104: 07/25/23 | K104: {=IFERROR(INDEX(Ipad_List!C:C,MATCH(All_User!D104,Ipad_List!J:J,0)),"없음")} -> HC0FP2JHG7 | L104: {=IFERROR(INDEX(TeamsNumber!B:B,MATCH(All_User!D104,TeamsNumber!D:D,0)),"없음")} -> tel:+82234517590 | M104: {=IFERROR(INDEX(Printer!D:D,MATCH(All_User!D104,Printer!G:G,0)),"없음")} -> 없음 | N104: {=IFERROR(INDEX(Monitor!A:A,MATCH(D104,Monitor!D:D,0)),"없음")} -> 없음 | O104: {=IFERROR(INDEX(sales!D:D,MATCH(D104,sales!C:C,0)),"없음")} -> MedSurg | P104: {=IFERROR(INDEX(sales!E:E,MATCH(D104,sales!C:C,0)),"없음")} -> Sales | Q104: {=IFERROR(INDEX(sales!C:C,MATCH(D104,sales!C:C,0)),"list없음")} -> david.kim3@stryker.com
A105: 105 | B105: James Kim | C105: 김재철 | D105: james.kim@stryker.com | E105: Lead Sales Representative | F105: Sales and Marketing Job Family Group | G105: Indirect Sales | H105: {=IFERROR(INDEX(Lease_List!D:D,MATCH(All_User!D105,Lease_List!H:H,0)),"없음")} -> 5CD5179KHQ | I105: 없음 | J105: 5CD32871LF | K105: {=IFERROR(INDEX(Ipad_List!C:C,MATCH(All_User!D105,Ipad_List!J:J,0)),"없음")} -> Q5M6F1YX19 | L105: {=IFERROR(INDEX(TeamsNumber!B:B,MATCH(All_User!D105,TeamsNumber!D:D,0)),"없음")} -> tel:+82234517696 | M105: {=IFERROR(INDEX(Printer!D:D,MATCH(All_User!D105,Printer!H:H,0)),"없음")} -> SL-C486FW | N105: {=IFERROR(INDEX(Monitor!A:A,MATCH(D105,Monitor!D:D,0)),"없음")} -> 없음 | O105: {=IFERROR(INDEX(sales!D:D,MATCH(D105,sales!C:C,0)),"없음")} -> Shoulder | P105: {=IFERROR(INDEX(sales!E:E,MATCH(D105,sales!C:C,0)),"없음")} -> Sales | Q105: {=IFERROR(INDEX(sales!C:C,MATCH(D105,sales!C:C,0)),"list없음")} -> james.kim@stryker.com
A106: 106 | B106: Hannah Kim | C106: 김예림 | D106: hannah.kim@stryker.com | E106: Associate Mako Product Specialist | F106: Sales and Marketing Job Family Group | G106: Medical Education | H106: {=IFERROR(INDEX(Lease_List!D:D,MATCH(All_User!D106,Lease_List!H:H,0)),"없음")} -> 5CD5062YF0 | I106: 없음 | K106: {=IFERROR(INDEX(Ipad_List!C:C,MATCH(All_User!D106,Ipad_List!J:J,0)),"없음")} -> VHJMJWTK6N | L106: {=IFERROR(INDEX(TeamsNumber!B:B,MATCH(All_User!D106,TeamsNumber!D:D,0)),"없음")} -> 없음 | M106: {=IFERROR(INDEX(Printer!D:D,MATCH(All_User!D106,Printer!H:H,0)),"없음")} -> 없음 | N106: {=IFERROR(INDEX(Monitor!A:A,MATCH(D106,Monitor!D:D,0)),"없음")} -> 없음 | O106: {=IFERROR(INDEX(sales!D:D,MATCH(D106,sales!C:C,0)),"없음")} -> Mako | P106: {=IFERROR(INDEX(sales!E:E,MATCH(D106,sales!C:C,0)),"없음")} -> MPS | Q106: {=IFERROR(INDEX(sales!C:C,MATCH(D106,sales!C:C,0)),"list없음")} -> hannah.kim@stryker.com
A107: 107 | B107: Greg Kim | C107: 김형근 | D107: greg.kim@stryker.com | E107: Regional Legal Counsel | F107: Legal Affairs Job Family Group | G107: Legal Generalist | H107: {=IFERROR(INDEX(Lease_List!D:D,MATCH(All_User!D107,Lease_List!H:H,0)),"없음")} -> 5CD4145N3P | I107: 없음 | K107: {=IFERROR(INDEX(Ipad_List!C:C,MATCH(All_User!D107,Ipad_List!J:J,0)),"없음")} -> 없음 | L107: {=IFERROR(INDEX(TeamsNumber!B:B,MATCH(All_User!D107,TeamsNumber!D:D,0)),"없음")} -> tel:+82234517593 | M107: {=IFERROR(INDEX(Printer!D:D,MATCH(All_User!D107,Printer!H:H,0)),"없음")} -> 없음 | N107: {=IFERROR(INDEX(Monitor!A:A,MATCH(D107,Monitor!D:D,0)),"없음")} -> 없음 | O107: {=IFERROR(INDEX(sales!D:D,MATCH(D107,sales!C:C,0)),"없음")} -> 없음 | P107: {=IFERROR(INDEX(sales!E:E,MATCH(D107,sales!C:C,0)),"없음")} -> 없음
A108: 109 | B108: Theo Kim | C108: 김덕영 | D108: theo.kim@stryker.com | E108: Commercial Reporting Administrator | F108: Customer Services Job Family Group | G108: Technical Customer Support | H108: {=IFERROR(INDEX(Lease_List!D:D,MATCH(All_User!D108,Lease_List!H:H,0)),"없음")} -> 5CD3469HDD | I108: 없음 | K108: {=IFERROR(INDEX(Ipad_List!C:C,MATCH(All_User!D108,Ipad_List!J:J,0)),"없음")} -> 없음 | L108: {=IFERROR(INDEX(TeamsNumber!B:B,MATCH(All_User!D108,TeamsNumber!D:D,0)),"없음")} -> 없음 | M108: {=IFERROR(INDEX(Printer!D:D,MATCH(All_User!D108,Printer!H:H,0)),"없음")} -> 없음 | N108: {=IFERROR(INDEX(Monitor!A:A,MATCH(D108,Monitor!D:D,0)),"없음")} -> 없음 | O108: {=IFERROR(INDEX(sales!D:D,MATCH(D108,sales!C:C,0)),"없음")} -> 없음 | P108: {=IFERROR(INDEX(sales!E:E,MATCH(D108,sales!C:C,0)),"없음")} -> 없음
A109: 110 | B109: Daphne Kim | C109: 김다영 | D109: daphne.kim@stryker.com | E109: Customer Service Representative | F109: Customer Services Job Family Group | G109: Customer Services | H109: {=IFERROR(INDEX(Lease_List!D:D,MATCH(All_User!D109,Lease_List!H:H,0)),"없음")} -> 5CD5062YDM | I109: 없음 | K109: {=IFERROR(INDEX(Ipad_List!C:C,MATCH(All_User!D109,Ipad_List!J:J,0)),"없음")} -> 없음 | L109: {=IFERROR(INDEX(TeamsNumber!B:B,MATCH(All_User!D109,TeamsNumber!D:D,0)),"없음")} -> tel:+82234517690 | M109: {=IFERROR(INDEX(Printer!D:D,MATCH(All_User!D109,Printer!H:H,0)),"없음")} -> 없음 | N109: {=IFERROR(INDEX(Monitor!A:A,MATCH(D109,Monitor!D:D,0)),"없음")} -> 없음 | O109: {=IFERROR(INDEX(sales!D:D,MATCH(D109,sales!C:C,0)),"없음")} -> 없음 | P109: {=IFERROR(INDEX(sales!E:E,MATCH(D109,sales!C:C,0)),"없음")} -> 없음
...

Sheet Lease_List
A1: Model | B1: 종류 | C1: SNOW Tag | D1: S/N | E1: lease Date | F1: BU | G1: User | H1: email | I1: Additional Information
A2: HP Elitebook 640 G10 | B2: Laptop | D2: 5CD3469HCY | E2: 40931 | F2: IT | G2: STOCK | I2: 액정파손 수리 완료 / choi kyu(고장)
A3: HP Elitebook 640 G10 | B3: Laptop | D3: 5CD3469HD2 | E3: 40931 | F3: 지평 | G3: Kunji Yun | H3: jpcustoms.skl@stryker.com | J3: {=IFERROR(INDEX(All_User!D:D,MATCH(D3,All_User!H:H,0)),"없음")} -> jpcustoms.skl@stryker.com
A4: HP Elitebook 640 G10 | B4: Laptop | D4: 5CD3469HCX | E4: 40931 | F4: Medsurg | G4: Theo Hwang | H4: theo.hwang@stryker.com | J4: {=IFERROR(INDEX(All_User!D:D,MATCH(D4,All_User!H:H,0)),"없음")} -> theo.hwang@stryker.com
A5: HP Elitebook 640 G10 | B5: Laptop | D5: 5CD3469HCZ | E5: 40931 | F5: IT | G5: kale.lee | H5: kale.lee@stryker.com | J5: {=IFERROR(INDEX(All_User!D:D,MATCH(D5,All_User!H:H,0)),"없음")} -> kale.lee@stryker.com
A6: HP Elitebook 640 G10 | B6: Laptop | D6: 5CD3469HD0 | E6: 40931 | F6: NV | G6: Sophie Bae | H6: sophie.bae@stryker.com | J6: {=IFERROR(INDEX(All_User!D:D,MATCH(D6,All_User!H:H,0)),"없음")} -> sophie.bae@stryker.com
A7: HP Elitebook 640 G10 | B7: Laptop | D7: 5CD3469HD1 | E7: 40931 | F7: Mako | G7: Nathan Lee | H7: nathan.lee@stryker.com | J7: {=IFERROR(INDEX(All_User!D:D,MATCH(D7,All_User!H:H,0)),"없음")} -> nathan.lee@stryker.com
A8: HP Elitebook 640 G10 | B8: Laptop | D8: 5CD3469HD3 | E8: 40931 | F8: Finance | G8: Sungyi Jeon | H8: sungyi.jeon@stryker.com | J8: {=IFERROR(INDEX(All_User!D:D,MATCH(D8,All_User!H:H,0)),"없음")} -> sungyi.jeon@stryker.com
A9: HP Elitebook 640 G10 | B9: Laptop | D9: 5CD3469HD4 | E9: 40931 | F9: Finance | G9: Freddy Park | H9: freddy.park@stryker.com | J9: {=IFERROR(INDEX(All_User!D:D,MATCH(D9,All_User!H:H,0)),"없음")} -> freddy.park@stryker.com
A10: HP Elitebook 640 G10 | B10: Laptop | D10: 5CD3469HD5 | E10: 40931 | F10: Mako | G10: Jackson park | H10: jackson.park@stryker.com | J10: {=IFERROR(INDEX(All_User!D:D,MATCH(D10,All_User!H:H,0)),"없음")} -> jackson.park@stryker.com
A11: HP Elitebook 640 G10 | B11: Laptop | D11: 5CD3469HD6 | E11: 40931 | F11: Mako | G11: Bruce Cha | H11: Bruce.Cha@stryker.com | J11: {=IFERROR(INDEX(All_User!D:D,MATCH(D11,All_User!H:H,0)),"없음")} -> Bruce.Cha@stryker.com
A12: HP Elitebook 640 G10 | B12: Laptop | D12: 5CD3469HD7 | E12: 40931 | F12: RA&QA | G12: Chloe Lee | H12: chloe.lee@stryker.com | J12: {=IFERROR(INDEX(All_User!D:D,MATCH(D12,All_User!H:H,0)),"없음")} -> chloe.lee@stryker.com
A13: HP Elitebook 640 G10 | B13: Laptop | D13: 5CD3469HD8 | E13: 40931 | F13: Finance | G13: jenna.yoo | H13: jenna.yoo@stryker.com | J13: {=IFERROR(INDEX(All_User!D:D,MATCH(D13,All_User!H:H,0)),"없음")} -> jenna.yoo@stryker.com
A14: HP Elitebook 640 G10 | B14: Laptop | D14: 5CD3469HD9 | E14: 40931 | F14: Mako | G14: david.oh | H14: david.oh@stryker.com | J14: {=IFERROR(INDEX(All_User!D:D,MATCH(D14,All_User!H:H,0)),"없음")} -> david.oh@stryker.com
... A20: HP Elitebook 640 G10 | B20: Laptop | D20: 5CD3469HDJ | E20: 40931 | F20: CA | G20: Songmin Kim | H20: songmin.kim@stryker.com | J20: {=IFERROR(INDEX(All_User!D:D,MATCH(D20,All_User!H:H,0)),"없음")} -> songmin.kim@stryker.com
A21: HP Elitebook 640 G10 | B21: Laptop | C21: 430530 | D21: 5CD3469HDK | E21: 40931 | F21: Yongma | G21: order | H21: yongma01(깡통) | J21: {=IFERROR(INDEX(All_User!D:D,MATCH(D21,All_User!H:H,0)),"없음")} -> yongma01(깡통)
A22: HP Elitebook 640 G10 | B22: Laptop | C22: 445031 | D22: 5CD3469HDL | E22: 40931 | F22: IT | G22: STOCK | I22: 블루스크린 PC 반납
A23: HP Elitebook 640 G10 | B23: Laptop | D23: 5CD3469HDM | E23: 40931 | F23: HR | G23: Hansol Shin | H23: hansol.shin@stryker.com | J23: {=IFERROR(INDEX(All_User!D:D,MATCH(D23,All_User!H:H,0)),"없음")} -> hansol.shin@stryker.com
A24: HP Elitebook 640 G10 | B24: Laptop | D24: 5CD3469HDN | E24: 40931 | F24: Planning | G24: Chloe Baek | H24: chloe.baek@stryker.com | J24: {=IFERROR(INDEX(All_User!D:D,MATCH(D24,All_User!H:H,0)),"없음")} -> chloe.baek@stryker.com
A25: HP Elitebook 640 G10 | B25: Laptop | D25: 5CD3469HDP | E25: 40931 | F25: 도원 | G25: Financeadmin4.SKL | H25: financeadmin4.skl@stryker.com | J25: {=IFERROR(INDEX(All_User!D:D,MATCH(D25,All_User!H:H,0)),"없음")} -> financeadmin4.skl@stryker.com
A26: HP Elitebook 640 G10 | B26: Laptop | D26: 5CD3469HDQ | E26: 40931 | F26: Planning | G26: Cindy Jeon | H26: cindy.jeon@stryker.com | J26: {=IFERROR(INDEX(All_User!D:D,MATCH(D26,All_User!H:H,0)),"없음")} -> cindy.jeon@stryker.com
A27: HP Elitebook 640 G10 | B27: Laptop | D27: 5CD3469HDR | E27: 40931 | F27: RA&QA | G27: Irene Jun | H27: irene.jun@stryker.com | J27: {=IFERROR(INDEX(All_User!D:D,MATCH(D27,All_User!H:H,0)),"없음")} -> irene.jun@stryker.com
A28: HP Elitebook 640 G10 | B28: Laptop | D28: 5CD3469HDS | E28: 40931 | F28: 김포 | G28: wondae.koh | H28: wondae.ko@stryker.com | J28: {=IFERROR(INDEX(All_User!D:D,MATCH(D28,All_User!H:H,0)),"없음")} -> wondae.ko@stryker.com
A29: HP Elitebook 640 G10 | B29: Laptop | D29: 5CD3469HDT | E29: 40931 | F29: Knee | G29: Jenny Jung | H29: jenny.jung@stryker.com | J29: {=IFERROR(INDEX(All_User!D:D,MATCH(D29,All_User!H:H,0)),"없음")} -> jenny.jung@stryker.com
A30: HP Elitebook 640 G10 | B30: Laptop | D30: 5CD3469HDV | E30: 40931 | F30: RAQA | G30: Ahyoung Kim | H30: ahyoung.kim@stryker.com | J30: {=IFERROR(INDEX(All_User!D:D,MATCH(D30,All_User!H:H,0)),"없음")} -> ahyoung.kim@stryker.com
A31: HP Elitebook 640 G10 | B31: Laptop | D31: 5CD3469HDG | E31: 40931 | F31: Yongma | G31: CIS | H31: yongma05(깡통) | J31: {=IFERROR(INDEX(All_User!D:D,MATCH(D31,All_User!H:H,0)),"없음")} -> yongma05(깡통)
A32: HP Elitebook 640 G10 | B32: Laptop | D32: 5CD409908H | E32: 04/22/24 | F32: IT | G32: STOCK.
A33: HP Elitebook 640 G10 | B33: Laptop | D33: 5CD409908K | E33: 04/22/24 | F33: HR | G33: Yoori Kim | H33: yoori.kim@stryker.com | J33: {=IFERROR(INDEX(All_User!D:D,MATCH(D33,All_User!H:H,0)),"없음")} -> yoori.kim@stryker.com
A34: HP Elitebook 640 G10 | B34: Laptop | D34: 5CD409908M | E34: 04/22/24 | F34: NV | G34: Sue Kim | H34: Sue.Kim@stryker.com | J34: {=IFERROR(INDEX(All_User!D:D,MATCH(D34,All_User!H:H,0)),"없음")} -> Sue.Kim@stryker.com
A35: HP Elitebook 640 G10 | B35: Laptop | D35: 5CD409908J | E35: 04/22/24 | F35: Implants | G35: Suhyun Kim | H35: Suhyun.Kim@stryker.com | J35: {=IFERROR(INDEX(All_User!D:D,MATCH(D35,All_User!H:H,0)),"없음")} -> Suhyun.Kim@stryker.com
A36: HP Elitebook 640 G10 | B36: Laptop | D36: 5CD409908L | E36: 04/22/24 | F36: NV | G36: Henry Kim | H36: henry.kim1@stryker.com | J36: {=IFERROR(INDEX(All_User!D:D,MATCH(D36,All_User!H:H,0)),"없음")} -> henry.kim1@stryker.com
A37: HP Elitebook 640 G10 | B37: Laptop | D37: 5CD409908N | E37: 04/22/24 | F37: IT | G37: Kmultiuser | H37: kmultiuser@stryker.com
A38: HP Elitebook 640 G10 | B38: Laptop | D38: 5CD4145N3F | E38: 38407 | F38: 김포 | G38: Demoadmin.ym | H38: demoadmin.ym@stryker.com | J38: {=IFERROR(INDEX(All_User!D:D,MATCH(D38,All_User!H:H,0)),"없음")} -> demoadmin.ym@stryker.com
A39: HP Elitebook 640 G10 | B39: Laptop | D39: 5CD4145N3M | E39: 38407 | F39: IT | G39: STOCK | I39: 키보드 교체(한글 스티커)
A40: HP Elitebook 640 G10 | B40: Laptop | D40: 5CD4145N3Q | E40: 38407 | F40: IT | G40: STOCK | I40: Bitlocker Error (KB00216607 참고) KB00216607 에러 발생 > 조치 카탈로그 KB13320 또한 에러 발생
A41: HP Elitebook 640 G10 | B41: Laptop | C41: 435615 | D41: 5CD4145N3G | E41: 38407 | F41: 도원 | G41: Financeadmin3.SKL | H41: Financeadmin3.SKL@stryker.com | J41: {=IFERROR(INDEX(All_User!D:D,MATCH(D41,All_User!H:H,0)),"없음")} -> Financeadmin3.SKL@stryker.com
A42: HP Elitebook 640 G10 | B42: Laptop | D42: 5CD4145N3S | E42: 38407 | F42: Finance | G42: jay.moon | H42: jay.moon@stryker.com | J42: {=IFERROR(INDEX(All_User!D:D,MATCH(D42,All_User!H:H,0)),"없음")} -> jay.moon@stryker.com
A43: HP Elitebook 640 G10 | B43: Laptop | D43: 5CD4145N3N | E43: 38407 | F43: CS | G43: Hyeran Ahn | H43: hyeran.an@stryker.com | J43: {=IFERROR(INDEX(All_User!D:D,MATCH(D43,All_User!H:H,0)),"없음")} -> hyeran.an@stryker.com
A44: HP Elitebook 640 G10 | B44: Laptop | D44: 5CD4145N3P | E44: 38407 | F44: Legal | G44: Greg Kim | H44: greg.kim@stryker.com | J44: {=IFERROR(INDEX(All_User!D:D,MATCH(D44,All_User!H:H,0)),"없음")} -> greg.kim@stryker.com
A45: HP Elitebook 640 G10 | B45: Laptop | D45: 5CD4145N3K | E45: 38407 | F45: Mako | G45: Mason Kim | H45: mason.kim1@stryker.com | J45: {=IFERROR(INDEX(All_User!D:D,MATCH(D45,All_User!H:H,0)),"없음")} -> mason.kim1@stryker.com
A46: HP Elitebook 640 G10 | B46: Laptop | D46: 5CD4145N3R | E46: 38407 | F46: 김포 | G46: hangil.jeong | H46: hangil.jeong@stryker.com | J46: {=IFERROR(INDEX(All_User!D:D,MATCH(D46,All_User!H:H,0)),"없음")} -> hangil.jeong@stryker.com
A47: HP Elitebook 640 G10 | B47: Laptop | D47: 5CD4145N3H | E47: 38407 | F47: Knee | G47: JW Yoon | H47: jw.yoon@stryker.com | J47: {=IFERROR(INDEX(All_User!D:D,MATCH(D47,All_User!H:H,0)),"없음")} -> jw.yoon@stryker.com
A48: HP Elitebook 640 G10 | B48: Laptop | D48: 5CD4145N3J | E48: 38407 | F48: IT | G48: 지문등록 | H48: SYKAdmin
A49: HP Elitebook 640 G10 | B49: Laptop | D49: 5CD4145N3L | E49: 38407 | F49: Medsurg | G49: Ethan Na | H49: ethan.na@stryker.com | J49: {=IFERROR(INDEX(All_User!D:D,MATCH(D49,All_User!H:H,0)),"없음")} -> ethan.na@stryker.com
A50: HP Elitebook 640 G10 | B50: Laptop | D50: 5CD4145N3T | E50: 38407 | F50: Planning | G50: James Park | H50: james.park@stryker.com | J50: {=IFERROR(INDEX(All_User!D:D,MATCH(D50,All_User!H:H,0)),"없음")} -> james.park@stryker.com
A51: HP Elitebook 640 G10 | B51: Laptop | D51: 5CD4145N3V | E51: 38407 | F51: Implants | G51: Brad Choi | H51: brad.choi@stryker.com | J51: {=IFERROR(INDEX(All_User!D:D,MATCH(D51,All_User!H:H,0)),"없음")} -> brad.choi@stryker.com
A52: HP Elitebook 640 G10 | B52: Laptop | D52: 5CD4232BF6 | E52: 06/20/24 | F52: IT | G52: Kmultiuser | H52: kmultiuser@stryker.com | I52: (보드손상 수리) | J52: chloe님 아르바이트 대여
A53: HP Elitebook 640 G10 | B53: Laptop | D53: 5CD4232BF5 | E53: 06/20/24 | F53: IT | G53: STOCK | I53: SCCM
A54: HP Elitebook 640 G10 | B54: Laptop | D54: 5CD4232BF7 | E54: 06/20/24 | F54: MAKO | G54: yeonjoo.kim | H54: yeonjoo.kim@stryker.com | J54: {=IFERROR(INDEX(All_User!D:D,MATCH(D54,All_User!H:H,0)),"없음")} -> yeonjoo.kim@stryker.com
A55: HP Elitebook 640 G10 | B55: Laptop | D55: 5CD4232BFQ | E55: 06/20/24 | F55: Mako | G55: Mason Oh | H55: mason.oh@stryker.com | J55: {=IFERROR(INDEX(All_User!D:D,MATCH(D55,All_User!H:H,0)),"없음")} -> mason.oh@stryker.com
A56: HP Elitebook 640 G10 | B56: Laptop | D56: 5CD4232BFS | E56: 06/20/24 | F56: TS | G56: Jayden Song | H56: jayden.song@stryker.com | J56: {=IFERROR(INDEX(All_User!D:D,MATCH(D56,All_User!H:H,0)),"없음")} -> jayden.song@stryker.com
A57: HP Elitebook 640 G10 | B57: Laptop | D57: 5CD4232BFP | E57: 06/20/24 | F57: TS | G57: David Lee | H57: david.lee4@stryker.com | J57: {=IFERROR(INDEX(All_User!D:D,MATCH(D57,All_User!H:H,0)),"없음")} -> david.lee4@stryker.com
A58: HP Elitebook 640 G10 | B58: Laptop | D58: 5CD4232BF1 | E58: 06/20/24 | F58: Knee | G58: david.chung | H58: david.chung@stryker.com | J58: {=IFERROR(INDEX(All_User!D:D,MATCH(D58,All_User!H:H,0)),"없음")} -> david.chung@stryker.com
A59: HP Elitebook 640 G10 | B59: Laptop | D59: 5CD4232BFN | E59: 06/20/24 | F59: Medsurg | G59: Danny Kim | H59: danny.kim@stryker.com | J59: {=IFERROR(INDEX(All_User!D:D,MATCH(D59,All_User!H:H,0)),"없음")} -> danny.kim@stryker.com
A60: HP Elitebook 640 G10 | B60: Laptop | D60: 5CD4232BFF | E60: 06/20/24 | F60: Mako | G60: Jisoo Byeon | H60: jisoo.byeon@stryker.com | J60: {=IFERROR(INDEX(All_User!D:D,MATCH(D60,All_User!H:H,0)),"없음")} -> jisoo.byeon@stryker.com
A61: HP Elitebook 640 G10 | B61: Laptop | D61: 5CD4232BF9 | E61: 06/20/24 | F61: GM | G61: Kevin Shim | H61: kevin.shim@stryker.com | J61: {=IFERROR(INDEX(All_User!D:D,MATCH(D61,All_User!H:H,0)),"없음")} -> kevin.shim@stryker.com
A62: HP Elitebook 640 G10 | B62: Laptop | D62: 5CD4232BFG | E62: 06/20/24 | F62: RA&QA | G62: Celine Jung | H62: celine.jung@stryker.com | J62: {=IFERROR(INDEX(All_User!D:D,MATCH(D62,All_User!H:H,0)),"없음")} -> celine.jung@stryker.com
A63: HP Elitebook 640 G10 | B63: Laptop | D63: 5CD4232BFC | E63: 06/20/24 | F63: Implants | G63: Peter Oh | H63: peter.oh@stryker.com | J63: {=IFERROR(INDEX(All_User!D:D,MATCH(D63,All_User!H:H,0)),"없음")} -> peter.oh@stryker.com
A64: HP Elitebook 640 G10 | B64: Laptop | D64: 5CD4232BFT | E64: 06/20/24 | F64: Mako | G64: Ara ko | H64: ara.ko@stryker.com | J64: {=IFERROR(INDEX(All_User!D:D,MATCH(D64,All_User!H:H,0)),"없음")} -> ara.ko@stryker.com
A65: HP Elitebook 640 G10 | B65: Laptop | D65: 5CD4232BFB | E65: 06/20/24 | F65: RA NV | G65: jennifer.paek | H65: jennifer.paek@stryker.com | J65: {=IFERROR(INDEX(All_User!D:D,MATCH(D65,All_User!H:H,0)),"없음")} -> jennifer.paek@stryker.com
... A67: HP Elitebook 640 G10 | B67: Laptop | D67: 5CD4232BF3 | E67: 06/20/24 | F67: RA&QA | G67: Leslie Kim | H67: Leslie.kim@stryker.com | J67: {=IFERROR(INDEX(All_User!D:D,MATCH(D67,All_User!H:H,0)),"없음")} -> Leslie.kim@stryker.com
A68: HP Elitebook 640 G10 | B68: Laptop | D68: 5CD4232BFD | E68: 06/20/24 | F68: IT | G68: STOCK | I68: 전원 고장 | J68: {=IFERROR(INDEX(All_User!D:D,MATCH(D68,All_User!H:H,0)),"없음")} -> 없음
A69: HP Elitebook 640 G10 | B69: Laptop | D69: 5CD4232BF2 | E69: 06/20/24 | F69: IT | G69: STOCK | I69: SCCM
A70: HP Elitebook 640 G10 | B70: Laptop | D70: 5CD4232BFL | E70: 06/20/24 | F70: Mako | G70: GD Ahn | H70: gd.ahn@stryker.com | J70: {=IFERROR(INDEX(All_User!D:D,MATCH(D70,All_User!H:H,0)),"없음")} -> gd.ahn@stryker.com
A71: HP Elitebook 640 G10 | B71: Laptop | D71: 5CD4232BFH | E71: 06/20/24 | F71: Mako | G71: Ko Arin | H71: arin.ko@stryker.com | J71: {=IFERROR(INDEX(All_User!D:D,MATCH(D71,All_User!H:H,0)),"없음")} -> arin.ko@stryker.com
A72: HP Elitebook 640 G10 | B72: Laptop | C72: 438728 | D72: 5CD4232BF8 | E72: 06/20/24 | F72: Yongma | G72: Yongma, Stryker | H72: WMS4 /Kit/yongma03(깡통)
A73: HP Elitebook 640 G10 | B73: Laptop | D73: 5CD4232BFV | E73: 06/20/24 | F73: Mako | G73: Hong Ashley | H73: ashley.hong@stryker.com | J73: {=IFERROR(INDEX(All_User!D:D,MATCH(D73,All_User!H:H,0)),"없음")} -> ashley.hong@stryker.com
A74: HP Elitebook 640 G10 | B74: Laptop | D74: 5CD4232BFK | E74: 06/20/24 | F74: Mako | G74: Rosey Song | H74: rosey.song@stryker.com | J74: {=IFERROR(INDEX(All_User!D:D,MATCH(D74,All_User!H:H,0)),"없음")} -> rosey.song@stryker.com
A75: HP Elitebook 640 G10 | B75: Laptop | D75: 5CD4232BFJ | E75: 06/20/24 | F75: Knee | G75: Scott Jo | H75: scott.jo@stryker.com | J75: {=IFERROR(INDEX(All_User!D:D,MATCH(D75,All_User!H:H,0)),"없음")} -> scott.jo@stryker.com
A76: HP Elitebook 640 G10 | B76: Laptop | D76: 5CD4232BFR | E76: 06/20/24 | F76: CS | G76: kylie.leem | H76: kylie.leem@stryker.com | J76: {=IFERROR(INDEX(All_User!D:D,MATCH(D76,All_User!H:H,0)),"없음")} -> kylie.leem@stryker.com
A77: HP Elitebook 640 G10 | B77: Laptop | D77: 5CD4232BF4 | E77: 06/20/24 | F77: IT | G77: STOCK | I77: sungyoun.hur@stryker.com - 노트북 마이크 노이즈
A78: HP Elitebook 640 G10 | B78: Laptop | C78: 445036 | D78: 5CD4305D8G | E78: 08/20/24 | F78: IT | G78: STOCK | I78: 전원 고장
A79: HP Elitebook 640 G10 | B79: Laptop | D79: 5CD4305D8W | E79: 08/20/24 | F79: Mako | G79: Jayden Kim | H79: jayden.kim@stryker.com
A80: HP Elitebook 640 G10 | B80: Laptop | D80: 5CD4305D8P | E80: 08/20/24 | F80: Knee | G80: Ayaan Yoon | H80: ayaan.yoon@stryker.com | I80: 설치중 | J80: {=IFERROR(INDEX(All_User!D:D,MATCH(D80,All_User!H:H,0)),"없음")} -> ayaan.yoon@stryker.com
A81: HP Elitebook 640 G10 | B81: Laptop | D81: 5CD4305D8F | E81: 08/20/24 | F81: MedSurg | G81: bella yoon | H81: bella.yoon@stryker.com | J81: {=IFERROR(INDEX(All_User!D:D,MATCH(D81,All_User!H:H,0)),"없음")} -> bella.yoon@stryker.com
A82: HP Elitebook 640 G10 | B82: Laptop | C82: 445026 | D82: 5CD4305D8J | E82: 08/20/24 | F82: RAQA | G82: Sazy Park | H82: sazy.park@stryker.com | I82: 인턴 | J82: {=IFERROR(INDEX(All_User!D:D,MATCH(D82,All_User!H:H,0)),"없음")} -> sazy.park@stryker.com
A83: HP Elitebook 640 G10 | B83: Laptop | D83: 5CD4305D88 | E83: 08/20/24 | F83: Medical | G83: Michelle Park | H83: michelle.park@stryker.com | I83: 기존 노트북 미반환 | J83: {=IFERROR(INDEX(All_User!D:D,MATCH(D83,All_User!H:H,0)),"없음")} -> michelle.park@stryker.com
A84: HP Elitebook 640 G10 | B84: Laptop | D84: 5CD4305D8Q | E84: 08/20/24 | F84: Finance | G84: William Kim | H84: william.kim1@stryker.com | I84: 기존 노트북 미반환 | J84: {=IFERROR(INDEX(All_User!D:D,MATCH(D84,All_User!H:H,0)),"없음")} -> william.kim1@stryker.com
A85: HP Elitebook 640 G10 | B85: Laptop | D85: 5CD4305D94 | E85: 08/20/24 | F85: MPS | G85: seohyun.jung | H85: seohyun.jung@stryker.com | I85: 미반납 | J85: {=IFERROR(INDEX(All_User!D:D,MATCH(D85,All_User!H:H,0)),"없음")} -> seohyun.jung@stryker.com
A86: HP Elitebook 640 G10 | B86: Laptop | D86: 5CD4305D85 | E86: 08/20/24 | F86: Knee | G86: sunghoon.bang | H86: sunghoon.bang@stryker.com | J86: {=IFERROR(INDEX(All_User!D:D,MATCH(D86,All_User!H:H,0)),"없음")} -> sunghoon.bang@stryker.com
A87: HP Elitebook 640 G10 | B87: Laptop | C87: 445046 | D87: 5CD4305D92 | E87: 08/20/24 | F87: Yongma | G87: Yongma, Stryker | H87: yongma02(깡통) | J87: {=IFERROR(INDEX(All_User!D:D,MATCH(D87,All_User!H:H,0)),"없음")} -> yongma02(깡통)
A88: HP Elitebook 640 G10 | B88: Laptop | D88: 5CD4305D8V | E88: 08/20/24 | F88: RA&QA | G88: Jiwon Yoo | H88: jiwon.yoo@stryker.com | J88: {=IFERROR(INDEX(All_User!D:D,MATCH(D88,All_User!H:H,0)),"없음")} -> jiwon.yoo@stryker.com
A89: HP Elitebook 640 G10 | B89: Laptop | D89: 5CD4305D8T | E89: 08/20/24 | F89: TS | G89: suhan.lee | H89: suhan.lee@stryker.com | J89: {=IFERROR(INDEX(All_User!D:D,MATCH(D89,All_User!H:H,0)),"없음")} -> suhan.lee@stryker.com
A90: HP Elitebook 640 G10 | B90: Laptop | D90: 5CD4305D91 | E90: 08/20/24 | F90: Planning | G90: Eunji Lee | H90: eunji.lee@stryker.com | J90: {=IFERROR(INDEX(All_User!D:D,MATCH(D90,All_User!H:H,0)),"없음")} -> eunji.lee@stryker.com
A91: HP Elitebook 640 G10 | B91: Laptop | D91: 5CD4305D8L | E91: 08/20/24 | F91: Sales | G91: Son Amy | H91: amy.son@stryker.com | J91: {=IFERROR(INDEX(All_User!D:D,MATCH(D91,All_User!H:H,0)),"없음")} -> amy.son@stryker.com
A92: HP Elitebook 640 G10 | B92: Laptop | C92: 445043 | D92: 5CD4305D8S | E92: 08/20/24 | F92: IT | G92: Daniel.Han | H92: daniel.han@stryker.com | J92: {=IFERROR(INDEX(All_User!D:D,MATCH(D92,All_User!H:H,0)),"없음")} -> daniel.han@stryker.com
A93: HP Elitebook 640 G10 | B93: Laptop | D93: 5CD4305D8R | E93: 08/20/24 | F93: HR | G93: Ma Serene | H93: serene.ma@stryker.com | J93: {=IFERROR(INDEX(All_User!D:D,MATCH(D93,All_User!H:H,0)),"없음")} -> serene.ma@stryker.com
A94: HP Elitebook 640 G10 | B94: Laptop | D94: 5CD4305D81 | E94: 08/20/24 | F94: Mako | G94: dongkyu.kim | H94: dongkyu.kim@stryker.com | J94: {=IFERROR(INDEX(All_User!D:D,MATCH(D94,All_User!H:H,0)),"없음")} -> dongkyu.kim@stryker.com
A95: HP Elitebook 640 G10 | B95: Laptop | D95: 5CD4305D83 | E95: 08/20/24 | F95: TS | G95: ts.korea | H95: ts.korea@stryker.com | I95: 사무용 / 캐드용과 중복 계정 | J95: {=IFERROR(INDEX(All_User!D:D,MATCH(D95,All_User!H:H,0)),"없음")} -> ts.korea@stryker.com
A96: HP Elitebook 640 G10 | B96: Laptop | D96: 5CD4305D8C | E96: 08/20/24 | F96: Medsurg | G96: Nathan Eom | H96: Nathan.Eom@stryker.com | J96: {=IFERROR(INDEX(All_User!D:D,MATCH(D96,All_User!H:H,0)),"없음")} -> Nathan.Eom@stryker.com
A97: HP Elitebook 640 G10 | B97: Laptop | C97: 445016 | D97: 5CD4305D7Z | E97: 08/20/24 | F97: IT | G97: STOCK | H97: - | I97: 키보드 수리완료
A98: HP Elitebook 640 G10 | B98: Laptop | D98: 5CD4305D8B | E98: 08/20/24 | F98: Yongma | G98: OrderAdmin1 | H98: orderadmin1.ym@stryker.com | J98: {=IFERROR(INDEX(All_User!D:D,MATCH(D98,All_User!H:H,0)),"없음")} -> orderadmin1.ym@stryker.com
A99: HP Elitebook 640 G10 | B99: Laptop | D99: 5CD4305D8X | E99: 08/20/24 | F99: Knee | G99: Suhwan Jung | H99: suhwan.jung@stryker.com | J99: {=IFERROR(INDEX(All_User!D:D,MATCH(D99,All_User!H:H,0)),"없음")} -> suhwan.jung@stryker.com
A100: HP Elitebook 640 G10 | B100: Laptop | D100: 5CD4305D84 | E100: 08/20/24 | F100: Mako | G100: Julie Park | H100: julie.park@stryker.com | J100: {=IFERROR(INDEX(All_User!D:D,MATCH(D100,All_User!H:H,0)),"없음")} -> julie.park@stryker.com
A101: HP Elitebook 640 G10 | B101: Laptop | D101: 5CD4305D87 | E101: 08/20/24 | F101: Finance | G101: demian.lee | H101: demian.lee@stryker.com | J101: {=IFERROR(INDEX(All_User!D:D,MATCH(D101,All_User!H:H,0)),"없음")} -> demian.lee@stryker.com
A102: HP Elitebook 640 G10 | B102: Laptop | D102: 5CD4305D8M | E102: 08/20/24 | F102: Market Access | G102: JH Ji | H102: jh.ji@stryker.com | J102: {=IFERROR(INDEX(All_User!D:D,MATCH(D102,All_User!H:H,0)),"없음")} -> jh.ji@stryker.com
A103: HP Elitebook 640 G10 | B103: Laptop | D103: 5CD4305D82 | E103: 08/20/24 | F103: RAQA | G103: Clare Yang | H103: clare.yang@stryker.com | J103: {=IFERROR(INDEX(All_User!D:D,MATCH(D103,All_User!H:H,0)),"없음")} -> clare.yang@stryker.com
A104: HP Elitebook 640 G10 | B104: Laptop | C104: 430532 | D104: 5CD4305D8D | E104: 08/20/24 | F104: Shoulder | G104: Lia Jung | H104: lia.jung@stryker.com | I104: 인턴 | J104: {=IFERROR(INDEX(All_User!D:D,MATCH(D104,All_User!H:H,0)),"없음")} -> lia.jung@stryker.com
A105: HP Elitebook 640 G10 | B105: Laptop | D105: 5CD4305D96 | E105: 08/20/24 | F105: Operation | G105: imsum.won | H105: imsun.won@stryker.com | J105: {=IFERROR(INDEX(All_User!D:D,MATCH(D105,All_User!H:H,0)),"없음")} -> imsun.won@stryker.com
A106: HP Elitebook 640 G10 | B106: Laptop | D106: 5CD4305D80 | E106: 08/20/24 | F106: Knee | G106: Yoonbee Jeong | H106: yoonbee.jeong@stryker.com | J106: {=IFERROR(INDEX(All_User!D:D,MATCH(D106,All_User!H:H,0)),"없음")} -> yoonbee.jeong@stryker.com
...

Sheet TeamsNumber
A1: Extension | B1: LineURI | C1: Number formated for Country | D1: email | E1: Business Title | F1: ID
A2: 7500 | B2: tel:+82234517500 | C2: =+82 2 3451 7500 | D2: dahye.jeong@stryker.com | E2: #N/A | F2: 대표번호 할당 불가
A3: 7501 | B3: tel:+82234517501 | C3: =+82 2 3451 7501 | D3: sungyi.jeon@stryker.com | E3: #N/A
A4: 7502 | B4: tel:+82234517502 | C4: =+82 2 3451 7502 | D4: annie.lee@stryker.com | E4: #N/A
A5: 7503 | B5: tel:+82234517503 | C5: =+82 2 3451 7503 | D5: hr.sklasem@stryker.com | E5: #N/A
A6: 7504 | B6: tel:+82234517504 | C6: =+82 2 3451 7504 | D6: leadership.sklasem@stryker.com | E6: #N/A
A7: 7505 | B7: tel:+82234517505 | C7: =+82 2 3451 7505 | D7: mahwah.sklasem@stryker.com | E7: #N/A
A8: 7506 | B8: tel:+82234517506 | C8: =+82 2 3451 7506 | D8: mako.sklasem@stryker.com | E8: #N/A
A9: 7507 | B9: tel:+82234517507 | C9: =+82 2 3451 7507 | D9: nv.sklasem@stryker.com | E9: #N/A
A10: 7508 | B10: tel:+82234517508 | C10: =+82 2 3451 7508 | D10: raqa.sklasem@stryker.com | E10: #N/A
A11: 7509 | B11: tel:+82234517509 | C11: =+82 2 3451 7509 | D11: target.sklasem@stryker.com | E11: #N/A
A12: 7510 | B12: tel:+82234517510 | C12: =+82 2 3451 7510 | D12: drsouthkorea.teams@stryker.com | E12: #N/A
A13: 7511 | B13: tel:+82234517511 | C13: =+82 2 3451 7511 | D13: jiwon.yoo@stryker.com | E13: #N/A
A14: 7512 | B14: tel:+82234517512 | C14: =+82 2 3451 7512 | D14: andrew.ahn@stryker.com | E14: #N/A
... A19: 7517 | B19: tel:+82234517517 | C19: =+82 2 3451 7517 | D19: mason.choi@stryker.com | E19: #N/A
A20: 7518 | B20: tel:+82234517518 | C20: =+82 2 3451 7518 | D20: kita.ym@stryker.com | E20: #N/A | F20: 용마 키트 Admin
A21: 7519 | B21: tel:+82234517519 | C21: =+82 2 3451 7519 | D21: chloe.baek@stryker.com | E21: #N/A
A22: 7520 | B22: tel:+82234517520 | C22: =+82 2 3451 7520 | D22: kevin.shim@stryker.com | E22: #N/A
A23: 7521 | B23: tel:+82234517521 | C23: =+82 2 3451 7521 | D23: chloe.lee@stryker.com | E23: #N/A
A24: 7522 | B24: tel:+82234517522 | C24: =+82 2 3451 7522 | D24: chris.shin@stryker.com | E24: #N/A
A25: 7523 | B25: tel:+82234517523 | C25: =+82 2 3451 7523 | D25: sally.choi@stryker.com | E25: #N/A
A26: 7524 | B26: tel:+82234517524 | C26: =+82 2 3451 7524 | D26: leslie.kim@stryker.com | E26: #N/A
A27: 7525 | B27: tel:+82234517525 | C27: =+82 2 3451 7525 | D27: claire.choi@stryker.com | E27: #N/A
A28: 7526 | B28: tel:+82234517526 | C28: =+82 2 3451 7526 | D28: clare.yang@stryker.com | E28: #N/A
A29: 7527 | B29: tel:+82234517527 | C29: =+82 2 3451 7527 | D29: chan.jeon@stryker.com | E29: #N/A
A30: 7528 | B30: tel:+82234517528 | C30: =+82 2 3451 7528 | D30: dana.shin@stryker.com | E30: #N/A
A31: 7529 | B31: tel:+82234517529 | C31: =+82 2 3451 7529 | D31: soyoun.kim@stryker.com | E31: #N/A
A32: 7530 | B32: tel:+82234517530 | C32: =+82 2 3451 7530 | D32: danny.kim@stryker.com | E32: #N/A
... A35: 7533 | B35: tel:+82234517533 | C35: =+82 2 3451 7533 | D35: david.yang@stryker.com | E35: #N/A
A36: 7534 | B36: tel:+82234517534 | C36: =+82 2 3451 7534 | E36: Shoulder KLT 사용하던 것
A37: 7535 | B37: tel:+82234517535 | C37: =+82 2 3451 7535 | D37: ethan.jang@stryker.com | E37: #N/A
A38: 7536 | B38: tel:+82234517536 | C38: =+82 2 3451 7536 | D38: dongkyu.kim@stryker.com | E38: #N/A
A39: 7537 | B39: tel:+82234517537 | C39: =+82 2 3451 7537 | D39: jisoo.yang@stryker.com | E39: #N/A
A40: 7538 | B40: tel:+82234517538 | C40: =+82 2 3451 7538 | E40: Elin KIM / knee 사용
A41: 7539 | B41: tel:+82234517539 | C41: =+82 2 3451 7539 | E41: Legal KLT 사용하던 것
A42: 7540 | B42: tel:+82234517540 | C42: =+82 2 3451 7540 | D42: yoori.kim@stryker.com | E42: #N/A
A43: 7541 | B43: tel:+82234517541 | C43: =+82 2 3451 7541 | D43: hansol.shin@stryker.com | E43: #N/A
A44: 7542 | B44: tel:+82234517542 | C44: =+82 2 3451 7542 | D44: ethan.song@stryker.com | E44: #N/A
A45: 7543 | B45: tel:+82234517543 | C45: =+82 2 3451 7543 | D45: chloe.kang@stryker.com | E45: #N/A
A46: 7544 | B46: tel:+82234517544 | C46: =+82 2 3451 7544 | D46: freddy.park@stryker.com | E46: #N/A
A47: 7545 | B47: tel:+82234517545 | C47: =+82 2 3451 7545 | D47: peter.oh@stryker.com | E47: #N/A
A48: 7546 | B48: tel:+82234517546 | C48: =+82 2 3451 7546 | D48: mihee.han@stryker.com | E48: #N/A
A49: 7547 | B49: tel:+82234517547 | C49: =+82 2 3451 7547 | D49: jeff.lee@stryker.com | E49: #N/A
A50: 7548 | B50: tel:+82234517548 | C50: =+82 2 3451 7548 | D50: gregory.seo@stryker.com | E50: #N/A
A51: 7549 | B51: tel:+82234517549 | C51: =+82 2 3451 7549 | D51: bruce.cha@stryker.com | E51: #N/A
A52: 7550 | B52: tel:+82234517550 | C52: =+82 2 3451 7550 | D52: louis.kang@stryker.com | E52: #N/A
A53: 7551 | B53: tel:+82234517551 | C53: =+82 2 3451 7551 | D53: jiho.yoo@stryker.com | E53: #N/A
... A55: 7553 | B55: tel:+82234517553 | C55: =+82 2 3451 7553 | D55: cozy.huh@stryker.com | E55: #N/A
A56: 7554 | B56: tel:+82234517554 | C56: =+82 2 3451 7554 | E56: Sales/tony.kang@stryker.com
A57: 7555 | B57: tel:+82234517555 | C57: =+82 2 3451 7555 | D57: minki.kim@stryker.com | E57: #N/A
A58: 7556 | B58: tel:+82234517556 | C58: =+82 2 3451 7556 | D58: sarah.youn@stryker.com | E58: #N/A
A59: 7557 | B59: tel:+82234517557 | C59: =+82 2 3451 7557 | D59: willy.chang@stryker.com | E59: #N/A
A60: 7558 | B60: tel:+82234517558 | C60: =+82 2 3451 7558 | D60: justin.kim@stryker.com | E60: #N/A
A61: 7559 | B61: tel:+82234517559 | C61: =+82 2 3451 7559 | D61: brad.choi@stryker.com | E61: #N/A
A62: 7560 | B62: tel:+82234517560 | C62: =+82 2 3451 7560 | D62: yeonjoo.kim@stryker.com | E62: #N/A
A63: 7561 | B63: tel:+82234517561 | C63: =+82 2 3451 7561 | D63: Bella.yoon@stryker.com | E63: #N/A
A64: 7562 | B64: tel:+82234517562 | C64: =+82 2 3451 7562 | D64: rosie.lee@stryker.com | E64: #N/A
A65: 7563 | B65: tel:+82234517563 | C65: =+82 2 3451 7563 | D65: ayaan.lee@stryker.com | E65: #N/A
A66: 7564 | B66: tel:+82234517564 | C66: =+82 2 3451 7564 | D66: jennifer.paek@stryker.com | E66: #N/A
A67: 7565 | B67: tel:+82234517565 | C67: =+82 2 3451 7565 | E67: Sales Manager / william.chai@stryker.com
A68: 7566 | B68: tel:+82234517566 | C68: =+82 2 3451 7566 | D68: gd.ahn@stryker.com | E68: #N/A
A69: 7567 | B69: tel:+82234517567 | C69: =+82 2 3451 7567 | D69: roy.choi@stryker.com | E69: #N/A
A70: 7568 | B70: tel:+82234517568 | C70: =+82 2 3451 7568 | D70: bella.bang@stryker.com | E70: #N/A
A71: 7569 | B71: tel:+82234517569 | C71: =+82 2 3451 7569 | D71: jade.jung@stryker.com | E71: #N/A
A72: 7570 | B72: tel:+82234517570 | C72: =+82 2 3451 7570 | D72: james.kang@stryker.com | E72: #N/A
A73: 7571 | B73: tel:+82234517571 | C73: =+82 2 3451 7571 | D73: michelle.park@stryker.com | E73: #N/A
A74: 7572 | B74: tel:+82234517572 | C74: =+82 2 3451 7572 | D74: rosey.song@stryker.com | E74: #N/A
A75: 7573 | B75: tel:+82234517573 | C75: =+82 2 3451 7573 | D75: ian.hwang@stryker.com | E75: #N/A
A76: 7574 | B76: tel:+82234517574 | C76: =+82 2 3451 7574 | D76: seohyun.jung@stryker.com | E76: #N/A
A77: 7575 | B77: tel:+82234517575 | C77: =+82 2 3451 7575 | D77: allen.ku@stryker.com | E77: #N/A
A78: 7576 | B78: tel:+82234517576 | C78: =+82 2 3451 7576 | D78: kyle.lim@stryker.com | E78: #N/A
A79: 7577 | B79: tel:+82234517577 | C79: =+82 2 3451 7577 | D79: amy.son@stryker.com | E79: #N/A
... A100: 7598 | B100: tel:+82234517598 | C100: =+82 2 3451 7598 | D100: suhyun.kim@stryker.com | E100: #N/A
A101: 7599 | B101: tel:+82234517599 | C101: =+82 2 3451 7599 | E101: Medsurg / harim shin 사용하던것
A102: 7600 | B102: tel:+82234517600 | C102: =+82 2 3451 7600 | D102: gyolim.gu@stryker.com | E102: #N/A
A103: 7601 | B103: tel:+82234517601 | C103: =+82 2 3451 7601 | D103: hailey.kim@stryker.com | E103: #N/A
A104: 7602 | B104: tel:+82234517602 | C104: =+82 2 3451 7602 | D104: antonio.cho@stryker.com | E104: Medsurg / shin yoojin shin 사용하던것
A105: 7603 | B105: tel:+82234517603 | C105: =+82 2 3451 7603 | D105: jay.ji@stryker.com | E105: #N/A
A106: 7604 | B106: tel:+82234517604 | C106: =+82 2 3451 7604 | D106: lucas.jeon@stryker.com | E106: #N/A
A107: 7605 | B107: tel:+82234517605 | C107: =+82 2 3451 7605 | D107: Jenny.jung@stryker.com | E107: #N/A
A108: 7606 | B108: tel:+82234517606 | C108: =+82 2 3451 7606 | D108: henry.lee@stryker.com | E108: #N/A
A109: 7607 | B109: tel:+82234517607 | C109: =+82 2 3451 7607 | E109: #N/A
A110: 7608 | B110: tel:+82234517608 | C110: =+82 2 3451 7608 | D110: peter.park@stryker.com | E110: #N/A
A111: 7609 | B111: tel:+82234517609 | C111: =+82 2 3451 7609 | D111: jy.park@stryker.com | E111: #N/A
A112: 7610 | B112: tel:+82234517610 | C112: =+82 2 3451 7610 | D112: jack.eum@stryker.com | E112: #N/A
A113: 7611 | B113: tel:+82234517611 | C113: =+82 2 3451 7611 | D113: nathan.eom@stryker.com | E113: #N/A
A114: 7612 | B114: tel:+82234517612 | C114: =+82 2 3451 7612 | D114: ethan.na@stryker.com | E114: #N/A
A115: 7613 | B115: tel:+82234517613 | C115: =+82 2 3451 7613 | D115: joy.lee@stryker.com | E115: #N/A
A116: 7614 | B116: tel:+82234517614 | C116: =+82 2 3451 7614 | D116: wondae.ko@stryker.com | E116: #N/A
A117: 7615 | B117: tel:+82234517615 | C117: =+82 2 3451 7615 | D117: mindo.kim@stryker.com | E117: #N/A
A118: 7616 | B118: tel:+82234517616 | C118: =+82 2 3451 7616 | D118: jack.park@stryker.com | E118: #N/A
A119: 7617 | B119: tel:+82234517617 | C119: =+82 2 3451 7617 | D119: jay.moon@stryker.com | E119: #N/A
A120: 7618 | B120: tel:+82234517618 | C120: =+82 2 3451 7618 | D120: jae.chung@stryker.com | E120: #N/A
A121: 7619 | B121: tel:+82234517619 | C121: =+82 2 3451 7619 | D121: jaehee.seo@stryker.com | E121: #N/A
A122: 7620 | B122: tel:+82234517620 | C122: =+82 2 3451 7620 | D122: aspyn.kim@stryker.com | E122: #N/A
A123: 7621 | B123: tel:+82234517621 | C123: =+82 2 3451 7621 | E123: Medsurg / jayden shin 사용하던것
A124: 7622 | B124: tel:+82234517622 | C124: =+82 2 3451 7622 | D124: daniel.park@stryker.com | E124: #N/A
A125: 7623 | B125: tel:+82234517623 | C125: =+82 2 3451 7623 | D125: kyu.choi@stryker.com | E125: #N/A
A126: 7624 | B126: tel:+82234517624 | C126: =+82 2 3451 7624 | D126: mason.oh@stryker.com | E126: #N/A
A127: 7625 | B127: tel:+82234517625 | C127: =+82 2 3451 7625 | D127: suhan.lee@stryker.com | E127: #N/A
...

Sheet Ipad_List
A1: 개수 | B1: Model | C1: S/N | D1: Date | E1: 전화 번호 | F1: 애플펜슬 2세대 | G1: BU | H1: Role | I1: User | J1: email | K1: Additional Information | L1: 해지유무 | M1: 참고
A3: 1 | B3: iPAD_Pro_12.9_Gen3_64 | C3: DLXZX04QKC5Q | D3: 44121 | E3: 010-4352-6949 | F3: 1 | G3: IT | H3: IT | K3: Johnny Choi 반납 / 펜슬 미반납 | L3: 해지완료 | M3: 2025.03.19 재약정 / 위약금 발생
A4: 2 | B4: iPAD_Air_Gen5_256 | C4: KG27H3Q1J1 | D4: 44711 | E4: 010-6681-6949 | F4: 1 | G4: Knee | H4: KLT | I4: Jason Han | J4: jason.han@stryker.com | M4: 2025.03.19 재약정
A5: 3 | B5: iPAD_Pro_12.9_Gen3_64 | C5: DLXCC00MKC43 | D5: 44121 | E5: 010-9984-6182 | F5: 1 | G5: GM | H5: KLT | I5: Kevin Shim | J5: kevin.shim@stryker.com
A6: 4 | B6: iPAD_Pro_12.9_Gen3_64 | C6: DLXCC0M0KC43 | D6: 44121 | E6: 해지 완료 | G6: Finance | H6: KLT | I6: Heesun Cho | J6: heesun.cho@stryker.com | L6: 해지완료
A7: 5 | B7: IPADP4_11-128 | C7: FQ29PC2NKJ | D7: 44995 | E7: 010-6878-0164 | F7: 1 | G7: Spare | H7: KLT | I7: TESTing by Jun
A8: 6 | B8: IPADP4_11-128 | C8: K9J441WF9W | D8: 44995 | E8: 010-6878-0172 | F8: 1 | G8: Mako | H8: MPS | I8: Sujin park | J8: sujin.park@stryker.com
A9: 7 | B9: IPADP4_11-128 | C9: J1XWPW66YY | D9: 44995 | E9: 해지 완료 | G9: IT | H9: IT | I9: Kale Lee | J9: kale.lee@stryker.com | L9: 해지완료
A10: 8 | B10: IPADP4_11-128 | C10: CK7JHKH443 | D10: 44995 | E10: 010-6878-0256 | G10: IT | H10: IT | I10: stock | M10: 수리완료 오른쪽 라인 터치 안됨
A11: 9 | B11: IPADP4_11-128 | C11: G9YWDFP14H | D11: 44995 | E11: 010-6878-0276 | G11: Operation | H11: KLT | I11: Minsu Yi | J11: minsu.yi@stryker.com
A12: 10 | B12: IPADP4_11-128 | C12: HL7Q0T6MHW | D12: 44995 | E12: 010-6878-0299 | F12: 1 | G12: Mako | H12: MPS | I12: Vincent Bea | J12: vincent.bae@stryker.com
A13: 11 | B13: IPADP4_11-128 | C13: J2Y7TQ0Y79 | D13: 44995 | E13: 010-6878-0340 | G13: IT | H13: IT | I13: stock | K13: Tony Kang 쓰던거 IPAD부족할때 사용 | L13: 해지완료
A14: 12 | B14: IPADP4_11-128 | C14: MP2C9F46FN | D14: 45079 | E14: 010-6878-0446 | F14: 1 | G14: Implants | H14: KLT | I14: Peter Oh | J14: peter.oh@stryker.com
A15: 13 | B15: IPADP4_11-128 | C15: J9157FQXYM | D15: 45079 | E15: 010-6878-0449 | F15: 1 | G15: Implants | H15: Sales | I15: Genie Kim | J15: genie.kim@stryker.com | M15: {=IFERROR(INDEX(sales!C:C,MATCH(J15,sales!C:C,0)),"LIST없음")} -> genie.kim@stryker.com
A16: 14 | B16: IPADP4_11-128 | C16: D50QVTWX76 | D16: 45079 | E16: 010-6878-0457 | G16: Medsurg | H16: MKT | I16: Bella Yoon | J16: bella.yoon@stryker.com | M16: {=IFERROR(INDEX(Printer!H:H,MATCH(J16,Printer!H:H,0)),"PRINTER LIST없음")} -> PRINTER LIST없음
A17: 15 | B17: IPADP4_11-128 | C17: GXDWV9GT62 | D17: 45079 | E17: 010-6878-0458 | F17: 1 | G17: Mako | H17: Sales | I17: david oh | J17: david.oh@stryker.com | M17: {=IFERROR(INDEX(sales!C:C,MATCH(J17,sales!C:C,0)),"LIST없음")} -> david.oh@stryker.com
A18: 16 | B18: IPADP4_11-128 | C18: G09WDG49T4 | D18: 45079 | E18: 010-6878-0459 | G18: Mako | H18: MPS | I18: Sol jung | J18: sol.jung@stryker.com
A19: 17 | B19: IPADP4_11-128 | C19: M9CN2VYJ46 | D19: 45079 | E19: 010-6878-0463 | F19: 1 | G19: Medical | H19: Sales | I19: Michelle Park | J19: michelle.park@stryker.com | M19: {=IFERROR(INDEX(sales!C:C,MATCH(J19,sales!C:C,0)),"LIST없음")} -> michelle.park@stryker.com
A20: 18 | B20: IPADP4_11-128 | C20: C14X1226DV | D20: 45079 | E20: 010-6878-0464 | G20: HR | H20: KLT | I20: Yoori Kim | J20: yoori.kim@stryker.com
A21: 19 | B21: IPADP4_11-128 | C21: TRW5JJG7JP | D21: 45079 | E21: 010-6878-0465 | G21: RAQA | H21: KLT | I21: Leslie Kim | J21: Leslie.kim@stryker.com
A22: 20 | B22: IPADP4_11-128 | C22: J6YXV33LDP | D22: 45079 | E22: 010-6878-0359 | G22: Mako | H22: MPS | I22: Jade Jung | J22: jade.jung@stryker.com
A23: 21 | B23: IPADP4_11-128 | C23: KJ44CP93XQ | D23: 45079 | E23: 010-6878-0381 | F23: 1 | G23: NV | H23: Sales | I23: Gregory Seo | J23: Gregory.Seo@stryker.com | M23: {=IFERROR(INDEX(Printer!H:H,MATCH(J23,Printer!H:H,0)),"PRINTER LIST없음")} -> Gregory.Seo@stryker.com
A24: 22 | B24: IPADP4_11-128 | C24: HW21HF1YCH | D24: 45079 | E24: 010-6878-0382 | G24: MA | H24: KLT | I24: JH Ji | J24: jh.ji@stryker.com | L24: 해지완료
A25: 23 | B25: IPADP4_11-128 | C25: KXDGGF9C90 | D25: 45079 | E25: 010-6878-0389 | F25: 1 | G25: Medusrg | H25: Sales | I25: Joy Lee | J25: joy.lee@stryker.com | M25: {=IFERROR(INDEX(sales!C:C,MATCH(J25,sales!C:C,0)),"LIST없음")} -> joy.lee@stryker.com
A26: 24 | B26: IPADP4_11-128 | C26: HC0FP2JHG7 | D26: 45079 | E26: 010-6878-0392 | F26: 1 | G26: Medsurg | H26: Sales | I26: David Kim | J26: david.kim3@stryker.com | L26: 해지완료 | M26: {=IFERROR(INDEX(sales!C:C,MATCH(J26,sales!C:C,0)),"LIST없음")} -> david.kim3@stryker.com
A27: 25 | B27: IPADP4_11-128 | C27: DG3XL2W5VX | D27: 45079 | E27: 010-6878-0394 | F27: 1 | G27: Knee | H27: MKT | I27: Jenny Jung | J27: jenny.jung@stryker.com | L27: 해지완료 | M27: {=IFERROR(INDEX(Printer!H:H,MATCH(J27,Printer!H:H,0)),"PRINTER LIST없음")} -> PRINTER LIST없음
A28: 26 | B28: IPADP4_11-128 | C28: C19HH7PP2V | D28: 45079 | E28: 010-6878-0395 | F28: 1 | G28: Mako | H28: MPS | I28: Seo Hyun Jung | J28: seohyun.jung@stryker.com
A29: 27 | B29: IPADP4_11-128 | C29: KVKXR477HX | D29: 45079 | E29: 010-6878-0398 | F29: 1 | G29: Mako | H29: MPS | I29: Shawn Kim | J29: shawn.kim@stryker.com | K29: william chai 사용한것
A30: 28 | B30: IPADP4_11-128 | C30: JN14143DQC | D30: 45079 | E30: 010-6878-0437 | F30: 1 | G30: Medsurg | H30: Sales | I30: Henry Lee | J30: henry.lee@stryker.com | M30: {=IFERROR(INDEX(sales!C:C,MATCH(J30,sales!C:C,0)),"LIST없음")} -> henry.lee@stryker.com
A31: 29 | B31: IPADP4_11-128 | C31: C2QFHGVW92 | D31: 45079 | E31: 010-6878-0443 | F31: 1 | G31: NV | H31: Sales | I31: Mi Na Song | J31: mina.song@stryker.com | M31: {=IFERROR(INDEX(sales!C:C,MATCH(J31,sales!C:C,0)),"LIST없음")} -> mina.song@stryker.com
A32: 30 | B32: IPADP4_11-128 | C32: DP77MWKXNR | D32: 45131 | E32: 010-6878-0534 | G32: TS | H32: TS | I32: Owen Park | J32: owen.park@stryker.com | M32: {=IFERROR(INDEX(Printer!H:H,MATCH(J32,Printer!H:H,0)),"PRINTER LIST없음")} -> PRINTER LIST없음
A33: 31 | B33: IPADP4_11-128 | C33: GWR3CYT2GJ | D33: 45131 | E33: 010-6878-0536 | F33: 1 | G33: Mako | H33: MKT | I33: Rosie Lee | J33: rosie.lee@stryker.com | L33: 해지완료 | M33: {=IFERROR(INDEX(Printer!H:H,MATCH(J33,Printer!H:H,0)),"PRINTER LIST없음")} -> PRINTER LIST없음
A34: 32 | B34: IPADP4_11-128 | C34: HYC714DK25 | D34: 45131 | E34: 010-6878-0541 | G34: Implants | H34: MKT | I34: Sarah Youn | J34: sarah.youn@stryker.com | L34: 해지완료 | M34: {=IFERROR(INDEX(Printer!H:H,MATCH(J34,Printer!H:H,0)),"PRINTER LIST없음")} -> PRINTER LIST없음
A35: 33 | B35: IPADP4_11-128 | C35: L4J4KPXGPN | D35: 45131 | E35: 010-6878-0548 | G35: IT | H35: IT | I35: stock | J35: - | K35: 김자영마지막 : Legal / KLT IPAD부족할때 사용 | L35: 해지완료
A36: 34 | B36: IPADP4_11-128 | C36: L2717D33PM | D36: 45131 | E36: 010-6878-0562 | F36: 1 | G36: Mako | H36: MPS | I36: Lucia Park | J36: lucia.park@stryker.com
A37: 35 | B37: IPADP4_11-128 | C37: CXVPVQXG09 | D37: 45131 | E37: 010-6878-0481 | F37: 1 | G37: Knee | H37: Sales | I37: Leo Han | J37: leo.han@stryker.com | M37: {=IFERROR(INDEX(sales!C:C,MATCH(J37,sales!C:C,0)),"LIST없음")} -> leo.han@stryker.com
A38: 36 | B38: IPADP4_11-128 | C38: P7Q3X0HYFW | D38: 45131 | E38: 010-6878-0483 | F38: 1 | G38: Knee | H38: Sales | I38: Jayden Kim | J38: jayden.kim@stryker.com | M38: {=IFERROR(INDEX(sales!C:C,MATCH(J38,sales!C:C,0)),"LIST없음")} -> jayden.kim@stryker.com
A39: 37 | B39: IPADP4_11-128 | C39: CQ0MQK66GM | D39: 45131 | E39: 010-6878-0485 | F39: 1 | G39: Knee | H39: Sales | I39: Claire Choi | J39: claire.choi@stryker.com | M39: {=IFERROR(INDEX(sales!C:C,MATCH(J39,sales!C:C,0)),"LIST없음")} -> claire.choi@stryker.com
A40: 38 | B40: IPADP4_11-128 | C40: XCYDTQ4H1F | D40: 45131 | E40: 010-6878-0487 | F40: 1 | G40: Knee | H40: Sales | I40: Suhwan Jung | J40: suhwan.jung@stryker.com | L40: 해지완료 | M40: {=IFERROR(INDEX(sales!C:C,MATCH(J40,sales!C:C,0)),"LIST없음")} -> suhwan.jung@stryker.com
A41: 39 | B41: IPADP4_11-128 | C41: LR4DPX93T4 | D41: 45131 | E41: 010-6878-0490 | F41: 1 | G41: Knee | H41: Sales | I41: Chris Shin | J41: chris.shin@stryker.com | M41: {=IFERROR(INDEX(sales!C:C,MATCH(J41,sales!C:C,0)),"LIST없음")} -> chris.shin@stryker.com
A42: 40 | B42: IPADP4_11-128 | C42: JWXX9D7C0H | D42: 45131 | E42: 010-6878-0491 | G42: Operation | H42: KLT | I42: YJ Seo | J42: yj.seo@stryker.com
A43: 41 | B43: IPADP4_11-128 | C43: D1HJ9KM7XJ | D43: 45131 | E43: 010-6878-0492 | F43: 1 | G43: Knee | H43: Sales | I43: Hailey Song | J43: hailey.song@stryker.com | M43: {=IFERROR(INDEX(sales!C:C,MATCH(J43,sales!C:C,0)),"LIST없음")} -> hailey.song@stryker.com
A44: 42 | B44: IPADP4_11-128 | C44: M6T0VJHK6P | D44: 45131 | E44: 010-6878-0496 | F44: 1 | G44: Implants | H44: Sales | I44: Jason Kim | J44: jason.kim1@stryker.com | M44: {=IFERROR(INDEX(sales!C:C,MATCH(J44,sales!C:C,0)),"LIST없음")} -> jason.kim1@stryker.com
A45: 43 | B45: IPADP4_11-128 | C45: DWFLMWX243 | D45: 45131 | E45: 010-6878-0498 | G45: Medusrg | H45: Sales | I45: Danny Kim | J45: danny.kim@stryker.com | M45: {=IFERROR(INDEX(sales!C:C,MATCH(J45,sales!C:C,0)),"LIST없음")} -> danny.kim@stryker.com
A46: 44 | B46: IPADP4_11-128 | C46: H7Q22YXYWF | D46: 45131 | E46: 010-6878-0499 | F46: 1 | G46: Knee | H46: Sales | I46: Louis Kang | J46: louis.kang@stryker.com | M46: {=IFERROR(INDEX(sales!C:C,MATCH(J46,sales!C:C,0)),"LIST없음")} -> louis.kang@stryker.com
A47: 45 | B47: IPADP4_11-128 | C47: J99N6MMPMT | D47: 45131 | E47: 010-6878-0461 | F47: 1 | G47: Knee | H47: Sales | I47: Ashley Hong | J47: ashley.hong@stryker.com | M47: {=IFERROR(INDEX(sales!C:C,MATCH(J47,sales!C:C,0)),"LIST없음")} -> ashley.hong@stryker.com
A48: 46 | B48: IPADP4_11-128 | C48: JYVMXW3RWV | D48: 45131 | E48: 010-6878-0467 | F48: 1 | G48: Knee | H48: Sales | I48: Jiho Yoo | J48: jiho.yoo@stryker.com | K48: 데이터0 | M48: {=IFERROR(INDEX(sales!C:C,MATCH(J48,sales!C:C,0)),"LIST없음")} -> jiho.yoo@stryker.com
A49: 47 | B49: IPADP4_11-128 | C49: M2FKP9T7QX | D49: 45131 | E49: 010-6878-0469 | F49: 1 | G49: Knee | H49: Sales | I49: Yoonbee Jeong | J49: yoonbee.jeong@stryker.com | M49: {=IFERROR(INDEX(Printer!H:H,MATCH(J49,Printer!H:H,0)),"PRINTER LIST없음")} -> yoonbee.jeong@stryker.com
A50: 48 | B50: IPADP4_11-128 | C50: CJ66CPWXQ2 | D50: 45131 | E50: 010-6878-0471 | F50: 1 | G50: Knee | H50: Sales | I50: Ara Ko | J50: ara.ko@stryker.com | M50: {=IFERROR(INDEX(sales!C:C,MATCH(J50,sales!C:C,0)),"LIST없음")} -> ara.ko@stryker.com
A51: 49 | B51: IPADP4_11-128 | C51: JFK7CC9090 | D51: 45131 | E51: 010-6878-0472 | F51: 1 | G51: Knee | H51: Sales | I51: Scott Jo | J51: scott.jo@stryker.com | M51: {=IFERROR(INDEX(sales!C:C,MATCH(J51,sales!C:C,0)),"LIST없음")} -> scott.jo@stryker.com
A52: 50 | B52: IPADP4_11-128 | C52: MK21Q5L65C | D52: 45131 | E52: 010-6878-0473 | F52: 1 | G52: NV | H52: Sales | I52: Jackson Kim | J52: jackson.kim@stryker.com | M52: {=IFERROR(INDEX(Printer!H:H,MATCH(J52,Printer!H:H,0)),"PRINTER LIST없음")} -> jackson.kim@stryker.com
A53: 51 | B53: IPADP4_11-128 | C53: GXK670F7DH | D53: 45131 | E53: 010-6878-0474 | G53: Implants | H53: Sales | I53: Peter Park | J53: peter.park@stryker.com | M53: {=IFERROR(INDEX(sales!C:C,MATCH(J53,sales!C:C,0)),"LIST없음")} -> peter.park@stryker.com
A54: 52 | B54: IPADP4_11-128 | C54: F9XWF4345F | D54: 45131 | E54: 010-6878-0475 | F54: 1 | G54: Mako | H54: Sales | I54: Dongkyu Kim | J54: dongkyu.kim@stryker.com | M54: {=IFERROR(INDEX(sales!C:C,MATCH(J54,sales!C:C,0)),"LIST없음")} -> dongkyu.kim@stryker.com
A55: 53 | B55: IPADP4_11-128 | C55: DXP5W6NH22 | D55: 45131 | E55: 010-6878-0476 | F55: 1 | G55: IT | H55: KLT | I55: Jun Song | J55: jun.song@stryker.com
A56: 54 | B56: IPADP4_11-128 | C56: MNPXXL2C5X | D56: 45131 | E56: 010-6878-0479 | F56: 1 | G56: Medsurg | H56: Sales | I56: Hyoseon Park | J56: hyoseon.park@stryker.com | M56: {=IFERROR(INDEX(sales!C:C,MATCH(J56,sales!C:C,0)),"LIST없음")} -> hyoseon.park@stryker.com
A57: 55 | B57: IPADP4_11-128 | C57: JJWL6VTHKK | D57: 45204 | E57: 010-6878-0571 | F57: 1 | G57: Mako | H57: MPS | I57: Aspyn Kim | J57: aspyn.kim@stryker.com
A58: 56 | B58: IPADP4_11-128 | C58: DFC7V7Q9X3 | D58: 45204 | E58: 010-6878-0568 | F58: 1 | G58: Mako | H58: MPS | I58: Somi Jeong | J58: somi.jeong@stryker.com
A59: 57 | B59: IPADP4_11-128 | C59: K9NWHMWT44 | D59: 45204 | E59: 010-6878-0573 | F59: 1 | G59: Mako | H59: MPS | I59: Minjeong Kim | J59: minjeong.kim@stryker.com
A60: 58 | B60: IPADP4_11-128 | C60: LY9JGJQMTP | D60: 45204 | E60: 010-6878-0348 | F60: 1 | G60: Mako | H60: MPS | I60: Mindo Kim | J60: mindo.kim@stryker.com
A61: 59 | B61: IPADP4_11-128 | C61: DYQP729JPM | D61: 45204 | E61: 010-6878-0575 | F61: 1 | G61: NV | H61: Sales | I61: Yejin Heo | J61: yejin.heo@stryker.com | M61: {=IFERROR(INDEX(sales!C:C,MATCH(J61,sales!C:C,0)),"LIST없음")} -> yejin.heo@stryker.com
A62: 60 | B62: IPADP4_11-128 | C62: FQPW2GVP7C | D62: 45246 | E62: 010-6878-0640 | G62: NV | H62: MKT | I62: Rayna Kim | J62: Rayna.Kim@stryker.com | M62: {=IFERROR(INDEX(Printer!H:H,MATCH(J62,Printer!H:H,0)),"PRINTER LIST없음")} -> PRINTER LIST없음
A63: 61 | B63: IPADP4_11-128 | C63: GYGG3N90Y4 | D63: 45246 | E63: 010-6878-0644 | F63: 1 | G63: Medsurg | H63: KLT | I63: Roy Lim | J63: roy.lim@stryker.com
A64: 62 | B64: IPADP4_11-128 | C64: MX224565CF | D64: 45246 | E64: 010-6878-0649 | F64: 1 | G64: Shoulder | H64: Sales | I64: Mason Oh | J64: mason.oh@stryker.com | M64: {=IFERROR(INDEX(sales!C:C,MATCH(J64,sales!C:C,0)),"LIST없음")} -> mason.oh@stryker.com
A65: 63 | B65: IPADP4_11-128 | C65: DMW34MWM7C | D65: 45246 | E65: 010-6878-0652 | F65: 1 | G65: Mako | H65: MPS | I65: Ayaan Yoon | J65: ayaan.yoon@stryker.com
A66: 64 | B66: IPADP4_11-128 | C66: GGWR7NXY2D | D66: 45246 | E66: 010-6878-0657 | F66: 1 | G66: Shoulder | H66: Sales | I66: Jay Ji | J66: jay.ji@stryker.com | M66: {=IFERROR(INDEX(Printer!H:H,MATCH(J66,Printer!H:H,0)),"PRINTER LIST없음")} -> PRINTER LIST없음
A67: 65 | B67: IPADP4_11-128 | C67: C4RQH3W74V | D67: 45246 | E67: 010-6878-0659 | F67: 1 | G67: TS | H67: TS | I67: Andrew Ahn | J67: andrew.ahn@stryker.com | M67: {=IFERROR(INDEX(Printer!H:H,MATCH(J67,Printer!H:H,0)),"PRINTER LIST없음")} -> PRINTER LIST없음
A68: 66 | B68: IPADP4_11-128 | C68: LHJDGDMQCH | D68: 45246 | E68: 010-6878-0670 | F68: 1 | G68: Implants | H68: Sales | I68: Ayaan Lee | J68: ayaan.lee@stryker.com | M68: {=IFERROR(INDEX(sales!C:C,MATCH(J68,sales!C:C,0)),"LIST없음")} -> ayaan.lee@stryker.com
A69: 67 | B69: IPADP4_11-128 | C69: HYFKQFR4RD | D69: 45246 | E69: 010-6878-0672 | F69: 1 | G69: Mako | H69: MKT | I69: Yeonjoo Kim | J69: yeonjoo.kim@stryker.com | M69: {=IFERROR(INDEX(Printer!H:H,MATCH(J69,Printer!H:H,0)),"PRINTER LIST없음")} -> yeonjoo.kim@stryker.com
A70: 68 | B70: iPadP4_11-128GB | C70: GD2WG3K71P | D70: 45321 | E70: 010-6878-0138 | G70: Medsurg | H70: Sales | I70: Theo Hwang | J70: theo.hwang@stryker.com | M70: {=IFERROR(INDEX(sales!C:C,MATCH(J70,sales!C:C,0)),"LIST없음")} -> theo.hwang@stryker.com
A71: 69 | B71: iPadP4_11-128GB | C71: MKTFHJRWT2 | D71: 45321 | E71: 010-6878-0237 | F71: 1 | G71: Medsurg | H71: Sales | I71: Brad Choi | J71: brad.choi@stryker.com | M71: {=IFERROR(INDEX(sales!C:C,MATCH(J71,sales!C:C,0)),"LIST없음")} -> brad.choi@stryker.com
A72: 70 | B72: iPadP4_11-128GB | C72: Q4VGFW40QV | D72: 45330 | E72: 010-6878-0769 | G72: TS | H72: TS | I72: Carl Cha | J72: carl.cha@stryker.com | M72: {=IFERROR(INDEX(Printer!H:H,MATCH(J72,Printer!H:H,0)),"PRINTER LIST없음")} -> PRINTER LIST없음
A73: 71 | B73: IPADP_M4-11-256 | C73: XYGFK42KQP | D73: 45474 | E73: 010-6804-6949 | G73: TS | H73: TS | I73: Oscar Hwang | J73: oscar.hwang@stryker.com | M73: {=IFERROR(INDEX(Printer!H:H,MATCH(J73,Printer!H:H,0)),"PRINTER LIST없음")} -> oscar.hwang@stryker.com
A74: 72 | B74: IPADP_M4-11-256 | C74: Q5M6F1YX19 | D74: 45474 | E74: 010-7306-6949 | F74: 1 | G74: Shoulder | H74: Sales | I74: James Kim | J74: james.kim@stryker.com | M74: {=IFERROR(INDEX(sales!C:C,MATCH(J74,sales!C:C,0)),"LIST없음")} -> james.kim@stryker.com
A75: 73 | B75: IPADP_M4-11-256 | C75: GW245H3KYL | D75: 45474 | E75: 010-5168-6949 | F75: 1 | G75: Medsurg | H75: Sales | I75: Nathan Eom | J75: Nathan.Eom@stryker.com | M75: {=IFERROR(INDEX(sales!C:C,MATCH(J75,sales!C:C,0)),"LIST없음")} -> Nathan.Eom@stryker.com
A76: 74 | B76: IPADP_M4-11-256 | C76: VHJMJWTK6N | D76: 45474 | E76: 010-4339-6949 | F76: 1 | G76: Mako | H76: MPS | I76: kim hannah | J76: hannah.kim@stryker.com
A77: 75 | B77: IPADP_M4-11-256 | C77: YWFN4L7RQJ | D77: 45474 | E77: 010-9528-6949 | F77: 1 | G77: Medsurg | H77: Sales | I77: Jin Park | J77: jin.park@stryker.com | M77: {=IFERROR(INDEX(sales!C:C,MATCH(J77,sales!C:C,0)),"LIST없음")} -> jin.park@stryker.com
A78: 76 | B78: IPADP_M4-11-256 | C78: J7J79LY961 | D78: 45474 | E78: 010-9627-6949 | F78: 1 | G78: NV | H78: Sales | I78: Lucas Jeon | J78: lucas.jeon@stryker.com | M78: {=IFERROR(INDEX(sales!C:C,MATCH(J78,sales!C:C,0)),"LIST없음")} -> lucas.jeon@stryker.com
A79: 77 | B79: IPADP_M4-11-256 | C79: LD0W924NX3 | D79: 45474 | E79: 010-6847-6949 | F79: 1 | G79: Mako | H79: MPS | I79: Roy Choi | J79: roy.choi@stryker.com
A80: 78 | B80: IPADP_M4-11-256 | C80: QT422FMH26 | D80: 45474 | E80: 010-7434-6949 | F80: 1 | G80: Compliance | H80: KLT | I80: Soyoun Kim | J80: soyoun.kim@stryker.com
A81: 79 | B81: IPADP_M4-11-256 | C81: P40KK7NLQG | D81: 45474 | E81: 010-9725-6949 | F81: 1 | G81: Mako | H81: MPS | I81: Mason Kim | J81: mason.kim1@stryker.com
A82: 80 | B82: IPADP_M4-11-256 | C82: M90KHK7Y1F | D82: 45565 | E82: 010-3414-6949 | G82: Medsurg | H82: Sales | I82: Dana Shin | J82: dana.shin@stryker.com | M82: {=IFERROR(INDEX(sales!C:C,MATCH(J82,sales!C:C,0)),"LIST없음")} -> dana.shin@stryker.com
A83: 81 | B83: IPADP_M4-11-256 | C83: L2Q9F70301 | D83: 45565 | E83: 010-6704-6949 | F83: 1 | G83: Medsurg | H83: Sales | I83: Martin Cho | J83: martin.cho@stryker.com | M83: {=IFERROR(INDEX(sales!C:C,MATCH(J83,sales!C:C,0)),"LIST없음")} -> martin.cho@stryker.com
A84: 82 | B84: IPADP_M4-11-256 | C84: OQ2GGXF3FK | D84: 45565 | E84: 010-9548-6949 | F84: 1 | G84: Knee | H84: Sales | I84: sung hoon bang | J84: sunghoon.bang@stryker.com | M84: {=IFERROR(INDEX(sales!C:C,MATCH(J84,sales!C:C,0)),"LIST없음")} -> sunghoon.bang@stryker.com
A85: 83 | B85: IPADP_M4-11-256 | C85: Q9JKF6RRK4 | D85: 45600 | E85: 010-6725-6949 | F85: 1 | G85: Shoulder | H85: Sales | I85: Daniel jang | J85: daniel.jang@stryker.com | M85: {=IFERROR(INDEX(sales!C:C,MATCH(J85,sales!C:C,0)),"LIST없음")} -> daniel.jang@stryker.com
A86: 84 | B86: IPADP_M4-11-256 | C86: MXK59D7LPL | D86: 45600 | E86: 010-9787-6949 | F86: 1 | G86: Medsurg | H86: Sales | I86: Ethan Na | J86: ethan.na@stryker.com | M86: {=IFERROR(INDEX(sales!C:C,MATCH(J86,sales!C:C,0)),"LIST없음")} -> ethan.na@stryker.com
A87: 85 | B87: IPADP_M4-11-256 | C87: M7WVNHQ0YQ | D87: 45600 | E87: 010-4459-6949 | F87: 1 | G87: Mako | H87: KLT | I87: Jeff Lee | J87: Jeff.Lee@stryker.com
A88: 86 | B88: IPADP_M4-11-256 | C88: XGH27YLWQM | D88: 45600 | E88: 010-7458-6949 | F88: 1 | G88: Implants | H88: MKT | I88: Minki Kim | J88: minki.kim@stryker.com | M88: {=IFERROR(INDEX(Printer!H:H,MATCH(J88,Printer!H:H,0)),"PRINTER LIST없음")} -> PRINTER LIST없음
A89: 87 | B89: IPADP_M4-11-256 | C89: VKGPQR7276 | D89: 45600 | E89: 010-7254-6949 | G89: ICM | H89: KLT | I89: James Kang | J89: James.Kang@stryker.com
A90: 88 | B90: IPADP_M4-11-256 | C90: RVF25297YV | D90: 45600 | E90: 010-6860-6949 | F90: 1 | G90: TS | H90: TS | I90: Jayden Song | J90: jayden.song@stryker.com | M90: {=IFERROR(INDEX(Printer!H:H,MATCH(J90,Printer!H:H,0)),"PRINTER LIST없음")} -> PRINTER LIST없음
A91: 89 | B91: IPADP_M4-11-256 | C91: MQ6X021QX2 | D91: 45600 | E91: 010-4468-6949 | F91: 1 | G91: Implants | H91: Sales | I91: Suhyun Kim | J91: Suhyun.Kim@stryker.com | M91: {=IFERROR(INDEX(sales!C:C,MATCH(J91,sales!C:C,0)),"LIST없음")} -> Suhyun.Kim@stryker.com
A92: 90 | B92: IPADP_M4-11-256 | C92: GHL46K1F9M | D92: 45600 | E92: 010-9723-6949 | F92: 1 | G92: NV | H92: Sales | I92: Ian hwang | J92: ian.hwang@stryker.com | K92: 10/28 esim삭제로 재등록 , 비용 2700원 발생 /Jayden Shin 반납한것 | M92: {=IFERROR(INDEX(Printer!H:H,MATCH(J92,Printer!H:H,0)),"PRINTER LIST없음")} -> ian.hwang@stryker.com
A93: 91 | B93: IPADP_M4-11-256 | C93: FNP3C7WRP2 | D93: 45600 | E93: 010-6852-6949 | F93: 1 | G93: NV | H93: Sales | I93: Young Hwang | J93: young.hwang@stryker.com | M93: {=IFERROR(INDEX(sales!C:C,MATCH(J93,sales!C:C,0)),"LIST없음")} -> young.hwang@stryker.com
A94: 92 | B94: IPADP_M4-11-256 | C94: FWJG39XV9Q | D94: 45600 | E94: 010-7350-6949 | G94: Medsurg | H94: Sales | I94: Simon Sin | J94: Simon.sin@stryker.com | M94: {=IFERROR(INDEX(sales!C:C,MATCH(J94,sales!C:C,0)),"LIST없음")} -> Simon.sin@stryker.com
A95: 93 | B95: IPADP_M4-11-256 | C95: FN47DRXYYW | D95: 45600 | E95: 010-9594-6949 | F95: 1 | G95: TS | H95: TS | I95: Daniel Lee | J95: daniel.lee1@stryker.com | M95: {=IFERROR(INDEX(Printer!H:H,MATCH(J95,Printer!H:H,0)),"PRINTER LIST없음")} -> daniel.lee1@stryker.com
A96: 94 | B96: IPADP_M4-11-256 | C96: W6RQPLQLJY | D96: 45600 | E96: 010-9606-6949 | F96: 1 | G96: Medsurg | H96: Sales | I96: Daniel Park | J96: daniel.park@stryker.com | M96: {=IFERROR(INDEX(sales!C:C,MATCH(J96,sales!C:C,0)),"LIST없음")} -> daniel.park@stryker.com
A97: 95 | B97: IPADP_M4-11-256 | C97: HP6F2M6GJ7 | D97: 45600 | E97: 010-3409-6949 | G97: NV | H97: Sales | I97: Kyu choi | J97: kyu.choi@stryker.com | M97: {=IFERROR(INDEX(sales!C:C,MATCH(J97,sales!C:C,0)),"LIST없음")} -> kyu.choi@stryker.com
A98: 96 | B98: IPADP_M4-11-256 | C98: THD6Q4W3LT | D98: 45600 | E98: 010-4365-6949 | F98: 1 | G98: Mako | H98: Sales | I98: Justin Kim | J98: Justin.Kim@stryker.com | M98: {=IFERROR(INDEX(sales!C:C,MATCH(J98,sales!C:C,0)),"LIST없음")} -> Justin.Kim@stryker.com
A99: 97 | B99: IPADP_M4-11-256 | C99: WR34FVRW4C | D99: 45600 | E99: 010-6517-6949 | F99: 1 | G99: Mako | H99: MPS | I99: Bryan Park | J99: bryan.park@stryker.com | K99: Shoulder KLT 사용하던것
A100: 98 | B100: IPADP_M4-11-256 | C100: L69V0Q1VT3 | D100: 45600 | E100: 010-9604-6949 | G100: Mako | H100: MPS | I100: GD Ahn | J100: gd.ahn@stryker.com
A101: 99 | B101: IPADP_M4-11-256 | C101: RFJJ97J4YG | D101: 45600 | E101: 010-9539-6949 | G101: TS | H101: TS | I101: Huey Sim | J101: Huey.Sim@stryker.com | M101: {=IFERROR(INDEX(Printer!H:H,MATCH(J101,Printer!H:H,0)),"PRINTER LIST없음")} -> Huey.Sim@stryker.com
...

Sheet Printer
B1: Model | C1: date | D1: Additional Information 2 | E1: User | F1: BU | G1: ROLE | H1: email | I1: 카트리지 사용 내역
A2: 1 | B2: 삼성복합기 | D2: SL-C486FW | E2: OA Room | F2: 아셈타워 | G2: oa
A3: 2 | B3: 삼성복합기 | D3: 2차 조사 정보 없음 | E3: Jason Kim | F3: Implants | G3: Sales | H3: jason.kim1@stryker.com | J3: {=IFERROR(INDEX(All_User!D:D,MATCH(H3,All_User!D:D,0)),"없음")} -> jason.kim1@stryker.com | L3: {=IFERROR(INDEX(sales!G:G,MATCH(H3,sales!C:C,0)),"없음")} -> 2차 조사 정보 없음
A4: 3 | B4: SL-C486FW | C4: 45597 | D4: SL-C486FW | E4: Suhyun Kim | F4: Implants | G4: Sales | H4: Suhyun.Kim@stryker.com | J4: {=IFERROR(INDEX(All_User!D:D,MATCH(H4,All_User!D:D,0)),"없음")} -> Suhyun.Kim@stryker.com | L4: {=IFERROR(INDEX(sales!G:G,MATCH(H4,sales!C:C,0)),"없음")} -> SL-C486FW
A5: 4 | D5: 반납 | E5: Genie Kim | F5: Implants | G5: Sales | H5: genie.kim@stryker.com | J5: {=IFERROR(INDEX(All_User!D:D,MATCH(H5,All_User!D:D,0)),"없음")} -> genie.kim@stryker.com | L5: {=IFERROR(INDEX(sales!G:G,MATCH(H5,sales!C:C,0)),"없음")} -> 반납
A6: 5 | B6: SL-C563W | C6: 45108 | D6: SL-C563W | E6: Ayaan Lee | F6: Implants | G6: Sales | H6: ayaan.lee@stryker.com | J6: {=IFERROR(INDEX(All_User!D:D,MATCH(H6,All_User!D:D,0)),"없음")} -> ayaan.lee@stryker.com | L6: {=IFERROR(INDEX(sales!G:G,MATCH(H6,sales!C:C,0)),"없음")} -> SL-C563W
A7: 6 | B7: SL-C563W | C7: 45108 | D7: SL-C563W | E7: Martin Cho | F7: Implants | G7: Sales | H7: martin.cho@stryker.com | I7: SCLT-510Y (1) | J7: {=IFERROR(INDEX(All_User!D:D,MATCH(H7,All_User!D:D,0)),"없음")} -> martin.cho@stryker.com | L7: {=IFERROR(INDEX(sales!G:G,MATCH(H7,sales!C:C,0)),"없음")} -> SL-C563W
A8: 8 | B8: 삼성복합기 | C8: 2023년 9월 4색토너 | D8: SL-C438W | E8: Peter Park | F8: Shoulder | G8: Sales | H8: peter.park@stryker.com | J8: {=IFERROR(INDEX(All_User!D:D,MATCH(H8,All_User!D:D,0)),"없음")} -> peter.park@stryker.com | L8: {=IFERROR(INDEX(sales!G:G,MATCH(H8,sales!C:C,0)),"없음")} -> SL-C438W
A9: 9 | B9: 삼성복합기 | D9: 2차 조사 정보 없음 | E9: Mason Oh | F9: Shoulder | G9: Sales | H9: mason.oh@stryker.com | J9: {=IFERROR(INDEX(All_User!D:D,MATCH(H9,All_User!D:D,0)),"없음")} -> mason.oh@stryker.com | L9: {=IFERROR(INDEX(sales!G:G,MATCH(H9,sales!C:C,0)),"없음")} -> 2차 조사 정보 없음
A10: 10 | D10: SL-C486FW | E10: James Kim | F10: Shoulder | G10: Sales | H10: james.kim@stryker.com | J10: {=IFERROR(INDEX(All_User!D:D,MATCH(H10,All_User!D:D,0)),"없음")} -> james.kim@stryker.com | L10: {=IFERROR(INDEX(sales!G:G,MATCH(H10,sales!C:C,0)),"없음")} -> SL-C486FW
A11: 11 | B11: 삼성복합기 | D11: 확인중 | E11: Jeff Lee | F11: Mako | G11: Sales | H11: Jeff.Lee@stryker.com | J11: {=IFERROR(INDEX(All_User!D:D,MATCH(H11,All_User!D:D,0)),"없음")} -> Jeff.Lee@stryker.com | L11: {=IFERROR(INDEX(sales!G:G,MATCH(H11,sales!C:C,0)),"없음")} -> 확인중
A12: 12 | B12: 삼성복합기 | D12: SL-C483FW | E12: David Yang | F12: Mako | G12: Sales | H12: David.Yang@stryker.com | J12: {=IFERROR(INDEX(All_User!D:D,MATCH(H12,All_User!D:D,0)),"없음")} -> David.Yang@stryker.com | L12: {=IFERROR(INDEX(sales!G:G,MATCH(H12,sales!C:C,0)),"없음")} -> SL-C483FW
A13: 13 | B13: 삼성복합기 | C13: 2023년 12월 4색 토너 | D13: SL-C565W | E13: Justin Kim | F13: Mako | G13: Sales | H13: Justin.Kim@stryker.com | J13: {=IFERROR(INDEX(All_User!D:D,MATCH(H13,All_User!D:D,0)),"없음")} -> Justin.Kim@stryker.com | L13: {=IFERROR(INDEX(sales!G:G,MATCH(H13,sales!C:C,0)),"없음")} -> SL-C565W
A14: 14 | B14: 삼성복합기 | D14: SL-C565FW | E14: Willy Chang | F14: Mako | G14: Sales | H14: Willy.Chang@stryker.com | J14: {=IFERROR(INDEX(All_User!D:D,MATCH(H14,All_User!D:D,0)),"없음")} -> Willy.Chang@stryker.com | L14: {=IFERROR(INDEX(sales!G:G,MATCH(H14,sales!C:C,0)),"없음")} -> SL-C565FW
A15: 15 | B15: 삼성복합기 | D15: SL-C486FW | E15: David Oh | F15: Mako | G15: Sales | H15: david.oh@stryker.com | J15: {=IFERROR(INDEX(All_User!D:D,MATCH(H15,All_User!D:D,0)),"없음")} -> david.oh@stryker.com | L15: {=IFERROR(INDEX(sales!G:G,MATCH(H15,sales!C:C,0)),"없음")} -> SL-C486FW
A16: 16 | B16: 삼성복합기 | D16: 확인중 | E16: GD Ahn | F16: Mako | G16: Sales | H16: gd.ahn@stryker.com | J16: {=IFERROR(INDEX(All_User!D:D,MATCH(H16,All_User!D:D,0)),"없음")} -> gd.ahn@stryker.com | L16: {=IFERROR(INDEX(sales!G:G,MATCH(H16,sales!C:C,0)),"없음")} -> 확인중
A17: 17 | B17: 삼성복합기 | D17: 폐기 | E17: Roy Choi | F17: Mako | G17: Sales | H17: roy.choi@stryker.com | J17: {=IFERROR(INDEX(All_User!D:D,MATCH(H17,All_User!D:D,0)),"없음")} -> roy.choi@stryker.com | L17: {=IFERROR(INDEX(sales!G:G,MATCH(H17,sales!C:C,0)),"없음")} -> 폐기
A18: 18 | B18: SL-C563W | C18: 45261 | D18: SL-C563W | E18: Yeonjoo Kim | F18: Mako | G18: Sales | H18: yeonjoo.kim@stryker.com | J18: {=IFERROR(INDEX(All_User!D:D,MATCH(H18,All_User!D:D,0)),"없음")} -> yeonjoo.kim@stryker.com | L18: {=IFERROR(INDEX(sales!G:G,MATCH(H18,sales!C:C,0)),"없음")} -> SL-C563W
A19: 19 | B19: SL-C563W | C19: 45292 | D19: SL-C563W | E19: Yoonbee Jeong | F19: Mako | G19: Sales | H19: yoonbee.jeong@stryker.com | J19: {=IFERROR(INDEX(All_User!D:D,MATCH(H19,All_User!D:D,0)),"없음")} -> yoonbee.jeong@stryker.com | L19: {=IFERROR(INDEX(sales!G:G,MATCH(H19,sales!C:C,0)),"없음")} -> SL-C563W
A20: 20 | B20: SL-C563W | C20: 45292 | D20: SL-C563W | E20: Leo Han | F20: Mako | G20: Sales | H20: leo.han@stryker.com | J20: {=IFERROR(INDEX(All_User!D:D,MATCH(H20,All_User!D:D,0)),"없음")} -> leo.han@stryker.com | L20: {=IFERROR(INDEX(sales!G:G,MATCH(H20,sales!C:C,0)),"없음")} -> SL-C563W
A21: 21 | B21: SL-C563W | C21: 45292 | D21: SL-C563W | E21: Claire Choi | F21: Mako | G21: Sales | H21: claire.choi@stryker.com | J21: {=IFERROR(INDEX(All_User!D:D,MATCH(H21,All_User!D:D,0)),"없음")} -> claire.choi@stryker.com | L21: {=IFERROR(INDEX(sales!G:G,MATCH(H21,sales!C:C,0)),"없음")} -> SL-C563W
A22: 22 | B22: SL-C563W | C22: 45689 | D22: SL-C563W | E22: Jayden Kim | F22: Mako | G22: Sales | H22: jayden.kim@stryker.com | J22: {=IFERROR(INDEX(All_User!D:D,MATCH(H22,All_User!D:D,0)),"없음")} -> jayden.kim@stryker.com | L22: {=IFERROR(INDEX(sales!G:G,MATCH(H22,sales!C:C,0)),"없음")} -> SL-C563W
A23: 23 | B23: 삼성복합기 | D23: 2차 조사 정보 없음 | E23: JW Yoon | F23: Knee | G23: Sales | H23: jw.yoon@stryker.com | J23: {=IFERROR(INDEX(All_User!D:D,MATCH(H23,All_User!D:D,0)),"없음")} -> jw.yoon@stryker.com | L23: {=IFERROR(INDEX(sales!G:G,MATCH(H23,sales!C:C,0)),"없음")} -> 2차 조사 정보 없음
A24: 24 | B24: 삼성복합기 | D24: SL-C486FW | E24: Jiho Yoo | F24: Knee | G24: Sales | H24: jiho.yoo@stryker.com | J24: {=IFERROR(INDEX(All_User!D:D,MATCH(H24,All_User!D:D,0)),"없음")} -> jiho.yoo@stryker.com | L24: {=IFERROR(INDEX(sales!G:G,MATCH(H24,sales!C:C,0)),"없음")} -> SL-C486FW
A25: 25 | B25: SL-C563W | C25: 45352 | D25: SL-C563W | E25: Louis Kang | F25: Knee | G25: Sales | H25: louis.kang@stryker.com | J25: {=IFERROR(INDEX(All_User!D:D,MATCH(H25,All_User!D:D,0)),"없음")} -> louis.kang@stryker.com | L25: {=IFERROR(INDEX(sales!G:G,MATCH(H25,sales!C:C,0)),"없음")} -> SL-C563W
A26: 26 | B26: 삼성복합기 | C26: 45474 | D26: SL-C563W | E26: Theo Hwang | F26: Knee | G26: Sales | H26: theo.hwang@stryker.com | J26: {=IFERROR(INDEX(All_User!D:D,MATCH(H26,All_User!D:D,0)),"없음")} -> theo.hwang@stryker.com | L26: {=IFERROR(INDEX(sales!G:G,MATCH(H26,sales!C:C,0)),"없음")} -> SL-C563W
A27: 27 | B27: 삼성복합기 | D27: 2차 조사 정보 없음 | E27: Jack Eum | F27: Knee | G27: Sales | H27: jack.eum@stryker.com | J27: {=IFERROR(INDEX(All_User!D:D,MATCH(H27,All_User!D:D,0)),"없음")} -> jack.eum@stryker.com | L27: {=IFERROR(INDEX(sales!G:G,MATCH(H27,sales!C:C,0)),"없음")} -> 2차 조사 정보 없음
A28: 28 | B28: 삼성복합기 | D28: 2차 조사 정보 없음 | E28: Jin Park | F28: MedSurg | G28: Sales | H28: jin.park@stryker.com | J28: {=IFERROR(INDEX(All_User!D:D,MATCH(H28,All_User!D:D,0)),"없음")} -> jin.park@stryker.com | L28: {=IFERROR(INDEX(sales!G:G,MATCH(H28,sales!C:C,0)),"없음")} -> 2차 조사 정보 없음
A29: 29 | B29: 삼성복합기 | D29: SL-C483W | E29: Jaewook Chung | F29: MedSurg | G29: Sales | H29: jae.chung@stryker.com | J29: {=IFERROR(INDEX(All_User!D:D,MATCH(H29,All_User!D:D,0)),"없음")} -> jae.chung@stryker.com | L29: {=IFERROR(INDEX(sales!G:G,MATCH(H29,sales!C:C,0)),"없음")} -> SL-C483W
A30: 30 | B30: 삼성복합기 | D30: SL-C486FW | E30: Henry Lee | F30: MedSurg | G30: Sales | H30: henry.lee@stryker.com | J30: {=IFERROR(INDEX(All_User!D:D,MATCH(H30,All_User!D:D,0)),"없음")} -> henry.lee@stryker.com | L30: {=IFERROR(INDEX(sales!G:G,MATCH(H30,sales!C:C,0)),"없음")} -> SL-C486FW
A31: 31 | B31: 삼성복합기 | D31: SL-C486FW | E31: Nathan Eom | F31: MedSurg | G31: Sales | H31: Nathan.Eom@stryker.com | J31: {=IFERROR(INDEX(All_User!D:D,MATCH(H31,All_User!D:D,0)),"없음")} -> Nathan.Eom@stryker.com | L31: {=IFERROR(INDEX(sales!G:G,MATCH(H31,sales!C:C,0)),"없음")} -> SL-C486FW
A32: 32 | B32: SL-C563W | C32: 45413 | D32: SL-C563W | E32: Ethan Na | F32: MedSurg | G32: Sales | H32: ethan.na@stryker.com | I32: SCLT-510Y, C, M (3) | J32: {=IFERROR(INDEX(All_User!D:D,MATCH(H32,All_User!D:D,0)),"없음")} -> ethan.na@stryker.com | L32: {=IFERROR(INDEX(sales!G:G,MATCH(H32,sales!C:C,0)),"없음")} -> SL-C563W
A33: 33 | B33: SL-C563W | C33: 45444 | D33: SL-C563W | E33: Joy Lee | F33: MedSurg | G33: Sales | H33: joy.lee@stryker.com | J33: {=IFERROR(INDEX(All_User!D:D,MATCH(H33,All_User!D:D,0)),"없음")} -> joy.lee@stryker.com | L33: {=IFERROR(INDEX(sales!G:G,MATCH(H33,sales!C:C,0)),"없음")} -> SL-C563W
A34: 34 | B34: SL-C563W | C34: 45139 | D34: SL-C563W | E34: Danny Kim | F34: MedSurg | G34: Sales | H34: danny.kim@stryker.com | J34: {=IFERROR(INDEX(All_User!D:D,MATCH(H34,All_User!D:D,0)),"없음")} -> danny.kim@stryker.com | L34: {=IFERROR(INDEX(sales!G:G,MATCH(H34,sales!C:C,0)),"없음")} -> SL-C563W
A35: 35 | B35: 삼성복합기 | D35: 폐기함 | E35: Jayden Shin | F35: MedSurg | G35: Sales | H35: jayden.shin@stryker.com | J35: {=IFERROR(INDEX(All_User!D:D,MATCH(H35,All_User!D:D,0)),"없음")} -> 없음 | L35: {=IFERROR(INDEX(sales!G:G,MATCH(H35,sales!C:C,0)),"없음")} -> 없음
A36: 36 | B36: 삼성복합기 | D36: 모델명 확인요망 | E36: Andy Lee | F36: Medical | G36: Medical | H36: Andy.Lee@stryker.com | J36: {=IFERROR(INDEX(All_User!D:D,MATCH(H36,All_User!D:D,0)),"없음")} -> 없음 | L36: {=IFERROR(INDEX(sales!G:G,MATCH(H36,sales!C:C,0)),"없음")} -> 없음
A37: 37 | B37: 삼성복합기 | D37: SL-C486FW | E37: Dana Shin | F37: MedSurg | G37: Sales | H37: dana.shin@stryker.com | J37: {=IFERROR(INDEX(All_User!D:D,MATCH(H37,All_User!D:D,0)),"없음")} -> dana.shin@stryker.com | L37: {=IFERROR(INDEX(sales!G:G,MATCH(H37,sales!C:C,0)),"없음")} -> SL-C486FW
A38: 38 | B38: 삼성복합기 | D38: SL-C486FW | E38: Simon Sin | F38: MedSurg | G38: Sales | H38: Simon.sin@stryker.com | J38: {=IFERROR(INDEX(All_User!D:D,MATCH(H38,All_User!D:D,0)),"없음")} -> Simon.sin@stryker.com | L38: {=IFERROR(INDEX(sales!G:G,MATCH(H38,sales!C:C,0)),"없음")} -> SL-C486FW
A39: 39 | B39: C486 | D39: SL-C563W | E39: Hyoseon Park | F39: Medsurg | G39: Sales | H39: hyoseon.park@stryker.com | J39: {=IFERROR(INDEX(All_User!D:D,MATCH(H39,All_User!D:D,0)),"없음")} -> hyoseon.park@stryker.com | L39: {=IFERROR(INDEX(sales!G:G,MATCH(H39,sales!C:C,0)),"없음")} -> SL-C563W
A40: 41 | B40: SL-C563W | C40: 45108 | D40: SL-C563W | E40: Daniel Park | F40: MedSurg | G40: Sales | H40: daniel.park@stryker.com | J40: {=IFERROR(INDEX(All_User!D:D,MATCH(H40,All_User!D:D,0)),"없음")} -> daniel.park@stryker.com | L40: {=IFERROR(INDEX(sales!G:G,MATCH(H40,sales!C:C,0)),"없음")} -> SL-C563W
A41: 42 | B41: SL-C563W | C41: 45627 | D41: SL-C563W | E41: Brad Choi | F41: MedSurg | G41: Sales | H41: brad.choi@stryker.com | J41: {=IFERROR(INDEX(All_User!D:D,MATCH(H41,All_User!D:D,0)),"없음")} -> brad.choi@stryker.com | L41: {=IFERROR(INDEX(sales!G:G,MATCH(H41,sales!C:C,0)),"없음")} -> SL-C563W
A42: 43 | B42: SL-C563W | C42: 45383 | D42: SL-C565W | E42: Chan Jeon | F42: MedSurg | G42: Sales | H42: chan.jeon@stryker.com | J42: {=IFERROR(INDEX(All_User!D:D,MATCH(H42,All_User!D:D,0)),"없음")} -> chan.jeon@stryker.com | L42: {=IFERROR(INDEX(sales!G:G,MATCH(H42,sales!C:C,0)),"없음")} -> SL-C565W
A43: 44 | C43: #ERROR! | D43: 확인중 | E43: Sue Kim | F43: NV | G43: Sales | H43: Sue.Kim@stryker.com | J43: {=IFERROR(INDEX(All_User!D:D,MATCH(H43,All_User!D:D,0)),"없음")} -> Sue.Kim@stryker.com | L43: {=IFERROR(INDEX(sales!G:G,MATCH(H43,sales!C:C,0)),"없음")} -> 확인중
A44: 45 | B44: 삼성복합기 | D44: 확인중 | E44: Jackson Kim | F44: NV | G44: Sales | H44: jackson.kim@stryker.com | J44: {=IFERROR(INDEX(All_User!D:D,MATCH(H44,All_User!D:D,0)),"없음")} -> jackson.kim@stryker.com | L44: {=IFERROR(INDEX(sales!G:G,MATCH(H44,sales!C:C,0)),"없음")} -> 확인중
A45: 46 | B45: 삼성복합기 | D45: SL-C486FW | E45: Henry Kim | F45: NV | G45: Sales | H45: henry.kim1@stryker.com | J45: {=IFERROR(INDEX(All_User!D:D,MATCH(H45,All_User!D:D,0)),"없음")} -> henry.kim1@stryker.com | L45: {=IFERROR(INDEX(sales!G:G,MATCH(H45,sales!C:C,0)),"없음")} -> SL-C486FW
A46: 47 | B46: 삼성복합기 | D46: 반납 | E46: Tyler Park | F46: NV | G46: Sales | H46: tyler.park@stryker.com | J46: {=IFERROR(INDEX(All_User!D:D,MATCH(H46,All_User!D:D,0)),"없음")} -> tyler.park@stryker.com | L46: {=IFERROR(INDEX(sales!G:G,MATCH(H46,sales!C:C,0)),"없음")} -> 반납
A47: 48 | B47: 삼성복합기 | D47: 2차 조사 정보 없음 | E47: Yejin Heo | F47: NV | G47: Sales | H47: yejin.heo@stryker.com | J47: {=IFERROR(INDEX(All_User!D:D,MATCH(H47,All_User!D:D,0)),"없음")} -> yejin.heo@stryker.com | L47: {=IFERROR(INDEX(sales!G:G,MATCH(H47,sales!C:C,0)),"없음")} -> 2차 조사 정보 없음
A48: 49 | B48: SL-C563W | C48: 45597 | D48: SL-C563W | E48: Gregory Seo | F48: NV | G48: Sales | H48: Gregory.Seo@stryker.com | J48: {=IFERROR(INDEX(All_User!D:D,MATCH(H48,All_User!D:D,0)),"없음")} -> Gregory.Seo@stryker.com | L48: {=IFERROR(INDEX(sales!G:G,MATCH(H48,sales!C:C,0)),"없음")} -> SL-C563W
A49: 50 | B49: SL-C563W | C49: 45597 | D49: SL-C563W | E49: DJ Ahn | F49: NV | G49: Sales | H49: dj.ahn@stryker.com | J49: {=IFERROR(INDEX(All_User!D:D,MATCH(H49,All_User!D:D,0)),"없음")} -> dj.ahn@stryker.com | L49: {=IFERROR(INDEX(sales!G:G,MATCH(H49,sales!C:C,0)),"없음")} -> SL-C563W
A50: 51 | B50: 삼성복합기 | D50: 2차 조사 정보 없음 | E50: Young Hwang | F50: NV | G50: Sales | H50: young.hwang@stryker.com | J50: {=IFERROR(INDEX(All_User!D:D,MATCH(H50,All_User!D:D,0)),"없음")} -> young.hwang@stryker.com | L50: {=IFERROR(INDEX(sales!G:G,MATCH(H50,sales!C:C,0)),"없음")} -> 2차 조사 정보 없음
A51: 52 | B51: SL-C565FW | C51: 24년 2월 22일 4색 토너 | D51: SL-C565FW | E51: Kyu Choi | F51: NV | G51: Sales | H51: kyu.choi@stryker.com | J51: {=IFERROR(INDEX(All_User!D:D,MATCH(H51,All_User!D:D,0)),"없음")} -> kyu.choi@stryker.com | L51: {=IFERROR(INDEX(sales!G:G,MATCH(H51,sales!C:C,0)),"없음")} -> SL-C565FW
A52: 53 | C52: 24년 8월 지급 | D52: SL-C486FW | E52: Lucas Jeon | F52: NV | G52: Sales | H52: lucas.jeon@stryker.com | J52: {=IFERROR(INDEX(All_User!D:D,MATCH(H52,All_User!D:D,0)),"없음")} -> lucas.jeon@stryker.com | L52: {=IFERROR(INDEX(sales!G:G,MATCH(H52,sales!C:C,0)),"없음")} -> SL-C486FW
A53: 54 | B53: 삼성복합기 | D53: 확인중 | E53: Junghoon Seo | F53: Commercial Excellence | G53: CR | H53: junghoon.seo@stryker.com | J53: {=IFERROR(INDEX(All_User!D:D,MATCH(H53,All_User!D:D,0)),"없음")} -> junghoon.seo@stryker.com | L53: {=IFERROR(INDEX(sales!G:G,MATCH(H53,sales!C:C,0)),"없음")} -> 확인중
A54: 55 | B54: 삼성복합기 | D54: 2차 조사 정보 없음 | E54: Michelle Park | F54: Medical | G54: Medical | H54: michelle.park@stryker.com | J54: {=IFERROR(INDEX(All_User!D:D,MATCH(H54,All_User!D:D,0)),"없음")} -> michelle.park@stryker.com | L54: {=IFERROR(INDEX(sales!G:G,MATCH(H54,sales!C:C,0)),"없음")} -> 2차 조사 정보 없음
A55: 56 | B55: 삼성복합기 | C55: 23년 8월 4색 토너 | D55: SL-C563W | E55: Huey Sim | F55: 기술부 | G55: TS | H55: Huey.Sim@stryker.com | J55: {=IFERROR(INDEX(All_User!D:D,MATCH(H55,All_User!D:D,0)),"없음")} -> Huey.Sim@stryker.com | L55: {=IFERROR(INDEX(sales!G:G,MATCH(H55,sales!C:C,0)),"없음")} -> SL-C563W
A56: 57 | B56: 삼성복합기 | C56: 45292 | D56: SL-C563W | E56: Daniel Lee | F56: 기술부 | G56: TS | H56: daniel.lee1@stryker.com | J56: {=IFERROR(INDEX(All_User!D:D,MATCH(H56,All_User!D:D,0)),"없음")} -> daniel.lee1@stryker.com | L56: {=IFERROR(INDEX(sales!G:G,MATCH(H56,sales!C:C,0)),"없음")} -> SL-C563W
A57: 58 | B57: 삼성복합기 | D57: 확인중 | E57: Oscar Hwang | F57: 기술부 | G57: TS | H57: oscar.hwang@stryker.com | J57: {=IFERROR(INDEX(All_User!D:D,MATCH(H57,All_User!D:D,0)),"없음")} -> oscar.hwang@stryker.com | L57: {=IFERROR(INDEX(sales!G:G,MATCH(H57,sales!C:C,0)),"없음")} -> 확인중
A58: 59 | B58: 삼성복합기 | C58: 45352 | D58: SL-C563W | E58: David Lee | F58: 기술부 | G58: TS | H58: david.lee4@stryker.com | J58: {=IFERROR(INDEX(All_User!D:D,MATCH(H58,All_User!D:D,0)),"없음")} -> david.lee4@stryker.com | L58: {=IFERROR(INDEX(sales!G:G,MATCH(H58,sales!C:C,0)),"없음")} -> SL-C563W
A59: 60 | B59: SL-C486FW | D59: SL-C563W | E59: Song Rosey | F59: Mako | G59: Sales | H59: Rosey.song@stryker.com | J59: {=IFERROR(INDEX(All_User!D:D,MATCH(H59,All_User!D:D,0)),"없음")} -> rosey.song@stryker.com | L59: {=IFERROR(INDEX(sales!G:G,MATCH(H59,sales!C:C,0)),"없음")} -> SL-C563W
A60: 61 | B60: SL-C563W | D60: SL-C563W | E60: Cha Bruce | F60: Mako | G60: Sales | H60: Bruce.Cha@stryker.com | J60: {=IFERROR(INDEX(All_User!D:D,MATCH(H60,All_User!D:D,0)),"없음")} -> Bruce.Cha@stryker.com | L60: {=IFERROR(INDEX(sales!G:G,MATCH(H60,sales!C:C,0)),"없음")} -> SL-C563W
A61: 62 | B61: SL-C563W | D61: SL-C563W | E61: Kim Neal | F61: Mako | G61: Sales | H61: neal.kim@stryker.com | J61: {=IFERROR(INDEX(All_User!D:D,MATCH(H61,All_User!D:D,0)),"없음")} -> neal.kim@stryker.com | L61: {=IFERROR(INDEX(sales!G:G,MATCH(H61,sales!C:C,0)),"없음")} -> SL-C563W
A62: 63 | B62: SL-C486FW | C62: 45839 | D62: SL-C486FW | E62: TS | F62: 기술부 | G62: TS | H62: TS 창고 | J62: {=IFERROR(INDEX(All_User!D:D,MATCH(H62,All_User!D:D,0)),"없음")} -> 없음 | L62: {=IFERROR(INDEX(sales!G:G,MATCH(H62,sales!C:C,0)),"없음")} -> 없음
A63: 64 | C63: 45870 | D63: SL-C563W | E63: TS | F63: 기술부 | G63: TS | H63: TS 창고 | J63: {=IFERROR(INDEX(All_User!D:D,MATCH(H63,All_User!D:D,0)),"없음")} -> 없음 | L63: {=IFERROR(INDEX(sales!G:G,MATCH(H63,sales!C:C,0)),"없음")} -> 없음
A64: 65 | B64: SL-C486FW | D64: 모델명 확인요망 | G64: Stock | H64: 정상작동 | J64: {=IFERROR(INDEX(All_User!D:D,MATCH(H64,All_User!D:D,0)),"없음")} -> 없음 | L64: {=IFERROR(INDEX(sales!G:G,MATCH(H64,sales!C:C,0)),"없음")} -> 없음
A65: 66 | B65: SL-C563W | D65: 모델명 확인요망 | G65: Stock | H65: 정상작동 | J65: {=IFERROR(INDEX(All_User!D:D,MATCH(H65,All_User!D:D,0)),"없음")} -> 없음 | L65: {=IFERROR(INDEX(sales!G:G,MATCH(H65,sales!C:C,0)),"없음")} -> 없음
A66: 67 | B66: SL-C563W | D66: 모델명 확인요망 | G66: Stock | H66: 롤러 잔 복사 | J66: {=IFERROR(INDEX(All_User!D:D,MATCH(H66,All_User!D:D,0)),"없음")} -> 없음 | L66: {=IFERROR(INDEX(sales!G:G,MATCH(H66,sales!C:C,0)),"없음")} -> 없음
A67: 63 | B67: 삼성복합기 | D67: SL-C486FW | F67: 기술부 | H67: 기술부1 | J67: {=IFERROR(INDEX(All_User!D:D,MATCH(H67,All_User!D:D,0)),"없음")} -> 없음 | L67: {=IFERROR(INDEX(sales!G:G,MATCH(H67,sales!C:C,0)),"없음")} -> SL-C486FW
A68: 64 | B68: 삼성복합기 | D68: SL-C563W | F68: 기술부 | H68: 기술부2 | J68: {=IFERROR(INDEX(All_User!D:D,MATCH(H68,All_User!D:D,0)),"없음")} -> 없음 | L68: {=IFERROR(INDEX(sales!G:G,MATCH(H68,sales!C:C,0)),"없음")} -> SL-C563W
A69: 65 | B69: 삼성복합기 | D69: SL-C483FW | F69: 기술부 | H69: 기술부3 | J69: {=IFERROR(INDEX(All_User!D:D,MATCH(H69,All_User!D:D,0)),"없음")} -> 없음 | L69: {=IFERROR(INDEX(sales!G:G,MATCH(H69,sales!C:C,0)),"없음")} -> SL-C483FW
A70: 66 | B70: 삼성복합기 | D70: SL-C563W | E70: Ian Hwang | F70: NV | G70: Sales | H70: ian.hwang@stryker.com | J70: {=IFERROR(INDEX(All_User!D:D,MATCH(H70,All_User!D:D,0)),"없음")} -> ian.hwang@stryker.com | L70: {=IFERROR(INDEX(sales!G:G,MATCH(H70,sales!C:C,0)),"없음")} -> SL-C563W

Sheet Monitor
A1: Model | B1: Date | C1: User | D1: email | E1: Additional Information
A2: LCD 모니터 | C2: Alicia Bang | D2: alicia.bang@stryker.com
A3: LCD 모니터 | C3: Alice Han | D3: alice.han@stryker.com
A4: LCD 모니터 | C4: Terry Kim | D4: terry.kim@stryker.com
A5: LCD 모니터 | C5: Jiyoung Park | D5: jy.park@stryker.com
A6: LCD 모니터 | C6: Jeff Lee | D6: Jeff.Lee@stryker.com
A7: LCD 모니터 | C7: James Park | D7: james.park@stryker.com
A8: LCD 모니터 | C8: STOCK | E8: HP 모니터
A9: LCD 모니터 | C9: Bella Yoon | D9: bella.yoon@stryker.com
A10: LCD 모니터 | C10: Chloe Kang | D10: chloe.kang@stryker.com
A11: LCD 모니터 | C11: Leslie Kim | D11: Leslie.kim@stryker.com
A12: LCD 모니터 | C12: STOCK
A13: LCD 모니터 | C13: Shinhye Park | E13: 퇴사
A14: LCD 모니터 | C14: Demian Lee | D14: demian.lee@stryker.com
A15: LCD 모니터 | C15: Jenny Jung | D15: jenny.jung@stryker.com
A16: LCD 모니터 | C16: Seran Jung | E16: 퇴사
A17: LCD 모니터 | C17: Chloe Lee | D17: chloe.lee@stryker.com
A18: LCD 모니터 | C18: Cozy Huh | D18: cozy.huh@stryker.com
A19: LCD 모니터 | C19: Freddy Park | D19: freddy.park@stryker.com
A20: LCD 모니터 | C20: Julie Son | D20: julie.son@stryker.com | E20: 퇴사
A21: LCD 모니터 | C21: Ju Lee | E21: 퇴사
A22: LCD 모니터 | C22: Terry Kim | D22: terry.kim@stryker.com
A23: LCD 모니터 | C23: Minsu Yi | D23: minsu.yi@stryker.com
A24: 반납완료 | C24: Clare Yang | D24: clare.yang@stryker.com | E24: 반납완료
A25: LCD 모니터 | B25: 45689 | C25: TS 장지동
A26: LCD 모니터 | B26: 45323 | C26: James Kang | D26: James.Kang@stryker.com
A27: LCD 모니터 | B27: 45352 | C27: Jaewook Chung | D27: jae.chung@stryker.com
A28: LCD 모니터 | B28: 45413 | C28: Heesun Cho | D28: heesun.cho@stryker.com
A29: LCD 모니터 | B29: 45474 | C29: TS 장지동
A30: 반납완료 | B30: 45474 | C30: Soyeon Park | D30: soyeon.park@stryker.com | E30: 반납완료
A31: 반납완료 | B31: 45517 | C31: Lucy Han | D31: lucy.han@stryker.com | E31: 반납완료
A32: LCD 모니터 | B32: 45635 | C32: Sungyi Jeon
A33: LCD 모니터 | B33: 45717 | C33: jay ji | D33: jay.ji@stryker.com
A34: LCD 모니터 | B34: 45754 | C34: Kim Lina | D34: lina.kim@stryker.com
A35: LCD 모니터 | B35: 45805 | C35: won imsun | D35: imsun.won@stryker.com
A36: LCD 모니터 | B36: 45889 | C36: Hwang Stella | D36: stella.hwang@stryker.com
A37: E2422H | B37: 45943 | C37: 용마 | D37: recon.ym@stryker.com | E37: 보유 모니터 지급 | F37: E2422H
A38: SE2425H | B38: 45945 | C38: TS 장지동 | F38: SE2425H
A39: SE2425H | B39: 45945 | C39: TS 장지동 | F39: SE2425H
A40: SE2425H | B40: 45945 | C40: TS 장지동 | F40: SE2425H
A41: SE2425H | B41: 45952 | C41: sally choi | D41: sally.choi@stryker.com | F41: SE2425H
A42: SE2425H | B42: 45953 | C42: 용마 | D42: recon.ym@stryker.com | E42: 기존 모니터 파손으로 인한 교체 | F42: SE2425H
A43: E2422H | B43: 45973 | C43: andy kim | D43: Andy.kim@stryker.com | F43: E2422H
A44: LCD 모니터 | B44: 45987 | C44: sujin park | D44: sujin.park@stryker.com

Sheet LEASE_PC_SETTING
A1: NO | B1: Model | C1: 종류 | D1: SNOW Tag | E1: S/N | F1: lease Date | G1: dept | H1: User | I1: EMAIL | J1: 셋팅완료 | K1: 수령확인 | L1: 기존노트북 반납 | M1: PW | N1: HWP사용 | O1: account | P1: 공유폴더 | Q1: 추가사항 | R1: 작업자
A2: 1 | B2: HP Elitebook 640 G11 | H2: Gregory Seo | I2: Gregory.Seo@stryker.com | J2: ---
A3: 2 | B3: HP Elitebook 640 G11 | C3: Laptop | D3: 465320 | E3: 5CD5179KHY | F3: 04/22/25 | G3: MAKO | H3: Willy Chang | I3: Willy.Chang@stryker.com | J3: O | K3: O | L3: O | M3: Poiu1234 | N3: YES | O3: kkhjang
A4: 3 | B4: HP Elitebook 640 G11 | C4: Laptop | D4: 465332 | E4: 5CD5179KJ3 | F4: 04/22/25 | G4: MAKO | H4: David Yang | I4: David.Yang@stryker.com | J4: O | K4: O | L4: O | M4: Asdf4321 | N4: YES | O4: kkshyang
A5: 5 | B5: HP Elitebook 640 G11 | C5: Laptop | E5: 5CD5179KH6 | F5: 04/22/25 | G5: Knee | H5: Jiho Yoo | I5: jiho.yoo@stryker.com | J5: O | K5: O | L5: O | M5: Asdf1234## | N5: NO | O5: JYoo1
A6: 6 | B6: HP Elitebook 640 G11 | C6: Laptop | D6: 465312 | E6: 5CD5179KHH | F6: 04/22/25 | G6: Knee | H6: Louis Kang | I6: louis.kang@stryker.com | J6: O | K6: O | L6: O | M6: Qwer1111 | N6: YES | O6: kkwykang
A7: 7 | B7: HP Elitebook 640 G11 | C7: Laptop | E7: 5CD5179KHZ | F7: 04/22/25 | G7: NV | H7: Young Hwang | I7: young.hwang@stryker.com | J7: O | K7: O | L7: O | M7: Dnwk135135!!!! | N7: YES | O7: yhwang
A8: 8 | H8: Jin Park | I8: jin.park@stryker.com
A9: 9 | B9: HP Elitebook 640 G11 | C9: Laptop | E9: 5CD5179KGZ | F9: 04/22/25 | G9: Knee | H9: Jason Han | I9: jason.han@stryker.com | J9: O | K9: O | L9: O | M9: Kuntaman4$ | N9: YES | O9: jhan
A10: 10 | B10: HP Elitebook 640 G11 | C10: Laptop | E10: 5CD5179KH1 | F10: 04/22/25 | G10: Compliance | H10: Soyoun Kim | I10: soyoun.kim@stryker.com | J10: O | K10: O | L10: O | M10: Faith0327 | N10: YES | O10: skim10
A11: 12 | B11: HP Elitebook 640 G11 | C11: Laptop | E11: 5CD5179KHG | F11: 04/22/25 | G11: Instrument | H11: Martin Cho | I11: martin.cho@stryker.com | J11: O | K11: O | L11: O | M11: WHAUDTN199!! | N11: YES | O11: mcho1
A12: 13 | B12: HP Elitebook 640 G11 | C12: Laptop | D12: 465302 | E12: 5CD5179KHC | F12: 04/22/25 | H12: Dana Shin | I12: dana.shin@stryker.com | J12: O | K12: O | L12: O | M12: Sumin126!! | N12: YES | O12: dshin1
A13: 14 | B13: HP Elitebook 640 G11 | C13: Laptop | D13: 465329 | E13: 5CD5179KJC | F13: 04/22/25 | H13: Mi Na Song | I13: mina.song@stryker.com | J13: ---
A14: 15 | B14: HP Elitebook 640 G11 | C14: Laptop | D14: 465299 | E14: 5CD5179KH0 | F14: 04/22/25 | G14: Compliance | H14: Jaehee Seo | I14: jaehee.seo@stryker.com | J14: O | K14: O | M14: Jhse2222@ | N14: YES | O14: jseo2
A15: 16 | B15: HP Elitebook 640 G11 | C15: Laptop | D15: 465330 | E15: 5CD5179KJ2 | F15: 04/22/25 | G15: ICM | H15: James Kang | I15: James.Kang@stryker.com | J15: O | K15: O | L15: O | M15: Kelly2324$ | N15: NO | O15: kfjykang
A16: 17 | B16: HP Elitebook 640 G11 | C16: Laptop | E16: 5CD5179KH2 | F16: 04/22/25 | G16: MedSurg | H16: Henry Lee | I16: henry.lee@stryker.com | J16: O | K16: O | L16: O | M16: nEEEEEEEa*521478 | N16: YES | O16: hlee6
A17: 18 | B17: HP Elitebook 640 G11 | C17: Laptop | D17: 465315 | E17: 5CD5179KJ6 | F17: 04/22/25 | G17: TS | H17: Andrew Ahn | I17: andrew.ahn@stryker.com | J17: O | K17: O | L17: O | M17: Asdf1234 | N17: NO
A18: 19 | B18: HP Elitebook 640 G11 | C18: Laptop | D18: 465304 | E18: 5CD5179KHM | F18: 04/22/25 | G18: HR | H18: Chloe Kang | I18: chloe.kang@stryker.com | J18: O | K18: O | L18: O | M18: Qwer1234 | N18: YES
A19: 20 | B19: HP Elitebook 640 G11 | C19: Laptop | D19: 465296 | E19: 5CD5179KH8 | F19: 04/22/25 | G19: Planning | H19: YJ Seo | I19: yj.seo@stryker.com | J19: O | K19: O | L19: O | M19: Stryker2# | N19: YES | O19: koyjseo
A20: 21 | B20: HP Elitebook 640 G11 | C20: Laptop | D20: 465295 | E20: 5CD5179KH7 | F20: 04/22/25 | G20: TS | H20: Sim Huey | I20: huey.sim@stryker.com | J20: O | K20: O | L20: O | M20: Qwer1234 | N20: YES | O20: kkjhsim
A21: 22 | B21: HP Elitebook 640 G11 | C21: Laptop | D21: 465310 | E21: 5CD5179KHQ | F21: 04/22/25 | G21: Shoulder | H21: James Kim | I21: james.kim@stryker.com | J21: O | K21: O | L21: O | M21: !Shoulder1 | N21: YES | O21: jkim22
A22: 23 | B22: HP Elitebook 640 G11 | C22: Laptop | D22: 465310 | E22: 5CD5179KHQ | F22: 04/22/25 | G22: NV | H22: Choi, Kyu | I22: kyu.choi@stryker.com | J22: O | K22: O | L22: O | M22: Lindermen7& | N22: YES | O22: kchoi2 | Q22: 주소 : 서울시 강남구 언주로 110 10동 102호 성함 : 최규범 연락처 : 010-8910-2798
A23: 24 | B23: HP Elitebook 640 G10 | C23: Laptop | E23: 5CD4232BF7 | F23: 06/20/24 | G23: Mako | H23: Kim Yeonjoo | I23: yeonjoo.kim@stryker.com | J23: O | K23: O | L23: O | M23: Stryker9 | N23: YES | O23: ykim3
A24: 25 | B24: HP Elitebook 640 G10 | C24: Laptop | E24: 5CD3469HDB | F24: 40931 | G24: Finance | H24: Mihee han | I24: mihee.han@stryker.com | J24: O | K24: O | L24: O | M24: Icandoit202509!! | N24: YES | O24: mhan1
A25: 26 | B25: HP Elitebook 640 G11 | C25: Laptop | E25: 5CD442C07F | H25: minki kim | I25: minki.kim@stryker.com | J25: O | K25: O
A26: 27 | B26: HP EB8 G1i 14 | C26: Laptop | E26: 5CG53403D0 | G26: RA&QA | I26: alicia.bang@stryker.com | J26: O | K26: O | M26: Happywombat93! | N26: YES | O26: kradmin
A28: 대기 | B28: ZBOOK | C28: Laptop | E28: 5CD5428PHM | G28: TS | H28: ts.korea | I28: ts.korea@stryker.com | M28: Asdf1234 | O28: kts

Sheet 신규입사자
A1: 월 | B1: 날짜 | C1: 이름 | D1: NAME | E1: email | F1: FTE/Cont. | G1: ROLE | H1: BU | I1: 노트북 | J1: 아이패드 | K1: 모니터 | L1: 복합기 | M1: Teams | N1: 추가사항
A2: 0 | B2: 0 | D2: kale.lee | E2: kale.lee@stryker.com | F2: 샘플 삭제 금지 | I2: 5CD3469HCZ | J2: J1XWPW66YY | K2: 없음 | L2: 없음 | M2: #ERROR!
A3: 5 | B3: 2 | C3: 강지희 | D3: jihee.kang | E3: jihee.kang@stryker.com | F3: 5개월 계약 | H3: Mako | I3: 5CD4145N3J | J3: 없음 | K3: 없음 | L3: 없음 | M3: 없음
A4: 5 | B4: 7 | C4: 이현우 | D4: bruce.lee | E4: bruce.lee@stryker.com | F4: FTE | H4: Planning | I4: 5CD442C077 | J4: 없음 | K4: 없음 | L4: 없음 | M4: #ERROR!
A5: 5 | B5: 19 | C5: 김푸른강 | D5: neal.kim | E5: neal.kim@stryker.com | F5: FTE | G5: Sales | H5: Mako | I5: 5CD5062YDN | J5: FHTK4GJCF9 | K5: 없음 | L5: 없음 | M5: 없음
A6: 5 | B6: 26 | C6: 허윤재 | D6: lucas.heo | E6: lucas.heo@stryker.com | F6: FTE | G6: MPS | H6: Mako | I6: 5CD5062YDF | J6: H2JWWY6V5C | K6: 없음 | L6: 없음 | M6: 없음
A7: 6 | B7: 2 | C7: 황지영 | D7: Stella Hwang | E7: stella.hwang@stryker.com | F7: 1년 계약(Contingent) | G7: Sales | H7: Medsurg | I7: 5CD5062YF9 | J7: 없음 | K7: LCD 모니터 | L7: 없음 | M7: 없음
A8: 6 | B8: 30 | C8: 정교원 | D8: Gyowon Jeong | E8: gyowon.jeong@stryker.com | F8: 6개월 계약 | H8: Planning | I8: 5CD5062YF2 | J8: 없음 | K8: 없음 | L8: 없음 | M8: 없음
A9: 7 | B9: 7 | C9: 김보민 | D9: kmultiuser | E9: kmultiuser@stryker.com | F9: 1개월 계약 | H9: Implants | I9: 반납 | J9: 없음 | K9: 없음 | L9: 없음 | M9: 없음
A10: 7 | B10: 28 | C10: 김다은 | D10: Dawn Kim | E10: dawn.kim@stryker.com | F10: FTE | H10: Medsurg | I10: 5CD5179KJ4 | J10: 없음 | K10: 없음 | L10: 없음 | M10: #ERROR!
A11: 8 | B11: 4 | C11: 박효현 | D11: Bryan Park | E11: bryan.park@stryker.com | F11: FTE | G11: MPS | H11: Mako | I11: 5CD5179KJ9 | J11: WR34FVRW4C | K11: 없음 | L11: 없음 | M11: 없음
A12: 8 | B12: 11 | C12: 김보민 | D12: Bomin Kim | E12: Bomin.kim@stryker.com | F12: FTE | H12: Medsurg | I12: 5CD5179KJ7 | J12: 없음 | K12: 없음 | L12: 없음 | M12: #ERROR!
A13: 9 | B13: 1 | C13: 최수빈 | D13: Sally Choi | E13: sally.choi@stryker.com | F13: FTE | H13: ICM | I13: 5CD5179KHN | J13: 없음 | K13: 없음 | L13: 없음 | M13: #ERROR! | N13: schoi2
A14: 9 | B14: 1 | C14: 황인재 | D14: Ian hwang | E14: ian.hwang@stryker.com | F14: 인턴 | H14: NV | I14: 5CD3469HDL | J14: 없음 | K14: 없음 | L14: 없음 | M14: 없음 | N14: ihwang
A15: 9 | B15: 1 | C15: 정예진 | D15: Lia Jung | E15: lia.jung@stryker.com | F15: 인턴 | H15: Shoulder | I15: 5CD4305D8D | J15: 없음 | K15: 없음 | L15: 없음 | M15: 없음 | N15: ljung2
A16: 9 | B16: 1 | C16: 박성희 | D16: Sazy Park | E16: sazy.park@stryker.com | F16: 인턴 | H16: RAQA | I16: 5CD4305D8J | J16: 없음 | K16: 없음 | L16: 없음 | M16: 없음 | N16: spark10
A17: 10 | B17: 13 | C17: 김근호 | D17: shawn.kim | E17: shawn.kim@stryker.com | F17: FTE | G17: MPS | H17: MAKO | I17: 5CD4305D8J | J17: 없음
A18: 10 | B18: 26 | C18: 황인재 | D18: Ian hwang | E18: ian.hwang@stryker.com | F18: FTE | G18: Sales | H18: NV | I18: 5CD3469HDL | J18: CK7JHKH443 | K18: 없음 | L18: 없음 | M18: 없음 | N18: ihwang
A19: 11 | B19: 3 | C19: 김건우 | D19: Andy Kim | E19: andy.kim@stryker.com | F19: 1년 계약 | H19: RAQA | I19: 5CD5062YDV
A20: 11 | B20: 10 | C20: 조홍준 | D20: Antonio Cho | E20: antonio.cho@stryker.com | F20: 1년 계약 | H20: MedSurg
A21: 11 | B21: 26 | C21: 정윤 | D21: Yoon Chung | E21: yoon.chung@stryker.com | F21: 1년 계약 | H21: Knee

Sheet rEfRESH
B1: name | C1: email | D1: model | H1: ROle
A2: 1 | B2: Gregory Seo | C2: Gregory.Seo@stryker.com | D2: HP Elitebook 840 G8 | E2: 없음 | F2: {=IFERROR(INDEX(All_User!R:R,MATCH(C2,All_User!D:D,0)),"퇴사자아님")} -> 0 | H2: NV
A3: 2 | B3: Jin Park | C3: jin.park@stryker.com | D3: HP Elitebook 840 G8 | E3: 없음 | F3: {=IFERROR(INDEX(All_User!R:R,MATCH(C3,All_User!D:D,0)),"퇴사자아님")} -> 0 | H3: Medsurg
A4: 3 | B4: Mi Na Song | C4: mina.song@stryker.com | D4: HP Elitebook 840 G8 | E4: 없음 | F4: {=IFERROR(INDEX(All_User!R:R,MATCH(C4,All_User!D:D,0)),"퇴사자아님")} -> 0 | H4: NV
A5: 4 | B5: Jack Park | C5: jack.park@stryker.com | D5: HP Elitebook 840 G8 | E5: 없음 | F5: {=IFERROR(INDEX(All_User!R:R,MATCH(C5,All_User!D:D,0)),"퇴사자아님")} -> 0 | H5: RAQA
A6: 5 | B6: Jack Eum | C6: jack.eum@stryker.com | D6: HP Elitebook 840 G8 | E6: 없음 | F6: {=IFERROR(INDEX(All_User!R:R,MATCH(C6,All_User!D:D,0)),"퇴사자아님")} -> 0 | H6: Knee
A7: 6 | B7: Ayaan Lee | C7: ayaan.lee@stryker.com | D7: HP Elitebook 640 G9 | E7: 없음 | F7: {=IFERROR(INDEX(All_User!R:R,MATCH(C7,All_User!D:D,0)),"퇴사자아님")} -> 0 | H7: Implants
A8: 7 | B8: Joon Oh | C8: joon.oh@stryker.com | D8: HP Elitebook 640 G9 | E8: 없음 | F8: {=IFERROR(INDEX(All_User!R:R,MATCH(C8,All_User!D:D,0)),"퇴사자아님")} -> 0 | H8: Knee
A9: 8 | B9: Yejin Heo | C9: yejin.heo@stryker.com | D9: HP Elitebook 640 G9 | E9: 없음 | F9: {=IFERROR(INDEX(All_User!R:R,MATCH(C9,All_User!D:D,0)),"퇴사자아님")} -> 0 | H9: NV
A10: 9 | B10: Jaekyeong Lee | C10: jaekyeong.lee@stryker.com | D10: HP Elitebook 640 G9 | E10: 없음 | F10: {=IFERROR(INDEX(All_User!R:R,MATCH(C10,All_User!D:D,0)),"퇴사자아님")} -> 0 | H10: Market Access
A11: 10 | B11: Roy Choi | C11: roy.choi@stryker.com | D11: HP Elitebook 640 G9 | E11: 없음 | F11: {=IFERROR(INDEX(All_User!R:R,MATCH(C11,All_User!D:D,0)),"퇴사자아님")} -> 0 | H11: Mako
A12: 11 | B12: Lucas Jeon | C12: lucas.jeon@stryker.com | D12: HP Elitebook 640 G9 | E12: 없음 | F12: {=IFERROR(INDEX(All_User!R:R,MATCH(C12,All_User!D:D,0)),"퇴사자아님")} -> 0 | H12: NV
A13: 12 | B13: David Kim | C13: david.kim3@stryker.com | D13: HP Elitebook 640 G9 | E13: 없음 | F13: {=IFERROR(INDEX(All_User!R:R,MATCH(C13,All_User!D:D,0)),"퇴사자아님")} -> 0 | H13: Medsurg
... A16: 15 | B16: Chan Jeon | C16: chan.jeon@stryker.com | D16: HP Elitebook 640 G9 | E16: 없음 | F16: {=IFERROR(INDEX(All_User!R:R,MATCH(C16,All_User!D:D,0)),"퇴사자아님")} -> 0 | H16: Medsurg
A17: 16 | B17: Dong Jun Ahn | C17: dj.ahn@stryker.com | D17: 모델명 확인 불가 | E17: 없음 | F17: {=IFERROR(INDEX(All_User!R:R,MATCH(C17,All_User!D:D,0)),"퇴사자아님")} -> 0
A18: 17 | B18: Carl Cha | C18: carl.cha@stryker.com | D18: 모델명 확인 불가 | E18: 없음 | F18: {=IFERROR(INDEX(All_User!R:R,MATCH(C18,All_User!D:D,0)),"퇴사자아님")} -> 0
A19: 18 | B19: Claire Choi | C19: claire.choi@stryker.com | D19: 모델명 확인 불가 | E19: 없음 | F19: {=IFERROR(INDEX(All_User!R:R,MATCH(C19,All_User!D:D,0)),"퇴사자아님")} -> 0
A20: 19 | B20: Cozy Huh | C20: cozy.huh@stryker.com | D20: 모델명 확인 불가 | E20: 없음 | F20: {=IFERROR(INDEX(All_User!R:R,MATCH(C20,All_User!D:D,0)),"퇴사자아님")} -> 0
A21: 20 | B21: Mindo Kim | C21: mindo.kim@stryker.com | D21: 모델명 확인 불가 | E21: 없음 | F21: {=IFERROR(INDEX(All_User!R:R,MATCH(C21,All_User!D:D,0)),"퇴사자아님")} -> 0
A22: 21 | B22: Aspyn Kim | C22: aspyn.kim@stryker.com | D22: 모델명 확인 불가 | E22: 없음 | F22: {=IFERROR(INDEX(All_User!R:R,MATCH(C22,All_User!D:D,0)),"퇴사자아님")} -> 0
A23: 22 | B23: Allen Ku | C23: allen.ku@stryker.com | D23: 모델명 확인 불가 | E23: 없음 | F23: {=IFERROR(INDEX(All_User!R:R,MATCH(C23,All_User!D:D,0)),"퇴사자아님")} -> 0
A24: 23 | B24: Roy Lim | C24: roy.lim@stryker.com | D24: 모델명 확인 불가 | E24: 없음 | F24: {=IFERROR(INDEX(All_User!R:R,MATCH(C24,All_User!D:D,0)),"퇴사자아님")} -> 0
A25: 24 | B25: Jiyoung Park | C25: jy.park@stryker.com | D25: 모델명 확인 불가 | E25: 없음 | F25: {=IFERROR(INDEX(All_User!R:R,MATCH(C25,All_User!D:D,0)),"퇴사자아님")} -> 0
A26: 25 | B26: Peter Park | C26: peter.park@stryker.com | D26: 모델명 확인 불가 | E26: 없음 | F26: {=IFERROR(INDEX(All_User!R:R,MATCH(C26,All_User!D:D,0)),"퇴사자아님")} -> 0
A27: 26 | B27: Daniel Park | C27: daniel.park@stryker.com | D27: 모델명 확인 불가 | E27: 없음 | F27: {=IFERROR(INDEX(All_User!R:R,MATCH(C27,All_User!D:D,0)),"퇴사자아님")} -> 0
A28: 27 | B28: Chris Shin | C28: chris.shin@stryker.com | D28: 모델명 확인 불가 | E28: 없음 | F28: {=IFERROR(INDEX(All_User!R:R,MATCH(C28,All_User!D:D,0)),"퇴사자아님")} -> 0
... A30: 29 | B30: Sarah Youn | C30: sarah.youn@stryker.com | D30: 모델명 확인 불가 | E30: 없음 | F30: {=IFERROR(INDEX(All_User!R:R,MATCH(C30,All_User!D:D,0)),"퇴사자아님")} -> 0
A31: 30 | B31: Caps PC | C31: IT ROOM | D31: HP EliteDesk G6 Mini | E31: {=IFERROR(INDEX(All_User!H:H,MATCH(C31,All_User!D:D,0)),"all_user에 없음")} -> all_user에 없음 | H31: IT
B33: Owen Yang | C33: {=IFERROR(INDEX(All_User!D:D,MATCH(B33,All_User!B:B,0)),"없음")} -> owen.yang@stryker.com | D33: {=IFERROR(INDEX(All_User!H:H,MATCH(C33,All_User!D:D,0)),"없음")} -> 5CD442C07J
B34: Simon Sin | C34: {=IFERROR(INDEX(All_User!D:D,MATCH(B34,All_User!B:B,0)),"없음")} -> Simon.sin@stryker.com | D34: {=IFERROR(INDEX(All_User!H:H,MATCH(C34,All_User!D:D,0)),"없음")} -> 5CD5179KH9
B35: Jackson Kim | C35: {=IFERROR(INDEX(All_User!D:D,MATCH(B35,All_User!B:B,0)),"없음")} -> jackson.kim@stryker.com | D35: {=IFERROR(INDEX(All_User!H:H,MATCH(C35,All_User!D:D,0)),"없음")} -> 5CD5179KJ1
B36: Genie Kim | C36: {=IFERROR(INDEX(All_User!D:D,MATCH(B36,All_User!B:B,0)),"없음")} -> genie.kim@stryker.com | D36: {=IFERROR(INDEX(All_User!H:H,MATCH(C36,All_User!D:D,0)),"없음")} -> 5CD5179KHX
B37: Willy Chang | C37: {=IFERROR(INDEX(All_User!D:D,MATCH(B37,All_User!B:B,0)),"없음")} -> Willy.Chang@stryker.com | D37: {=IFERROR(INDEX(All_User!H:H,MATCH(C37,All_User!D:D,0)),"없음")} -> 5CD5179KHY
B38: Alice Han | C38: {=IFERROR(INDEX(All_User!D:D,MATCH(B38,All_User!B:B,0)),"없음")} -> alice.han@stryker.com | D38: {=IFERROR(INDEX(All_User!H:H,MATCH(C38,All_User!D:D,0)),"없음")} -> 5CD5179KHR
B39: David Yang | C39: {=IFERROR(INDEX(All_User!D:D,MATCH(B39,All_User!B:B,0)),"없음")} -> David.Yang@stryker.com | D39: {=IFERROR(INDEX(All_User!H:H,MATCH(C39,All_User!D:D,0)),"없음")} -> 5CD5179KJ3
B40: Jason Kim | C40: {=IFERROR(INDEX(All_User!D:D,MATCH(B40,All_User!B:B,0)),"없음")} -> jason.kim1@stryker.com | D40: {=IFERROR(INDEX(All_User!H:H,MATCH(C40,All_User!D:D,0)),"없음")} -> 5CD5062YDG
B41: Tyler Park | C41: {=IFERROR(INDEX(All_User!D:D,MATCH(B41,All_User!B:B,0)),"없음")} -> tyler.park@stryker.com | D41: {=IFERROR(INDEX(All_User!H:H,MATCH(C41,All_User!D:D,0)),"없음")} -> 5CD5179KHL
B42: Jiho Yoo | C42: {=IFERROR(INDEX(All_User!D:D,MATCH(B42,All_User!B:B,0)),"없음")} -> jiho.yoo@stryker.com | D42: {=IFERROR(INDEX(All_User!H:H,MATCH(C42,All_User!D:D,0)),"없음")} -> 5CD5179KH6
B43: Hailey Kim | C43: {=IFERROR(INDEX(All_User!D:D,MATCH(B43,All_User!B:B,0)),"없음")} -> hailey.kim@stryker.com | D43: {=IFERROR(INDEX(All_User!H:H,MATCH(C43,All_User!D:D,0)),"없음")} -> 5CD442C07B
B44: Jinny Park | C44: {=IFERROR(INDEX(All_User!D:D,MATCH(B44,All_User!B:B,0)),"없음")} -> jinny.park@stryker.com | D44: {=IFERROR(INDEX(All_User!H:H,MATCH(C44,All_User!D:D,0)),"없음")} -> 5CD5062YDX
... B54: Jaehee Seo | C54: {=IFERROR(INDEX(All_User!D:D,MATCH(B54,All_User!B:B,0)),"없음")} -> jaehee.seo@stryker.com | D54: {=IFERROR(INDEX(All_User!H:H,MATCH(C54,All_User!D:D,0)),"없음")} -> 5CD5179KH0
B55: SeoYeon Hong | C55: seoyeong.hong@stryker.com | D55: {=IFERROR(INDEX(All_User!H:H,MATCH(C55,All_User!D:D,0)),"없음")} -> 5CD4305D8H
B56: James Kang | C56: {=IFERROR(INDEX(All_User!D:D,MATCH(B56,All_User!B:B,0)),"없음")} -> James.Kang@stryker.com | D56: {=IFERROR(INDEX(All_User!H:H,MATCH(C56,All_User!D:D,0)),"없음")} -> 5CD5179KJ2
B57: Rayna Kim | C57: {=IFERROR(INDEX(All_User!D:D,MATCH(B57,All_User!B:B,0)),"없음")} -> Rayna.Kim@stryker.com | D57: {=IFERROR(INDEX(All_User!H:H,MATCH(C57,All_User!D:D,0)),"없음")} -> 5CD5179KJB
B58: Henry Lee | C58: {=IFERROR(INDEX(All_User!D:D,MATCH(B58,All_User!B:B,0)),"없음")} -> henry.lee@stryker.com | D58: {=IFERROR(INDEX(All_User!H:H,MATCH(C58,All_User!D:D,0)),"없음")} -> 5CD5179KH2
B59: Andrew Ahn | C59: {=IFERROR(INDEX(All_User!D:D,MATCH(B59,All_User!B:B,0)),"없음")} -> andrew.ahn@stryker.com | D59: {=IFERROR(INDEX(All_User!H:H,MATCH(C59,All_User!D:D,0)),"없음")} -> 5CD5179KJ6

Sheet sales
A1: Workday ID | B1: Preferred Name | C1: email | D1: BU | E1: Category 1 | F1: Job Title | G1: 프린터정보 | H1: IPAD | I1: 확인
A2: 1478259 | B2: Willy Chang （장훈） | C2: Willy.Chang@stryker.com | D2: Mako | E2: Sales | F2: Mako Account Manager | G2: {=IFERROR(INDEX(Printer!D:D,MATCH(C2,Printer!H:H,0)),"list 없음")} -> SL-C565FW | H2: {=IFERROR(INDEX(Ipad_List!C:C,MATCH(C2,Ipad_List!J:J,0)),"없음")} -> Q4VMC2579N | I2: 완료 | J2: {=IFERROR(INDEX(All_User!D:D,MATCH(C2,All_User!D:D,0)),"list없음")} -> Willy.Chang@stryker.com
A3: 1496493 | B3: David Yang （양승현） | C3: David.Yang@stryker.com | D3: Mako | E3: Sales | F3: Mako Account Manager | G3: {=IFERROR(INDEX(Printer!D:D,MATCH(C3,Printer!H:H,0)),"list 없음")} -> SL-C483FW | H3: {=IFERROR(INDEX(Ipad_List!C:C,MATCH(C3,Ipad_List!J:J,0)),"없음")} -> T32JYKMQQF | I3: 완료 | J3: {=IFERROR(INDEX(All_User!D:D,MATCH(C3,All_User!D:D,0)),"list없음")} -> David.Yang@stryker.com
A4: 2483496 | B4: Mi Na Song （송미나） | C4: mina.song@stryker.com | D4: NV | E4: NV | F4: Senior Business Manager, Neurovascular, Korea | G4: {=IFERROR(INDEX(Printer!D:D,MATCH(C4,Printer!H:H,0)),"list 없음")} -> list 없음 | H4: {=IFERROR(INDEX(Ipad_List!C:C,MATCH(C4,Ipad_List!J:J,0)),"없음")} -> C2QFHGVW92 | I4: 완료 | J4: {=IFERROR(INDEX(All_User!D:D,MATCH(C4,All_User!D:D,0)),"list없음")} -> mina.song@stryker.com
A5: 2483498 | B5: DJ Ahn （안동준） | C5: dj.ahn@stryker.com | D5: NV | E5: NV | F5: Sales Manager, Neurovascular | G5: {=IFERROR(INDEX(Printer!D:D,MATCH(C5,Printer!H:H,0)),"list 없음")} -> SL-C563W | H5: {=IFERROR(INDEX(Ipad_List!C:C,MATCH(C5,Ipad_List!J:J,0)),"없음")} -> QWG7C19T9N | I5: 완료 | J5: {=IFERROR(INDEX(All_User!D:D,MATCH(C5,All_User!D:D,0)),"list없음")} -> dj.ahn@stryker.com
A6: 2636418 | B6: Nathan Eom （엄태영） | C6: Nathan.Eom@stryker.com | D6: MedSurg | E6: Sales | F6: Sales Manager | G6: {=IFERROR(INDEX(Printer!D:D,MATCH(C6,Printer!H:H,0)),"list 없음")} -> SL-C486FW | H6: {=IFERROR(INDEX(Ipad_List!C:C,MATCH(C6,Ipad_List!J:J,0)),"없음")} -> GW245H3KYL | I6: 완료 | J6: {=IFERROR(INDEX(All_User!D:D,MATCH(C6,All_User!D:D,0)),"list없음")} -> Nathan.Eom@stryker.com
A7: 3172504 | B7: Bruce Cha （차철민） | C7: Bruce.Cha@stryker.com | D7: Mako | E7: Sales | F7: Mako Account Manager | G7: {=IFERROR(INDEX(Printer!D:D,MATCH(C7,Printer!H:H,0)),"list 없음")} -> SL-C563W | H7: {=IFERROR(INDEX(Ipad_List!C:C,MATCH(C7,Ipad_List!J:J,0)),"없음")} -> LXDC4F97QM | I7: 완료 | J7: {=IFERROR(INDEX(All_User!D:D,MATCH(C7,All_User!D:D,0)),"list없음")} -> Bruce.Cha@stryker.com
A8: 3217714 | B8: Danny Kim （김문호） | C8: danny.kim@stryker.com | D8: MedSurg | E8: Sales | F8: Sales Manager | G8: {=IFERROR(INDEX(Printer!D:D,MATCH(C8,Printer!H:H,0)),"list 없음")} -> SL-C563W | H8: {=IFERROR(INDEX(Ipad_List!C:C,MATCH(C8,Ipad_List!J:J,0)),"없음")} -> DWFLMWX243 | I8: 완료 | J8: {=IFERROR(INDEX(All_User!D:D,MATCH(C8,All_User!D:D,0)),"list없음")} -> danny.kim@stryker.com
A9: 3255182 | B9: Simon Sin （신정헌） | C9: Simon.sin@stryker.com | D9: MedSurg | E9: Sales | F9: Sales Manager | G9: {=IFERROR(INDEX(Printer!D:D,MATCH(C9,Printer!H:H,0)),"list 없음")} -> SL-C486FW | H9: {=IFERROR(INDEX(Ipad_List!C:C,MATCH(C9,Ipad_List!J:J,0)),"없음")} -> FWJG39XV9Q | I9: 완료 | J9: {=IFERROR(INDEX(All_User!D:D,MATCH(C9,All_User!D:D,0)),"list없음")} -> Simon.sin@stryker.com
A10: 3267620 | B10: Suhyun Kim （김수현） | C10: Suhyun.Kim@stryker.com | D10: Implants | E10: Sales | F10: Associate Sales Manager | G10: {=IFERROR(INDEX(Printer!D:D,MATCH(C10,Printer!H:H,0)),"list 없음")} -> SL-C486FW | H10: {=IFERROR(INDEX(Ipad_List!C:C,MATCH(C10,Ipad_List!J:J,0)),"없음")} -> MQ6X021QX2 | I10: 완료 | J10: {=IFERROR(INDEX(All_User!D:D,MATCH(C10,All_User!D:D,0)),"list없음")} -> Suhyun.Kim@stryker.com
A11: 6465818 | B11: Tyler Park （박래수） | C11: tyler.park@stryker.com | D11: NV | E11: NV | F11: Associate Sales Manager, Neurovascular | G11: {=IFERROR(INDEX(Printer!D:D,MATCH(C11,Printer!H:H,0)),"list 없음")} -> 반납 | H11: {=IFERROR(INDEX(Ipad_List!C:C,MATCH(C11,Ipad_List!J:J,0)),"없음")} -> VCF25MJ6YY | I11: 완료 | J11: {=IFERROR(INDEX(All_User!D:D,MATCH(C11,All_User!D:D,0)),"list없음")} -> tyler.park@stryker.com
A12: 6701810 | B12: Joy Lee （이윤선） | C12: joy.lee@stryker.com | D12: MedSurg | E12: Sales | F12: Lead Sales Representative | G12: {=IFERROR(INDEX(Printer!D:D,MATCH(C12,Printer!H:H,0)),"list 없음")} -> SL-C563W | H12: {=IFERROR(INDEX(Ipad_List!C:C,MATCH(C12,Ipad_List!J:J,0)),"없음")} -> KXDGGF9C90 | I12: 완료 | J12: {=IFERROR(INDEX(All_User!D:D,MATCH(C12,All_User!D:D,0)),"list없음")} -> joy.lee@stryker.com
A13: 2476410 | B13: Justin Kim （김정오） | C13: Justin.Kim@stryker.com | D13: Mako | E13: Sales | F13: Mako Capital Sales Manager | G13: {=IFERROR(INDEX(Printer!D:D,MATCH(C13,Printer!H:H,0)),"list 없음")} -> SL-C565W | H13: {=IFERROR(INDEX(Ipad_List!C:C,MATCH(C13,Ipad_List!J:J,0)),"없음")} -> THD6Q4W3LT | I13: 완료 | J13: {=IFERROR(INDEX(All_User!D:D,MATCH(C13,All_User!D:D,0)),"list없음")} -> Justin.Kim@stryker.com
... A79: 1029907 | B79: Bryan Park （박효현） | C79: bryan.park@stryker.com | D79: Mako | E79: MPS | F79: Mako Product Specialist | G79: {=IFERROR(INDEX(Printer!D:D,MATCH(C79,Printer!H:H,0)),"list 없음")} -> list 없음 | H79: {=IFERROR(INDEX(Ipad_List!C:C,MATCH(C79,Ipad_List!J:J,0)),"없음")} -> WR34FVRW4C | I79: 완료 | J79: {=IFERROR(INDEX(All_User!D:D,MATCH(C79,All_User!D:D,0)),"list없음")} -> bryan.park@stryker.com
B80: Bella Yoon | C80: bella.yoon@stryker.com | E80: MKT | G80: {=IFERROR(INDEX(Printer!D:D,MATCH(C80,Printer!H:H,0)),"list 없음")} -> list 없음 | H80: {=IFERROR(INDEX(Ipad_List!C:C,MATCH(C80,Ipad_List!J:J,0)),"없음")} -> D50QVTWX76 | I80: 완료 | J80: {=IFERROR(INDEX(All_User!D:D,MATCH(C80,All_User!D:D,0)),"list없음")} -> bella.yoon@stryker.com
B81: Gregory Seo | C81: Gregory.Seo@stryker.com | E81: Sales | G81: {=IFERROR(INDEX(Printer!D:D,MATCH(C81,Printer!H:H,0)),"list 없음")} -> SL-C563W | H81: {=IFERROR(INDEX(Ipad_List!C:C,MATCH(C81,Ipad_List!J:J,0)),"없음")} -> KJ44CP93XQ | I81: 완료 | J81: {=IFERROR(INDEX(All_User!D:D,MATCH(C81,All_User!D:D,0)),"list없음")} -> Gregory.Seo@stryker.com
B82: Jenny Jung | C82: jenny.jung@stryker.com | E82: MKT | G82: {=IFERROR(INDEX(Printer!D:D,MATCH(C82,Printer!H:H,0)),"list 없음")} -> list 없음 | H82: {=IFERROR(INDEX(Ipad_List!C:C,MATCH(C82,Ipad_List!J:J,0)),"없음")} -> DG3XL2W5VX | J82: {=IFERROR(INDEX(All_User!D:D,MATCH(C82,All_User!D:D,0)),"list없음")} -> jenny.jung@stryker.com
B83: Owen Park | C83: owen.park@stryker.com | E83: TS | G83: {=IFERROR(INDEX(Printer!D:D,MATCH(C83,Printer!H:H,0)),"list 없음")} -> list 없음 | H83: {=IFERROR(INDEX(Ipad_List!C:C,MATCH(C83,Ipad_List!J:J,0)),"없음")} -> DP77MWKXNR | I83: 완료 | J83: {=IFERROR(INDEX(All_User!D:D,MATCH(C83,All_User!D:D,0)),"list없음")} -> owen.park@stryker.com
B84: Rosie Lee | C84: rosie.lee@stryker.com | E84: MKT | G84: {=IFERROR(INDEX(Printer!D:D,MATCH(C84,Printer!H:H,0)),"list 없음")} -> list 없음 | H84: {=IFERROR(INDEX(Ipad_List!C:C,MATCH(C84,Ipad_List!J:J,0)),"없음")} -> GWR3CYT2GJ | I84: 완료 | J84: {=IFERROR(INDEX(All_User!D:D,MATCH(C84,All_User!D:D,0)),"list없음")} -> rosie.lee@stryker.com
B85: Sarah Youn | C85: sarah.youn@stryker.com | E85: MKT | G85: {=IFERROR(INDEX(Printer!D:D,MATCH(C85,Printer!H:H,0)),"list 없음")} -> list 없음 | H85: {=IFERROR(INDEX(Ipad_List!C:C,MATCH(C85,Ipad_List!J:J,0)),"없음")} -> HYC714DK25 | J85: {=IFERROR(INDEX(All_User!D:D,MATCH(C85,All_User!D:D,0)),"list없음")} -> sarah.youn@stryker.com
B86: Yoonbee Jeong | C86: yoonbee.jeong@stryker.com | E86: Sales | G86: {=IFERROR(INDEX(Printer!D:D,MATCH(C86,Printer!H:H,0)),"list 없음")} -> SL-C563W | H86: {=IFERROR(INDEX(Ipad_List!C:C,MATCH(C86,Ipad_List!J:J,0)),"없음")} -> M2FKP9T7QX | I86: 완료 | J86: {=IFERROR(INDEX(All_User!D:D,MATCH(C86,All_User!D:D,0)),"list없음")} -> yoonbee.jeong@stryker.com
B87: Jackson Kim | C87: jackson.kim@stryker.com | E87: Sales | G87: {=IFERROR(INDEX(Printer!D:D,MATCH(C87,Printer!H:H,0)),"list 없음")} -> 확인중 | H87: {=IFERROR(INDEX(Ipad_List!C:C,MATCH(C87,Ipad_List!J:J,0)),"없음")} -> MK21Q5L65C | J87: {=IFERROR(INDEX(All_User!D:D,MATCH(C87,All_User!D:D,0)),"list없음")} -> jackson.kim@stryker.com
B88: Rayna Kim | C88: Rayna.Kim@stryker.com | E88: MKT | G88: {=IFERROR(INDEX(Printer!D:D,MATCH(C88,Printer!H:H,0)),"list 없음")} -> list 없음 | H88: {=IFERROR(INDEX(Ipad_List!C:C,MATCH(C88,Ipad_List!J:J,0)),"없음")} -> FQPW2GVP7C | I88: 완료 | J88: {=IFERROR(INDEX(All_User!D:D,MATCH(C88,All_User!D:D,0)),"list없음")} -> Rayna.Kim@stryker.com
B89: Jay Ji | C89: jay.ji@stryker.com | E89: Sales | G89: {=IFERROR(INDEX(Printer!D:D,MATCH(C89,Printer!H:H,0)),"list 없음")} -> list 없음 | H89: {=IFERROR(INDEX(Ipad_List!C:C,MATCH(C89,Ipad_List!J:J,0)),"없음")} -> GGWR7NXY2D | I89: 완료 | J89: {=IFERROR(INDEX(All_User!D:D,MATCH(C89,All_User!D:D,0)),"list없음")} -> jay.ji@stryker.com
B90: Andrew Ahn | C90: andrew.ahn@stryker.com | E90: TS | G90: {=IFERROR(INDEX(Printer!D:D,MATCH(C90,Printer!H:H,0)),"list 없음")} -> list 없음 | H90: {=IFERROR(INDEX(Ipad_List!C:C,MATCH(C90,Ipad_List!J:J,0)),"없음")} -> C4RQH3W74V | I90: 완료 | J90: {=IFERROR(INDEX(All_User!D:D,MATCH(C90,All_User!D:D,0)),"list없음")} -> andrew.ahn@stryker.com
B91: Yeonjoo Kim | C91: yeonjoo.kim@stryker.com | E91: MKT | G91: {=IFERROR(INDEX(Printer!D:D,MATCH(C91,Printer!H:H,0)),"list 없음")} -> SL-C563W | H91: {=IFERROR(INDEX(Ipad_List!C:C,MATCH(C91,Ipad_List!J:J,0)),"없음")} -> HYFKQFR4RD | I91: 완료 | J91: {=IFERROR(INDEX(All_User!D:D,MATCH(C91,All_User!D:D,0)),"list없음")} -> yeonjoo.kim@stryker.com
B92: Carl Cha | C92: carl.cha@stryker.com | E92: TS | G92: {=IFERROR(INDEX(Printer!D:D,MATCH(C92,Printer!H:H,0)),"list 없음")} -> list 없음 | H92: {=IFERROR(INDEX(Ipad_List!C:C,MATCH(C92,Ipad_List!J:J,0)),"없음")} -> Q4VGFW40QV | J92: {=IFERROR(INDEX(All_User!D:D,MATCH(C92,All_User!D:D,0)),"list없음")} -> carl.cha@stryker.com
B93: Oscar Hwang | C93: oscar.hwang@stryker.com | E93: TS | G93: {=IFERROR(INDEX(Printer!D:D,MATCH(C93,Printer!H:H,0)),"list 없음")} -> 확인중 | H93: {=IFERROR(INDEX(Ipad_List!C:C,MATCH(C93,Ipad_List!J:J,0)),"없음")} -> XYGFK42KQP | J93: {=IFERROR(INDEX(All_User!D:D,MATCH(C93,All_User!D:D,0)),"list없음")} -> oscar.hwang@stryker.com
B94: Minki Kim | C94: minki.kim@stryker.com | E94: MKT | G94: {=IFERROR(INDEX(Printer!D:D,MATCH(C94,Printer!H:H,0)),"list 없음")} -> list 없음 | H94: {=IFERROR(INDEX(Ipad_List!C:C,MATCH(C94,Ipad_List!J:J,0)),"없음")} -> XGH27YLWQM | I94: 완료 | J94: {=IFERROR(INDEX(All_User!D:D,MATCH(C94,All_User!D:D,0)),"list없음")} -> minki.kim@stryker.com
B95: Jayden Song | C95: jayden.song@stryker.com | E95: TS | G95: {=IFERROR(INDEX(Printer!D:D,MATCH(C95,Printer!H:H,0)),"list 없음")} -> list 없음 | H95: {=IFERROR(INDEX(Ipad_List!C:C,MATCH(C95,Ipad_List!J:J,0)),"없음")} -> RVF25297YV | J95: {=IFERROR(INDEX(All_User!D:D,MATCH(C95,All_User!D:D,0)),"list없음")} -> jayden.song@stryker.com
B96: Ian hwang | C96: ian.hwang@stryker.com | E96: Sales | G96: {=IFERROR(INDEX(Printer!D:D,MATCH(C96,Printer!H:H,0)),"list 없음")} -> SL-C563W | H96: {=IFERROR(INDEX(Ipad_List!C:C,MATCH(C96,Ipad_List!J:J,0)),"없음")} -> GHL46K1F9M | J96: {=IFERROR(INDEX(All_User!D:D,MATCH(C96,All_User!D:D,0)),"list없음")} -> ian.hwang@stryker.com
B97: Daniel Lee | C97: daniel.lee1@stryker.com | E97: TS | G97: {=IFERROR(INDEX(Printer!D:D,MATCH(C97,Printer!H:H,0)),"list 없음")} -> SL-C563W | H97: {=IFERROR(INDEX(Ipad_List!C:C,MATCH(C97,Ipad_List!J:J,0)),"없음")} -> FN47DRXYYW | I97: 완료 | J97: {=IFERROR(INDEX(All_User!D:D,MATCH(C97,All_User!D:D,0)),"list없음")} -> daniel.lee1@stryker.com
B98: Huey Sim | C98: Huey.Sim@stryker.com | E98: TS | G98: {=IFERROR(INDEX(Printer!D:D,MATCH(C98,Printer!H:H,0)),"list 없음")} -> SL-C563W | H98: {=IFERROR(INDEX(Ipad_List!C:C,MATCH(C98,Ipad_List!J:J,0)),"없음")} -> RFJJ97J4YG | I98: 완료 | J98: {=IFERROR(INDEX(All_User!D:D,MATCH(C98,All_User!D:D,0)),"list없음")} -> Huey.Sim@stryker.com
B99: Jaewook Chung | C99: jae.chung@stryker.com | E99: MKT | G99: {=IFERROR(INDEX(Printer!D:D,MATCH(C99,Printer!H:H,0)),"list 없음")} -> SL-C483W | H99: {=IFERROR(INDEX(Ipad_List!C:C,MATCH(C99,Ipad_List!J:J,0)),"없음")} -> GMF3VLXNKG | I99: 완료 | J99: {=IFERROR(INDEX(All_User!D:D,MATCH(C99,All_User!D:D,0)),"list없음")} -> jae.chung@stryker.com
B100: Julie Park | C100: julie.park@stryker.com | E100: MKT | G100: {=IFERROR(INDEX(Printer!D:D,MATCH(C100,Printer!H:H,0)),"list 없음")} -> list 없음 | H100: {=IFERROR(INDEX(Ipad_List!C:C,MATCH(C100,Ipad_List!J:J,0)),"없음")} -> TK79FYYWPV | I100: 완료 | J100: {=IFERROR(INDEX(All_User!D:D,MATCH(C100,All_User!D:D,0)),"list없음")} -> julie.park@stryker.com
B101: David Lee | C101: david.lee4@stryker.com | E101: TS | G101: {=IFERROR(INDEX(Printer!D:D,MATCH(C101,Printer!H:H,0)),"list 없음")} -> SL-C563W | H101: {=IFERROR(INDEX(Ipad_List!C:C,MATCH(C101,Ipad_List!J:J,0)),"없음")} -> Q0C6LC7F3X | I101: 완료 | J101: {=IFERROR(INDEX(All_User!D:D,MATCH(C101,All_User!D:D,0)),"list없음")} -> david.lee4@stryker.com
B102: Ethan Jang | C102: ethan.jang@stryker.com | E102: TS | G102: {=IFERROR(INDEX(Printer!D:D,MATCH(C102,Printer!H:H,0)),"list 없음")} -> list 없음 | H102: {=IFERROR(INDEX(Ipad_List!C:C,MATCH(C102,Ipad_List!J:J,0)),"없음")} -> G7CV2M99YM | I102: 완료 | J102: {=IFERROR(INDEX(All_User!D:D,MATCH(C102,All_User!D:D,0)),"list없음")} -> ethan.jang@stryker.com
B103: Oh Peter | C103: peter.oh@stryker.com | D103: Implate | E103: Sales | F103: BU Director, Implants | G103: {=IFERROR(INDEX(Printer!D:D,MATCH(C103,Printer!H:H,0)),"list 없음")} -> list 없음 | H103: {=IFERROR(INDEX(Ipad_List!C:C,MATCH(C103,Ipad_List!J:J,0)),"없음")} -> MP2C9F46FN | I103: 완료 | J103: {=IFERROR(INDEX(All_User!D:D,MATCH(C103,All_User!D:D,0)),"list없음")} -> peter.oh@stryker.com
B104: Park JY | C104: jy.park@stryker.com | D104: Mako | E104: Sales | F104: Senior Business Operation Specialist | G104: {=IFERROR(INDEX(Printer!D:D,MATCH(C104,Printer!H:H,0)),"list 없음")} -> list 없음 | H104: {=IFERROR(INDEX(Ipad_List!C:C,MATCH(C104,Ipad_List!J:J,0)),"없음")} -> 없음
B105: Joon Oh | C105: joon.oh@stryker.com | E105: MKT | G105: {=IFERROR(INDEX(Printer!D:D,MATCH(C105,Printer!H:H,0)),"list 없음")} -> list 없음 | H105: {=IFERROR(INDEX(Ipad_List!C:C,MATCH(C105,Ipad_List!J:J,0)),"없음")} -> 없음
C106: Jeff.Lee@stryker.com | G106: {=IFERROR(INDEX(Printer!D:D,MATCH(C106,Printer!H:H,0)),"list 없음")} -> 확인중 | H106: {=IFERROR(INDEX(Ipad_List!C:C,MATCH(C106,Ipad_List!J:J,0)),"없음")} -> M7WVNHQ0YQ | J106: {=IFERROR(INDEX(All_User!D:D,MATCH(C106,All_User!D:D,0)),"list없음")} -> Jeff.Lee@stryker.com
C107: gd.ahn@stryker.com | G107: {=IFERROR(INDEX(Printer!D:D,MATCH(C107,Printer!H:H,0)),"list 없음")} -> 확인중 | H107: {=IFERROR(INDEX(Ipad_List!C:C,MATCH(C107,Ipad_List!J:J,0)),"없음")} -> L69V0Q1VT3 | J107: {=IFERROR(INDEX(All_User!D:D,MATCH(C107,All_User!D:D,0)),"list없음")} -> gd.ahn@stryker.com
C108: roy.choi@stryker.com | G108: {=IFERROR(INDEX(Printer!D:D,MATCH(C108,Printer!H:H,0)),"list 없음")} -> 폐기 | H108: {=IFERROR(INDEX(Ipad_List!C:C,MATCH(C108,Ipad_List!J:J,0)),"없음")} -> LD0W924NX3 | J108: {=IFERROR(INDEX(All_User!D:D,MATCH(C108,All_User!D:D,0)),"list없음")} -> roy.choi@stryker.com
C109: Sue.Kim@stryker.com | G109: {=IFERROR(INDEX(Printer!D:D,MATCH(C109,Printer!H:H,0)),"list 없음")} -> 확인중 | H109: {=IFERROR(INDEX(Ipad_List!C:C,MATCH(C109,Ipad_List!J:J,0)),"없음")} -> DDPWWYNVPX | J109: {=IFERROR(INDEX(All_User!D:D,MATCH(C109,All_User!D:D,0)),"list없음")} -> Sue.Kim@stryker.com
C110: junghoon.seo@stryker.com | G110: {=IFERROR(INDEX(Printer!D:D,MATCH(C110,Printer!H:H,0)),"list 없음")} -> 확인중 | H110: {=IFERROR(INDEX(Ipad_List!C:C,MATCH(C110,Ipad_List!J:J,0)),"없음")} -> 없음 | J110: {=IFERROR(INDEX(All_User!D:D,MATCH(C110,All_User!D:D,0)),"list없음")} -> junghoon.seo@stryker.com
C111: 기술부1 | G111: {=IFERROR(INDEX(Printer!D:D,MATCH(C111,Printer!H:H,0)),"list 없음")} -> SL-C486FW | H111: {=IFERROR(INDEX(Ipad_List!C:C,MATCH(C111,Ipad_List!J:J,0)),"없음")} -> 없음 | I111: 완료
C112: 기술부2 | G112: {=IFERROR(INDEX(Printer!D:D,MATCH(C112,Printer!H:H,0)),"list 없음")} -> SL-C563W | H112: {=IFERROR(INDEX(Ipad_List!C:C,MATCH(C112,Ipad_List!J:J,0)),"없음")} -> 없음 | I112: 완료
C113: 기술부3 | G113: {=IFERROR(INDEX(Printer!D:D,MATCH(C113,Printer!H:H,0)),"list 없음")} -> SL-C483FW | H113: {=IFERROR(INDEX(Ipad_List!C:C,MATCH(C113,Ipad_List!J:J,0)),"없음")} -> 없음 | I113: 완료

Sheet 퇴사자
A1: 월 | B1: 날짜 | C1: NAME | D1: email | E1: 설명 | F1: BU | G1: 노트북 | H1: 아이패드 | I1: 모니터 | J1: 복합기 | K1: Teams | L1: 추가사항
A2: 0 | B2: 0 | C2: kale.lee | D2: kale.lee@stryker.com | E2: 샘플 삭제 금지 | G2: {=IFERROR(INDEX(All_User!H:H,MATCH(D2,All_User!D:D,0)),"반납완료")} -> 5CD3469HCZ | H2: {=IFERROR(INDEX(All_User!K:K,MATCH(D2,All_User!D:D,0)),"없음")} -> J1XWPW66YY | I2: {=IFERROR(INDEX(All_User!N:N,MATCH(D2,All_User!D:D,0)),"없음")} -> 없음 | J2: {=IFERROR(INDEX(All_User!M:M,MATCH(D2,All_User!D:D,0)),"없음")} -> 없음 | K2: {=IFERROR(INDEX(All_User!L:L,MATCH(D2,All_User!D:D,0)),"없음")} -> tel:+82234517681
A3: 4 | B3: 30 | C3: Yeji Lee | D3: yeji.lee@stryker.com | E3: 퇴사자 | F3: Mako | G3: {=IFERROR(INDEX(All_User!H:H,MATCH(D3,All_User!D:D,0)),"반납완료")} -> 반납완료 | H3: 반납완료 | I3: 없음 | J3: 없음 | K3: {=IFERROR(INDEX(All_User!L:L,MATCH(D3,All_User!D:D,0)),"없음")} -> 없음 | L3: Dell 반납
A4: 4 | B4: 30 | C4: Hyeonjin YU | D4: hyeonjin.yoo@stryker.com | E4: 퇴사자 | F4: Mako | G4: {=IFERROR(INDEX(All_User!H:H,MATCH(D4,All_User!D:D,0)),"반납완료")} -> 반납완료 | H4: 반납완료 | I4: 없음 | J4: 없음 | K4: {=IFERROR(INDEX(All_User!L:L,MATCH(D4,All_User!D:D,0)),"없음")} -> 없음
A5: 5 | B5: 2 | C5: Inyoung Baek | D5: inyoung.baek@stryker.com | E5: 퇴사자 | F5: Mako | G5: {=IFERROR(INDEX(All_User!H:H,MATCH(D5,All_User!D:D,0)),"반납완료")} -> 반납완료 | H5: 없음 | I5: 없음 | J5: 없음 | K5: {=IFERROR(INDEX(All_User!L:L,MATCH(D5,All_User!D:D,0)),"없음")} -> 없음
A6: 5 | B6: 7 | C6: Hailey Na | D6: hailey.na@stryker.com | E6: 퇴사자 | F6: Medsurg | G6: {=IFERROR(INDEX(All_User!H:H,MATCH(D6,All_User!D:D,0)),"반납완료")} -> 반납완료 | H6: 없음 | I6: 없음 | J6: 없음 | K6: {=IFERROR(INDEX(All_User!L:L,MATCH(D6,All_User!D:D,0)),"없음")} -> 없음
A7: 4 | B7: 18 | C7: Seyeon Choi | D7: seyeon.choi@stryker.com | E7: 퇴사자 | F7: HR | G7: {=IFERROR(INDEX(All_User!H:H,MATCH(D7,All_User!D:D,0)),"반납완료")} -> 반납완료 | H7: 없음 | I7: 없음 | J7: 없음 | K7: {=IFERROR(INDEX(All_User!L:L,MATCH(D7,All_User!D:D,0)),"없음")} -> 없음
A8: 4 | B8: 30 | C8: Dawn Lim | D8: dawn.lim@stryker.com | E8: 퇴사자 | F8: Shoulder | G8: {=IFERROR(INDEX(All_User!H:H,MATCH(D8,All_User!D:D,0)),"반납완료")} -> 반납완료 | H8: 반납완료 | I8: 없음 | J8: 없음 | K8: {=IFERROR(INDEX(All_User!L:L,MATCH(D8,All_User!D:D,0)),"없음")} -> 없음 | L8: 복합기, 모니터 반납완료
A9: 6 | B9: 6 | C9: Kim, Dohyeon | D9: dohyeon.kim@stryker.com | E9: 퇴사자 | F9: Mako | G9: {=IFERROR(INDEX(All_User!H:H,MATCH(D9,All_User!D:D,0)),"반납완료")} -> 반납완료 | H9: 반납완료 | I9: 없음 | J9: 없음 | K9: {=IFERROR(INDEX(All_User!L:L,MATCH(D9,All_User!D:D,0)),"없음")} -> 없음
A10: 6 | B10: 4 | C10: Mo Yunju | D10: yunju.mo@stryker.com | E10: 퇴사자 | F10: Planning | G10: {=IFERROR(INDEX(All_User!H:H,MATCH(D10,All_User!D:D,0)),"반납완료")} -> 반납완료 | H10: 없음 | I10: 없음 | J10: 없음 | K10: {=IFERROR(INDEX(All_User!L:L,MATCH(D10,All_User!D:D,0)),"없음")} -> 없음
A11: 6 | B11: 30 | C11: Stacy Im | D11: stacy.im@stryker.com | E11: 퇴사자 | F11: ICM | G11: {=IFERROR(INDEX(All_User!H:H,MATCH(D11,All_User!D:D,0)),"반납완료")} -> 반납완료 | H11: 없음 | I11: 없음 | J11: 없음 | K11: {=IFERROR(INDEX(All_User!L:L,MATCH(D11,All_User!D:D,0)),"없음")} -> 없음
A12: 7 | B12: 7 | C12: Lucy Han | D12: lucy.han@stryker.com | E12: 퇴사자 | F12: Planning | G12: {=IFERROR(INDEX(All_User!H:H,MATCH(D12,All_User!D:D,0)),"반납완료")} -> 반납완료 | H12: 없음 | I12: 반납완료 | J12: 없음 | K12: {=IFERROR(INDEX(All_User!L:L,MATCH(D12,All_User!D:D,0)),"없음")} -> 없음 | L12: 모니터 반납 완료 | M12: < 여기까지 지문, 복합기 삭제 완료
A13: 8 | B13: 22 | C13: Jayoung Kim | D13: jayoung.kim@stryker.com | E13: 퇴사자 | F13: Legal | G13: {=IFERROR(INDEX(All_User!H:H,MATCH(D13,All_User!D:D,0)),"반납완료")} -> 반납완료 | H13: 반납완료 | I13: 없음 | J13: 없음 | K13: {=IFERROR(INDEX(All_User!L:L,MATCH(D13,All_User!D:D,0)),"없음")} -> 없음
A14: 8 | B14: 18 | C14: Harim Shin | D14: harim.shin@stryker.com | E14: 퇴사자 | F14: Medsurg | G14: {=IFERROR(INDEX(All_User!H:H,MATCH(D14,All_User!D:D,0)),"반납완료")} -> 반납완료 | H14: 없음 | I14: 없음 | J14: 없음 | K14: {=IFERROR(INDEX(All_User!L:L,MATCH(D14,All_User!D:D,0)),"없음")} -> 없음
A15: 8 | B15: 25 | C15: Yulie Choi | D15: yulie.choi@stryker.com | E15: 퇴사자 | F15: Planning | G15: {=IFERROR(INDEX(All_User!H:H,MATCH(D15,All_User!D:D,0)),"반납완료")} -> 반납완료 | H15: 없음 | I15: 없음 | J15: 없음 | K15: 없음
A16: 8 | B16: 31 | C16: Tony Kang | D16: tony.kang@stryker.com | E16: 퇴사자 | F16: MAKO | G16: {=IFERROR(INDEX(All_User!H:H,MATCH(D16,All_User!D:D,0)),"반납완료")} -> 반납완료 | H16: 없음 | I16: 없음 | J16: 반납 | K16: {=IFERROR(INDEX(All_User!L:L,MATCH(D16,All_User!D:D,0)),"없음")} -> 없음 | L16: 복합기 반납완료
A17: 8 | B17: 31 | C17: Elin Kim | D17: elin.kim@stryker.com | E17: 퇴사자 | F17: Knee | G17: {=IFERROR(INDEX(All_User!H:H,MATCH(D17,All_User!D:D,0)),"반납완료")} -> 반납완료 | H17: 반납완료 | I17: 없음 | J17: 없음 | K17: 없음 | L17: 아이패드 반납완료
A18: 8 | B18: 31 | C18: William Chai | D18: chai.william@stryker.com | E18: 퇴사자 | F18: Shoulder | G18: {=IFERROR(INDEX(All_User!H:H,MATCH(D18,All_User!D:D,0)),"반납완료")} -> 반납완료 | H18: 없음 | I18: 없음 | J18: 없음 | K18: 없음 | L18: 아이패드, 복합기 반납완료
A19: 8 | B19: 31 | C19: Donna Park | D19: donna.park@stryker.com | E19: 퇴사자 | F19: Operations | G19: {=IFERROR(INDEX(All_User!H:H,MATCH(D19,All_User!D:D,0)),"반납완료")} -> 반납완료 | H19: 없음 | I19: 없음 | J19: 없음 | K19: 없음
A20: 9 | B20: 10 | C20: Julie Son | D20: julie.son@stryker.com | E20: 퇴사자 | F20: RAQA | G20: {=IFERROR(INDEX(All_User!H:H,MATCH(D20,All_User!D:D,0)),"반납완료")} -> 반납완료 | H20: 없음 | I20: 반납완료 | J20: 없음 | K20: 없음 | L20: 모니터 반납 완료
A21: 9 | B21: 30 | C21: Jayden Shin | D21: jayden.shin@stryker.com | E21: 퇴사자 | F21: Medsurg | G21: {=IFERROR(INDEX(All_User!H:H,MATCH(D21,All_User!D:D,0)),"반납완료")} -> 반납완료 | H21: 없음 | I21: 반납완료 | J21: 폐기함 | K21: {=IFERROR(INDEX(TeamsNumber!C:C,MATCH(D21,TeamsNumber!D:D,0)),"없음")} -> 없음 | L21: 복합기는 사용 7년 폐기함
A22: 9 | B22: 26 | C22: Yoojin.Shin | D22: shin.yoojin@stryker.com | E22: 퇴사자 | F22: Medsurg | G22: {=IFERROR(INDEX(All_User!H:H,MATCH(D22,All_User!D:D,0)),"반납완료")} -> 반납완료 | H22: 없음 | I22: 없음 | J22: 없음 | K22: 없음
A23: 11 | B23: 30 | C23: Johnny Choi | D23: johnny.choi@stryker.com | E23: 퇴사자 | F23: Medsurg | G23: {=IFERROR(INDEX(All_User!H:H,MATCH(D23,All_User!D:D,0)),"반납완료")} -> 반납완료 | H23: 반납완료 | I23: 없음 | J23: 없음 | K23: {=IFERROR(INDEX(TeamsNumber!C:C,MATCH(D23,TeamsNumber!D:D,0)),"없음")} -> 없음 | L23: 아이패드반납완료/복합기 없다고함
A24: 10 | B24: 31 | C24: Kang Jihee | D24: jihee.kang@stryker.com | E24: 퇴사자 | F24: MAKO | G24: {=IFERROR(INDEX(All_User!H:H,MATCH(D24,All_User!D:D,0)),"반납완료")} -> 반납완료 | H24: 없음 | I24: 없음 | J24: 없음 | K24: {=IFERROR(INDEX(TeamsNumber!C:C,MATCH(D24,TeamsNumber!D:D,0)),"없음")} -> 없음
A25: 11 | B25: 12 | C25: Soyeon Park | D25: soyeon.park@stryker.com | E25: 퇴사자 | F25: MAKO | G25: {=IFERROR(INDEX(All_User!H:H,MATCH(D25,All_User!D:D,0)),"반납완료")} -> 5CD5179KJ0 | H25: {=IFERROR(INDEX(All_User!K:K,MATCH(D25,All_User!D:D,0)),"없음")} -> 없음 | I25: 반납완료 | J25: 없음 | K25: {=IFERROR(INDEX(All_User!L:L,MATCH(D25,All_User!D:D,0)),"없음")} -> 없음
A26: 12 | B26: 12 | C26: James Kang | D26: james.kang@stryker.com | E26: 퇴사자 | F26: ICM | G26: {=IFERROR(INDEX(All_User!H:H,MATCH(D26,All_User!D:D,0)),"반납완료")} -> 5CD5179KJ2 | H26: {=IFERROR(INDEX(All_User!K:K,MATCH(D26,All_User!D:D,0)),"없음")} -> VKGPQR7276 | I26: {=IFERROR(INDEX(All_User!N:N,MATCH(D26,All_User!D:D,0)),"없음")} -> LCD 모니터 | J26: {=IFERROR(INDEX(All_User!M:M,MATCH(D26,All_User!D:D,0)),"없음")} -> 없음 | K26: {=IFERROR(INDEX(All_User!L:L,MATCH(D26,All_User!D:D,0)),"없음")} -> tel:+82234517570 | L26: 아이패드반납완료/복합기 없다고함
A27: 11 | B27: 30 | C27: Minjeon Kim | D27: minjeong.kim@stryker.com | E27: 퇴사자 | F27: Mako | G27: {=IFERROR(INDEX(All_User!H:H,MATCH(D27,All_User!D:D,0)),"반납완료")} -> 5CD442C075 | H27: {=IFERROR(INDEX(All_User!K:K,MATCH(D27,All_User!D:D,0)),"없음")} -> K9NWHMWT44 | I27: {=IFERROR(INDEX(All_User!N:N,MATCH(D27,All_User!D:D,0)),"없음")} -> 없음 | J27: {=IFERROR(INDEX(All_User!M:M,MATCH(D27,All_User!D:D,0)),"없음")} -> 없음 | K27: {=IFERROR(INDEX(All_User!L:L,MATCH(D27,All_User!D:D,0)),"없음")} -> tel:+82234517628
A28: 12 | B28: 31 | C28: Clare Yang | D28: clare.yang@stryker.com | E28: 퇴사자 | F28: RAQA | G28: {=IFERROR(INDEX(All_User!H:H,MATCH(D28,All_User!D:D,0)),"반납완료")} -> 5CD4305D82 | H28: {=IFERROR(INDEX(All_User!K:K,MATCH(D28,All_User!D:D,0)),"없음")} -> 없음 | I28: {=IFERROR(INDEX(All_User!N:N,MATCH(D28,All_User!D:D,0)),"없음")} -> 반납완료 | J28: {=IFERROR(INDEX(All_User!M:M,MATCH(D28,All_User!D:D,0)),"없음")} -> 없음 | K28: {=IFERROR(INDEX(All_User!L:L,MATCH(D28,All_User!D:D,0)),"없음")} -> tel:+82234517526

Sheet 퇴사자_임시
A1: 17 | B1: William Chai | C1: 채원병 | D1: william.chai@stryker.com | E1: Sales Manager | F1: Sales and Marketing Job Family Group | G1: Indirect Sales | H1: {=IFERROR(INDEX(Lease_List!D:D,MATCH(All_User!D1,Lease_List!H:H,0)),"없음")} -> S/N | I1: 없음 | K1: {=IFERROR(INDEX(Ipad_List!C:C,MATCH(All_User!D1,Ipad_List!J:J,0)),"없음")} -> S/N | L1: {=IFERROR(INDEX(TeamsNumber!B:B,MATCH(All_User!D1,TeamsNumber!D:D,0)),"없음")} -> LineURI | M1: {=IFERROR(INDEX(Printer!D:D,MATCH(All_User!D1,Printer!H:H,0)),"없음")} -> Additional Information 2 | N1: {=IFERROR(INDEX(sales!D:D,MATCH(D1,sales!C:C,0)),"없음")} -> 없음 | O1: {=IFERROR(INDEX(sales!E:E,MATCH(D1,sales!C:C,0)),"없음")} -> 없음 | Q1: 8/31 퇴사
